Workbook

Sheet Summary
A1: asx-mlx / Summary
A4: ILLUSTRATIVE SENSITIVITY — not an actionable valuation
A7: Active scenario | B7: =Assumptions!B4 -> base
A8: Model value per share | B8: =Valuation!$B$11 -> 0.7871263
A9: Equity value | B9: =Valuation!$B$9 -> 6.9770209e+08
A10: Minimum illustrative cash | B10: =Valuation!$B$12 -> 374000000
A12: Markdown is the main research narrative. Use this workbook to inspect and edit detailed assumptions; recalculate in Excel or LibreOffice, save, then import to publish a validated snapshot back to the research memo.
A16: Known limitations: ILLUSTRATIVE IMPUTED-REVENUE SENSITIVITY ONLY. This is not an actionable fair-value estimate or an investment recommendation. • Production is used solely as the company-style imputed-revenue proxy (100% produced tin sold/paid); it is NOT reported payable sales. The workbook labels it production_tonnes_proxy. Realized payable sales, inventory, settlement timing and revenue must replace this proxy before valuation. See Readme for the full limitations register.

Sheet Assumptions
A1: asx-mlx / Assumptions
A4: Active scenario | B4: base | C4: Blue = editable inputs • Green = cross-sheet links • Black = calculations
A7: Cash | B7: 374000000 | C7: AUD
A8: Debt | B8: 3285000 | C8: AUD
A9: Other Assets | B9: 0 | C9: AUD
A10: Diluted Shares | B10: 886391538 | C10: shares
A11: Reference Price | C11: AUD/share
A12: Valuation Date | B12: 2026-09-20 | C12: YYYY-MM-DD
A13: Quote Date | C13: YYYY-MM-DD
A15: Enter dates as YYYY-MM-DD text. Blank quote and reference price mean no market comparison. Preserve the declared ownership basis; attributable inputs require ownership = 100%.
A19: BEAR / whole_operation
A20: Discount Rate | B20: 0.12
A21: Ownership | B21: 0.5
A22: Residual Value | B22: 0
A23: Explicit forecast periods | B23: 3
C24: 2027 | D24: 2028 | E24: 2029 | F24: 2030 | G24: 2031 | H24: 2032 | I24: 2033
A25: Production proxy (not payable sales) | B25: tonnes | C25: 10158.3 | D25: 10158.3 | E25: 10158.3 | F25: 0 | G25: 0 | H25: 0 | I25: 0
A26: Price | B26: AUD/tonne | C26: 51008 | D26: 51008 | E26: 51008 | F26: 0 | G26: 0 | H26: 0 | I26: 0
A27: Fx | B27: AUD/AUD | C27: 1 | D27: 1 | E27: 1 | F27: 0 | G27: 0 | H27: 0 | I27: 0
A28: Unit Cost | B28: AUD/tonne | C28: 30181.8 | D28: 30181.8 | E28: 30181.8 | F28: 0 | G28: 0 | H28: 0 | I28: 0
A29: Royalty Rate | B29: fraction | C29: 0 | D29: 0 | E29: 0 | F29: 0 | G29: 0 | H29: 0 | I29: 0
A30: Tax Rate | B30: fraction | C30: 0.3 | D30: 0.3 | E30: 0.3 | F30: 0 | G30: 0 | H30: 0 | I30: 0
A31: Depreciation | B31: AUD | C31: 0 | D31: 0 | E31: 0 | F31: 0 | G31: 0 | H31: 0 | I31: 0
A32: Capex | B32: AUD | C32: 93600000 | D32: 93600000 | E32: 93600000 | F32: 0 | G32: 0 | H32: 0 | I32: 0
A33: Working Capital Change | B33: AUD | C33: 0 | D33: 0 | E33: 0 | F33: 0 | G33: 0 | H33: 0 | I33: 0
A34: Closure | B34: AUD | C34: 0 | D34: 0 | E34: 100000000 | F34: 0 | G34: 0 | H34: 0 | I34: 0
A35: Corporate Cost | B35: AUD | C35: 2240000 | D35: 2240000 | E35: 2240000 | F35: 0 | G35: 0 | H35: 0 | I35: 0
A38: BASE / whole_operation
A39: Discount Rate | B39: 0.1
A40: Ownership | B40: 0.5
A41: Residual Value | B41: 0
A42: Explicit forecast periods | B42: 5
C43: 2027 | D43: 2028 | E43: 2029 | F43: 2030 | G43: 2031 | H43: 2032 | I43: 2033
A44: Production proxy (not payable sales) | B44: tonnes | C44: 11287 | D44: 11287 | E44: 11287 | F44: 11287 | G44: 11287 | H44: 0 | I44: 0
A45: Price | B45: AUD/tonne | C45: 63760 | D45: 63760 | E45: 63760 | F45: 63760 | G45: 63760 | H45: 0 | I45: 0
A46: Fx | B46: AUD/AUD | C46: 1 | D46: 1 | E46: 1 | F46: 1 | G46: 1 | H46: 0 | I46: 0
A47: Unit Cost | B47: AUD/tonne | C47: 27438 | D47: 27438 | E47: 27438 | F47: 27438 | G47: 27438 | H47: 0 | I47: 0
A48: Royalty Rate | B48: fraction | C48: 0 | D48: 0 | E48: 0 | F48: 0 | G48: 0 | H48: 0 | I48: 0
A49: Tax Rate | B49: fraction | C49: 0.3 | D49: 0.3 | E49: 0.3 | F49: 0.3 | G49: 0.3 | H49: 0 | I49: 0
A50: Depreciation | B50: AUD | C50: 0 | D50: 0 | E50: 0 | F50: 0 | G50: 0 | H50: 0 | I50: 0
A51: Capex | B51: AUD | C51: 93600000 | D51: 93600000 | E51: 93600000 | F51: 93600000 | G51: 93600000 | H51: 0 | I51: 0
A52: Working Capital Change | B52: AUD | C52: 0 | D52: 0 | E52: 0 | F52: 0 | G52: 0 | H52: 0 | I52: 0
A53: Closure | B53: AUD | C53: 0 | D53: 0 | E53: 0 | F53: 0 | G53: 100000000 | H53: 0 | I53: 0
A54: Corporate Cost | B54: AUD | C54: 2240000 | D54: 2240000 | E54: 2240000 | F54: 2240000 | G54: 2240000 | H54: 0 | I54: 0
A57: BULL / whole_operation
A58: Discount Rate | B58: 0.08
A59: Ownership | B59: 0.5
A60: Residual Value | B60: 0
A61: Explicit forecast periods | B61: 7
C62: 2027 | D62: 2028 | E62: 2029 | F62: 2030 | G62: 2031 | H62: 2032 | I62: 2033
A63: Production proxy (not payable sales) | B63: tonnes | C63: 12415.7 | D63: 12415.7 | E63: 12415.7 | F63: 12415.7 | G63: 12415.7 | H63: 12415.7 | I63: 12415.7
A64: Price | B64: AUD/tonne | C64: 76512 | D64: 76512 | E64: 76512 | F64: 76512 | G64: 76512 | H64: 76512 | I64: 76512
A65: Fx | B65: AUD/AUD | C65: 1 | D65: 1 | E65: 1 | F65: 1 | G65: 1 | H65: 1 | I65: 1
A66: Unit Cost | B66: AUD/tonne | C66: 26066.1 | D66: 26066.1 | E66: 26066.1 | F66: 26066.1 | G66: 26066.1 | H66: 26066.1 | I66: 26066.1
A67: Royalty Rate | B67: fraction | C67: 0 | D67: 0 | E67: 0 | F67: 0 | G67: 0 | H67: 0 | I67: 0
A68: Tax Rate | B68: fraction | C68: 0.3 | D68: 0.3 | E68: 0.3 | F68: 0.3 | G68: 0.3 | H68: 0.3 | I68: 0.3
A69: Depreciation | B69: AUD | C69: 0 | D69: 0 | E69: 0 | F69: 0 | G69: 0 | H69: 0 | I69: 0
A70: Capex | B70: AUD | C70: 93600000 | D70: 93600000 | E70: 93600000 | F70: 93600000 | G70: 93600000 | H70: 93600000 | I70: 93600000
A71: Working Capital Change | B71: AUD | C71: 0 | D71: 0 | E71: 0 | F71: 0 | G71: 0 | H71: 0 | I71: 0
A72: Closure | B72: AUD | C72: 0 | D72: 0 | E72: 0 | F72: 0 | G72: 0 | H72: 0 | I72: 100000000
A73: Corporate Cost | B73: AUD | C73: 2240000 | D73: 2240000 | E73: 2240000 | F73: 2240000 | G73: 2240000 | H73: 2240000 | I73: 2240000

Sheet Historical
A1: asx-mlx / Historical
A4: Source-linked reported facts. Historical coverage may be incomplete; no integrated statements are inferred.
A6: Metric | B6: Period | C6: Value | D6: Unit | E6: Currency | F6: Basis / ownership | G6: Published | H6: Source | I6: Page
A7: cash_and_cash_equivalents | B7: 2025-12-31 | C7: 293606000 | D7: AUD | E7: AUD | F7: reported / consolidated | G7: 2026-03-25 | H7: Open source report | I7: 25
A8: current_interest_bearing_liabilities | B8: 2025-12-31 | C8: 2849000 | D8: AUD | E8: AUD | F8: reported / consolidated | G8: 2026-03-25 | H8: Open source report | I8: 25
A9: noncurrent_interest_bearing_liabilities | B9: 2025-12-31 | C9: 436000 | D9: AUD | E9: AUD | F9: reported / consolidated | G9: 2026-03-25 | H9: Open source report | I9: 25
A10: issued_ordinary_shares | B10: 2025-12-31 | C10: 886391538 | D10: shares | F10: reported / consolidated | G10: 2026-03-25 | H10: Open source report | I10: 62
A11: rehabilitation_provision_present_value | B11: 2025-12-31 | C11: 33035000 | D11: AUD | E11: AUD | F11: reported / consolidated | G11: 2026-03-25 | H11: Open source report | I11: 60
A12: net_operating_cash_flow | B12: FY2025 | C12: 128323000 | D12: AUD | E12: AUD | F12: reported / consolidated | G12: 2026-03-25 | H12: Open source report | I12: 26
A13: cash_paid_property_plant_equipment | B13: FY2025 | C13: 13747000 | D13: AUD | E13: AUD | F13: reported / consolidated | G13: 2026-03-25 | H13: Open source report | I13: 26
A14: cash_paid_mine_properties_development | B14: FY2025 | C14: 22211000 | D14: AUD | E14: AUD | F14: reported / consolidated | G14: 2026-03-25 | H14: Open source report | I14: 26
A15: tin_in_concentrate_produced | B15: FY2025 | C15: 10748 | D15: tonnes_tin | F15: reported / whole_operation | G15: 2026-03-25 | H15: Open source report | I15: 9
A16: ownership_interest | B16: 2026-Q2 | C16: 0.5 | D16: fraction | F16: reported / whole_operation | G16: 2026-07-27 | H16: Open source report | I16: 2
A17: tin_in_concentrate_produced | B17: 2026-Q2 | C17: 2809 | D17: tonnes_tin | F17: reported / whole_operation | G17: 2026-07-27 | H17: Open source report | I17: 2
A18: tin_in_concentrate_produced | B18: TTM-ended-2026-06-30 | C18: 11287 | D18: tonnes_tin | F18: reported / whole_operation | G18: 2026-07-27 | H18: Open source report | I18: 2
A19: imputed_tin_price | B19: 2026-Q2 | C19: 73834 | D19: AUD_per_tonne_tin | E19: AUD | F19: reported / whole_operation | G19: 2026-07-27 | H19: Open source report | I19: 2
A20: imputed_tin_price | B20: TTM-ended-2026-06-30 | C20: 63760 | D20: AUD_per_tonne_tin | E20: AUD | F20: reported / whole_operation | G20: 2026-07-27 | H20: Open source report | I20: 2
A21: c1_cash_production_cost | B21: 2026-Q2 | C21: 20251 | D21: AUD_per_tonne_tin | E21: AUD | F21: reported / whole_operation | G21: 2026-07-27 | H21: Open source report | I21: 2
A22: c1_cash_production_cost | B22: TTM-ended-2026-06-30 | C22: 19349 | D22: AUD_per_tonne_tin | E22: AUD | F22: reported / whole_operation | G22: 2026-07-27 | H22: Open source report | I22: 2
A23: imputed_sales_and_marketing_cost | B23: 2026-Q2 | C23: 8758 | D23: AUD_per_tonne_tin | E23: AUD | F23: reported / whole_operation | G23: 2026-07-27 | H23: Open source report | I23: 2
A24: all_in_sustaining_cost | B24: 2026-Q2 | C24: 34865 | D24: AUD_per_tonne_tin | E24: AUD | F24: reported / whole_operation | G24: 2026-07-27 | H24: Open source report | I24: 2
A25: capital_expenditure | B25: 2026-Q2 | C25: 23400000 | D25: AUD | E25: AUD | F25: reported / whole_operation | G25: 2026-07-27 | H25: Open source report | I25: 3
A26: sustaining_capital_expenditure | B26: 2026-Q2 | C26: 16450000 | D26: AUD | E26: AUD | F26: reported / whole_operation | G26: 2026-07-27 | H26: Open source report | I26: 3
A27: project_capital_expenditure | B27: 2026-Q2 | C27: 6950000 | D27: AUD | E27: AUD | F27: reported / whole_operation | G27: 2026-07-27 | H27: Open source report | I27: 3
A28: cash_and_cash_equivalents | B28: 2026-06-30 | C28: 374000000 | D28: AUD | E28: AUD | F28: reported / consolidated | G28: 2026-07-27 | H28: Open source report | I28: 9
A29: corporate_costs | B29: 2026-Q2 | C29: 560000 | D29: AUD | E29: AUD | F29: reported / consolidated | G29: 2026-07-27 | H29: Open source report | I29: 8
A30: revenue | B30: FY2025 | C30: 284999000 | D30: AUD | E30: AUD | F30: reported / consolidated | G30: 2026-03-25 | H30: Open source report | I30: 24
... A79: opening_cash_and_cash_equivalents | B79: FY2024 | C79: 143042000 | D79: AUD | E79: AUD | F79: reported / consolidated | G79: 2026-03-25 | H79: Open source report | I79: 26

Sheet Operating
A1: asx-mlx / Operating
A4: Discount Rate | B4: =IF(Assumptions!$B$4="bear",Assumptions!$B$20,IF(Assumptions!$B$4="base",Assumptions!$B$39,Assumptions!$B$58)) -> 0.1
A5: Ownership | B5: =IF(Assumptions!$B$4="bear",Assumptions!$B$21,IF(Assumptions!$B$4="base",Assumptions!$B$40,Assumptions!$B$59)) -> 0.5
A6: Residual Value | B6: =IF(Assumptions!$B$4="bear",Assumptions!$B$22,IF(Assumptions!$B$4="base",Assumptions!$B$41,Assumptions!$B$60)) -> 0
A7: Horizon | B7: =IF(Assumptions!$B$4="bear",Assumptions!$B$23,IF(Assumptions!$B$4="base",Assumptions!$B$42,Assumptions!$B$61)) -> 5
A8: Volume basis | B8: =IF(Assumptions!$B$4="bear","imputed_production",IF(Assumptions!$B$4="base","imputed_production","imputed_production")) -> imputed_production
A9: Annual end-of-period forecast | C9: =YEAR(DATEVALUE(Assumptions!$B$12))+1 -> 2027 | D9: =YEAR(DATEVALUE(Assumptions!$B$12))+2 -> 2028 | E9: =YEAR(DATEVALUE(Assumptions!$B$12))+3 -> 2029 | F9: =YEAR(DATEVALUE(Assumptions!$B$12))+4 -> 2030 | G9: =YEAR(DATEVALUE(Assumptions!$B$12))+5 -> 2031 | H9: =YEAR(DATEVALUE(Assumptions!$B$12))+6 -> 2032 | I9: =YEAR(DATEVALUE(Assumptions!$B$12))+7 -> 2033
A10: Volume (see case basis) | B10: tonnes | C10: =IF(Assumptions!$B$4="bear",Assumptions!$C$25,IF(Assumptions!$B$4="base",Assumptions!$C$44,Assumptions!$C$63)) -> 11287 | D10: =IF(Assumptions!$B$4="bear",Assumptions!$D$25,IF(Assumptions!$B$4="base",Assumptions!$D$44,Assumptions!$D$63)) -> 11287 | E10: =IF(Assumptions!$B$4="bear",Assumptions!$E$25,IF(Assumptions!$B$4="base",Assumptions!$E$44,Assumptions!$E$63)) -> 11287 | F10: =IF(Assumptions!$B$4="bear",Assumptions!$F$25,IF(Assumptions!$B$4="base",Assumptions!$F$44,Assumptions!$F$63)) -> 11287 | G10: =IF(Assumptions!$B$4="bear",Assumptions!$G$25,IF(Assumptions!$B$4="base",Assumptions!$G$44,Assumptions!$G$63)) -> 11287 | H10: =IF(Assumptions!$B$4="bear",Assumptions!$H$25,IF(Assumptions!$B$4="base",Assumptions!$H$44,Assumptions!$H$63)) -> 0 | I10: =IF(Assumptions!$B$4="bear",Assumptions!$I$25,IF(Assumptions!$B$4="base",Assumptions!$I$44,Assumptions!$I$63)) -> 0
A11: Price | B11: see case input units | C11: =IF(Assumptions!$B$4="bear",Assumptions!$C$26,IF(Assumptions!$B$4="base",Assumptions!$C$45,Assumptions!$C$64)) -> 63760 | D11: =IF(Assumptions!$B$4="bear",Assumptions!$D$26,IF(Assumptions!$B$4="base",Assumptions!$D$45,Assumptions!$D$64)) -> 63760 | E11: =IF(Assumptions!$B$4="bear",Assumptions!$E$26,IF(Assumptions!$B$4="base",Assumptions!$E$45,Assumptions!$E$64)) -> 63760 | F11: =IF(Assumptions!$B$4="bear",Assumptions!$F$26,IF(Assumptions!$B$4="base",Assumptions!$F$45,Assumptions!$F$64)) -> 63760 | G11: =IF(Assumptions!$B$4="bear",Assumptions!$G$26,IF(Assumptions!$B$4="base",Assumptions!$G$45,Assumptions!$G$64)) -> 63760 | H11: =IF(Assumptions!$B$4="bear",Assumptions!$H$26,IF(Assumptions!$B$4="base",Assumptions!$H$45,Assumptions!$H$64)) -> 0 | I11: =IF(Assumptions!$B$4="bear",Assumptions!$I$26,IF(Assumptions!$B$4="base",Assumptions!$I$45,Assumptions!$I$64)) -> 0
A12: Fx | B12: see case input units | C12: =IF(Assumptions!$B$4="bear",Assumptions!$C$27,IF(Assumptions!$B$4="base",Assumptions!$C$46,Assumptions!$C$65)) -> 1 | D12: =IF(Assumptions!$B$4="bear",Assumptions!$D$27,IF(Assumptions!$B$4="base",Assumptions!$D$46,Assumptions!$D$65)) -> 1 | E12: =IF(Assumptions!$B$4="bear",Assumptions!$E$27,IF(Assumptions!$B$4="base",Assumptions!$E$46,Assumptions!$E$65)) -> 1 | F12: =IF(Assumptions!$B$4="bear",Assumptions!$F$27,IF(Assumptions!$B$4="base",Assumptions!$F$46,Assumptions!$F$65)) -> 1 | G12: =IF(Assumptions!$B$4="bear",Assumptions!$G$27,IF(Assumptions!$B$4="base",Assumptions!$G$46,Assumptions!$G$65)) -> 1 | H12: =IF(Assumptions!$B$4="bear",Assumptions!$H$27,IF(Assumptions!$B$4="base",Assumptions!$H$46,Assumptions!$H$65)) -> 0 | I12: =IF(Assumptions!$B$4="bear",Assumptions!$I$27,IF(Assumptions!$B$4="base",Assumptions!$I$46,Assumptions!$I$65)) -> 0
A13: Unit Cost | B13: AUD/tonne | C13: =IF(Assumptions!$B$4="bear",Assumptions!$C$28,IF(Assumptions!$B$4="base",Assumptions!$C$47,Assumptions!$C$66)) -> 27438 | D13: =IF(Assumptions!$B$4="bear",Assumptions!$D$28,IF(Assumptions!$B$4="base",Assumptions!$D$47,Assumptions!$D$66)) -> 27438 | E13: =IF(Assumptions!$B$4="bear",Assumptions!$E$28,IF(Assumptions!$B$4="base",Assumptions!$E$47,Assumptions!$E$66)) -> 27438 | F13: =IF(Assumptions!$B$4="bear",Assumptions!$F$28,IF(Assumptions!$B$4="base",Assumptions!$F$47,Assumptions!$F$66)) -> 27438 | G13: =IF(Assumptions!$B$4="bear",Assumptions!$G$28,IF(Assumptions!$B$4="base",Assumptions!$G$47,Assumptions!$G$66)) -> 27438 | H13: =IF(Assumptions!$B$4="bear",Assumptions!$H$28,IF(Assumptions!$B$4="base",Assumptions!$H$47,Assumptions!$H$66)) -> 0 | I13: =IF(Assumptions!$B$4="bear",Assumptions!$I$28,IF(Assumptions!$B$4="base",Assumptions!$I$47,Assumptions!$I$66)) -> 0
A14: Royalty Rate | B14: fraction | C14: =IF(Assumptions!$B$4="bear",Assumptions!$C$29,IF(Assumptions!$B$4="base",Assumptions!$C$48,Assumptions!$C$67)) -> 0 | D14: =IF(Assumptions!$B$4="bear",Assumptions!$D$29,IF(Assumptions!$B$4="base",Assumptions!$D$48,Assumptions!$D$67)) -> 0 | E14: =IF(Assumptions!$B$4="bear",Assumptions!$E$29,IF(Assumptions!$B$4="base",Assumptions!$E$48,Assumptions!$E$67)) -> 0 | F14: =IF(Assumptions!$B$4="bear",Assumptions!$F$29,IF(Assumptions!$B$4="base",Assumptions!$F$48,Assumptions!$F$67)) -> 0 | G14: =IF(Assumptions!$B$4="bear",Assumptions!$G$29,IF(Assumptions!$B$4="base",Assumptions!$G$48,Assumptions!$G$67)) -> 0 | H14: =IF(Assumptions!$B$4="bear",Assumptions!$H$29,IF(Assumptions!$B$4="base",Assumptions!$H$48,Assumptions!$H$67)) -> 0 | I14: =IF(Assumptions!$B$4="bear",Assumptions!$I$29,IF(Assumptions!$B$4="base",Assumptions!$I$48,Assumptions!$I$67)) -> 0
A15: Tax Rate | B15: fraction | C15: =IF(Assumptions!$B$4="bear",Assumptions!$C$30,IF(Assumptions!$B$4="base",Assumptions!$C$49,Assumptions!$C$68)) -> 0.3 | D15: =IF(Assumptions!$B$4="bear",Assumptions!$D$30,IF(Assumptions!$B$4="base",Assumptions!$D$49,Assumptions!$D$68)) -> 0.3 | E15: =IF(Assumptions!$B$4="bear",Assumptions!$E$30,IF(Assumptions!$B$4="base",Assumptions!$E$49,Assumptions!$E$68)) -> 0.3 | F15: =IF(Assumptions!$B$4="bear",Assumptions!$F$30,IF(Assumptions!$B$4="base",Assumptions!$F$49,Assumptions!$F$68)) -> 0.3 | G15: =IF(Assumptions!$B$4="bear",Assumptions!$G$30,IF(Assumptions!$B$4="base",Assumptions!$G$49,Assumptions!$G$68)) -> 0.3 | H15: =IF(Assumptions!$B$4="bear",Assumptions!$H$30,IF(Assumptions!$B$4="base",Assumptions!$H$49,Assumptions!$H$68)) -> 0 | I15: =IF(Assumptions!$B$4="bear",Assumptions!$I$30,IF(Assumptions!$B$4="base",Assumptions!$I$49,Assumptions!$I$68)) -> 0
A16: Depreciation | B16: AUD | C16: =IF(Assumptions!$B$4="bear",Assumptions!$C$31,IF(Assumptions!$B$4="base",Assumptions!$C$50,Assumptions!$C$69)) -> 0 | D16: =IF(Assumptions!$B$4="bear",Assumptions!$D$31,IF(Assumptions!$B$4="base",Assumptions!$D$50,Assumptions!$D$69)) -> 0 | E16: =IF(Assumptions!$B$4="bear",Assumptions!$E$31,IF(Assumptions!$B$4="base",Assumptions!$E$50,Assumptions!$E$69)) -> 0 | F16: =IF(Assumptions!$B$4="bear",Assumptions!$F$31,IF(Assumptions!$B$4="base",Assumptions!$F$50,Assumptions!$F$69)) -> 0 | G16: =IF(Assumptions!$B$4="bear",Assumptions!$G$31,IF(Assumptions!$B$4="base",Assumptions!$G$50,Assumptions!$G$69)) -> 0 | H16: =IF(Assumptions!$B$4="bear",Assumptions!$H$31,IF(Assumptions!$B$4="base",Assumptions!$H$50,Assumptions!$H$69)) -> 0 | I16: =IF(Assumptions!$B$4="bear",Assumptions!$I$31,IF(Assumptions!$B$4="base",Assumptions!$I$50,Assumptions!$I$69)) -> 0
A17: Capex | B17: AUD | C17: =IF(Assumptions!$B$4="bear",Assumptions!$C$32,IF(Assumptions!$B$4="base",Assumptions!$C$51,Assumptions!$C$70)) -> 93600000 | D17: =IF(Assumptions!$B$4="bear",Assumptions!$D$32,IF(Assumptions!$B$4="base",Assumptions!$D$51,Assumptions!$D$70)) -> 93600000 | E17: =IF(Assumptions!$B$4="bear",Assumptions!$E$32,IF(Assumptions!$B$4="base",Assumptions!$E$51,Assumptions!$E$70)) -> 93600000 | F17: =IF(Assumptions!$B$4="bear",Assumptions!$F$32,IF(Assumptions!$B$4="base",Assumptions!$F$51,Assumptions!$F$70)) -> 93600000 | G17: =IF(Assumptions!$B$4="bear",Assumptions!$G$32,IF(Assumptions!$B$4="base",Assumptions!$G$51,Assumptions!$G$70)) -> 93600000 | H17: =IF(Assumptions!$B$4="bear",Assumptions!$H$32,IF(Assumptions!$B$4="base",Assumptions!$H$51,Assumptions!$H$70)) -> 0 | I17: =IF(Assumptions!$B$4="bear",Assumptions!$I$32,IF(Assumptions!$B$4="base",Assumptions!$I$51,Assumptions!$I$70)) -> 0
A18: Working Capital Change | B18: AUD | C18: =IF(Assumptions!$B$4="bear",Assumptions!$C$33,IF(Assumptions!$B$4="base",Assumptions!$C$52,Assumptions!$C$71)) -> 0 | D18: =IF(Assumptions!$B$4="bear",Assumptions!$D$33,IF(Assumptions!$B$4="base",Assumptions!$D$52,Assumptions!$D$71)) -> 0 | E18: =IF(Assumptions!$B$4="bear",Assumptions!$E$33,IF(Assumptions!$B$4="base",Assumptions!$E$52,Assumptions!$E$71)) -> 0 | F18: =IF(Assumptions!$B$4="bear",Assumptions!$F$33,IF(Assumptions!$B$4="base",Assumptions!$F$52,Assumptions!$F$71)) -> 0 | G18: =IF(Assumptions!$B$4="bear",Assumptions!$G$33,IF(Assumptions!$B$4="base",Assumptions!$G$52,Assumptions!$G$71)) -> 0 | H18: =IF(Assumptions!$B$4="bear",Assumptions!$H$33,IF(Assumptions!$B$4="base",Assumptions!$H$52,Assumptions!$H$71)) -> 0 | I18: =IF(Assumptions!$B$4="bear",Assumptions!$I$33,IF(Assumptions!$B$4="base",Assumptions!$I$52,Assumptions!$I$71)) -> 0
A19: Closure | B19: AUD | C19: =IF(Assumptions!$B$4="bear",Assumptions!$C$34,IF(Assumptions!$B$4="base",Assumptions!$C$53,Assumptions!$C$72)) -> 0 | D19: =IF(Assumptions!$B$4="bear",Assumptions!$D$34,IF(Assumptions!$B$4="base",Assumptions!$D$53,Assumptions!$D$72)) -> 0 | E19: =IF(Assumptions!$B$4="bear",Assumptions!$E$34,IF(Assumptions!$B$4="base",Assumptions!$E$53,Assumptions!$E$72)) -> 0 | F19: =IF(Assumptions!$B$4="bear",Assumptions!$F$34,IF(Assumptions!$B$4="base",Assumptions!$F$53,Assumptions!$F$72)) -> 0 | G19: =IF(Assumptions!$B$4="bear",Assumptions!$G$34,IF(Assumptions!$B$4="base",Assumptions!$G$53,Assumptions!$G$72)) -> 100000000 | H19: =IF(Assumptions!$B$4="bear",Assumptions!$H$34,IF(Assumptions!$B$4="base",Assumptions!$H$53,Assumptions!$H$72)) -> 0 | I19: =IF(Assumptions!$B$4="bear",Assumptions!$I$34,IF(Assumptions!$B$4="base",Assumptions!$I$53,Assumptions!$I$72)) -> 0
A20: Corporate Cost | B20: AUD | C20: =IF(Assumptions!$B$4="bear",Assumptions!$C$35,IF(Assumptions!$B$4="base",Assumptions!$C$54,Assumptions!$C$73)) -> 2240000 | D20: =IF(Assumptions!$B$4="bear",Assumptions!$D$35,IF(Assumptions!$B$4="base",Assumptions!$D$54,Assumptions!$D$73)) -> 2240000 | E20: =IF(Assumptions!$B$4="bear",Assumptions!$E$35,IF(Assumptions!$B$4="base",Assumptions!$E$54,Assumptions!$E$73)) -> 2240000 | F20: =IF(Assumptions!$B$4="bear",Assumptions!$F$35,IF(Assumptions!$B$4="base",Assumptions!$F$54,Assumptions!$F$73)) -> 2240000 | G20: =IF(Assumptions!$B$4="bear",Assumptions!$G$35,IF(Assumptions!$B$4="base",Assumptions!$G$54,Assumptions!$G$73)) -> 2240000 | H20: =IF(Assumptions!$B$4="bear",Assumptions!$H$35,IF(Assumptions!$B$4="base",Assumptions!$H$54,Assumptions!$H$73)) -> 0 | I20: =IF(Assumptions!$B$4="bear",Assumptions!$I$35,IF(Assumptions!$B$4="base",Assumptions!$I$54,Assumptions!$I$73)) -> 0
A23: Revenue | B23: AUD | C23: =Operating!$C$10*Operating!$C$11*Operating!$C$12 -> 719659120 | D23: =Operating!$D$10*Operating!$D$11*Operating!$D$12 -> 719659120 | E23: =Operating!$E$10*Operating!$E$11*Operating!$E$12 -> 719659120 | F23: =Operating!$F$10*Operating!$F$11*Operating!$F$12 -> 719659120 | G23: =Operating!$G$10*Operating!$G$11*Operating!$G$12 -> 719659120 | H23: =Operating!$H$10*Operating!$H$11*Operating!$H$12 -> 0 | I23: =Operating!$I$10*Operating!$I$11*Operating!$I$12 -> 0
A24: Operating Cost | B24: AUD | C24: =Operating!$C$10*Operating!$C$13 -> 309692706 | D24: =Operating!$D$10*Operating!$D$13 -> 309692706 | E24: =Operating!$E$10*Operating!$E$13 -> 309692706 | F24: =Operating!$F$10*Operating!$F$13 -> 309692706 | G24: =Operating!$G$10*Operating!$G$13 -> 309692706 | H24: =Operating!$H$10*Operating!$H$13 -> 0 | I24: =Operating!$I$10*Operating!$I$13 -> 0
A25: Royalties | B25: AUD | C25: =Operating!$C$23*Operating!$C$14 -> 0 | D25: =Operating!$D$23*Operating!$D$14 -> 0 | E25: =Operating!$E$23*Operating!$E$14 -> 0 | F25: =Operating!$F$23*Operating!$F$14 -> 0 | G25: =Operating!$G$23*Operating!$G$14 -> 0 | H25: =Operating!$H$23*Operating!$H$14 -> 0 | I25: =Operating!$I$23*Operating!$I$14 -> 0
A26: Ebit | B26: AUD | C26: =Operating!$C$23-Operating!$C$24-Operating!$C$25-Operating!$C$16 -> 409966414 | D26: =Operating!$D$23-Operating!$D$24-Operating!$D$25-Operating!$D$16 -> 409966414 | E26: =Operating!$E$23-Operating!$E$24-Operating!$E$25-Operating!$E$16 -> 409966414 | F26: =Operating!$F$23-Operating!$F$24-Operating!$F$25-Operating!$F$16 -> 409966414 | G26: =Operating!$G$23-Operating!$G$24-Operating!$G$25-Operating!$G$16 -> 409966414 | H26: =Operating!$H$23-Operating!$H$24-Operating!$H$25-Operating!$H$16 -> 0 | I26: =Operating!$I$23-Operating!$I$24-Operating!$I$25-Operating!$I$16 -> 0
A27: Tax | B27: AUD | C27: =MAX(0,Operating!$C$26)*Operating!$C$15 -> 1.2298992e+08 | D27: =MAX(0,Operating!$D$26)*Operating!$D$15 -> 1.2298992e+08 | E27: =MAX(0,Operating!$E$26)*Operating!$E$15 -> 1.2298992e+08 | F27: =MAX(0,Operating!$F$26)*Operating!$F$15 -> 1.2298992e+08 | G27: =MAX(0,Operating!$G$26)*Operating!$G$15 -> 1.2298992e+08 | H27: =MAX(0,Operating!$H$26)*Operating!$H$15 -> 0 | I27: =MAX(0,Operating!$I$26)*Operating!$I$15 -> 0
A28: Nopat | B28: AUD | C28: =Operating!$C$26-Operating!$C$27 -> 2.8697649e+08 | D28: =Operating!$D$26-Operating!$D$27 -> 2.8697649e+08 | E28: =Operating!$E$26-Operating!$E$27 -> 2.8697649e+08 | F28: =Operating!$F$26-Operating!$F$27 -> 2.8697649e+08 | G28: =Operating!$G$26-Operating!$G$27 -> 2.8697649e+08 | H28: =Operating!$H$26-Operating!$H$27 -> 0 | I28: =Operating!$I$26-Operating!$I$27 -> 0
A29: Operating Fcf | B29: AUD | C29: =Operating!$C$28+Operating!$C$16-Operating!$C$17-Operating!$C$18-Operating!$C$19 -> 1.9337649e+08 | D29: =Operating!$D$28+Operating!$D$16-Operating!$D$17-Operating!$D$18-Operating!$D$19 -> 1.9337649e+08 | E29: =Operating!$E$28+Operating!$E$16-Operating!$E$17-Operating!$E$18-Operating!$E$19 -> 1.9337649e+08 | F29: =Operating!$F$28+Operating!$F$16-Operating!$F$17-Operating!$F$18-Operating!$F$19 -> 1.9337649e+08 | G29: =Operating!$G$28+Operating!$G$16-Operating!$G$17-Operating!$G$18-Operating!$G$19 -> 93376490 | H29: =Operating!$H$28+Operating!$H$16-Operating!$H$17-Operating!$H$18-Operating!$H$19 -> 0 | I29: =Operating!$I$28+Operating!$I$16-Operating!$I$17-Operating!$I$18-Operating!$I$19 -> 0
A30: Fcf | B30: AUD | C30: =Operating!$C$29*Operating!$B$5-Operating!$C$20+IF(1=Operating!$B$7,Operating!$B$6,0) -> 94448245 | D30: =Operating!$D$29*Operating!$B$5-Operating!$D$20+IF(2=Operating!$B$7,Operating!$B$6,0) -> 94448245 | E30: =Operating!$E$29*Operating!$B$5-Operating!$E$20+IF(3=Operating!$B$7,Operating!$B$6,0) -> 94448245 | F30: =Operating!$F$29*Operating!$B$5-Operating!$F$20+IF(4=Operating!$B$7,Operating!$B$6,0) -> 94448245 | G30: =Operating!$G$29*Operating!$B$5-Operating!$G$20+IF(5=Operating!$B$7,Operating!$B$6,0) -> 44448245 | H30: =Operating!$H$29*Operating!$B$5-Operating!$H$20+IF(6=Operating!$B$7,Operating!$B$6,0) -> 0 | I30: =Operating!$I$29*Operating!$B$5-Operating!$I$20+IF(7=Operating!$B$7,Operating!$B$6,0) -> 0
A31: Present Value | B31: AUD | C31: =Operating!$C$30/(1+Operating!$B$4)^1 -> 85862041 | D31: =Operating!$D$30/(1+Operating!$B$4)^2 -> 78056401 | E31: =Operating!$E$30/(1+Operating!$B$4)^3 -> 70960364 | F31: =Operating!$F$30/(1+Operating!$B$4)^4 -> 64509422 | G31: =Operating!$G$30/(1+Operating!$B$4)^5 -> 27598863 | H31: =Operating!$H$30/(1+Operating!$B$4)^6 -> 0 | I31: =Operating!$I$30/(1+Operating!$B$4)^7 -> 0
A32: Illustrative Cash | B32: AUD | C32: =Assumptions!$B$7+Operating!$C$30 -> 4.6844824e+08 | D32: =Operating!$C$32+Operating!$D$30 -> 5.6289649e+08 | E32: =Operating!$D$32+Operating!$E$30 -> 6.5734473e+08 | F32: =Operating!$E$32+Operating!$F$30 -> 7.5179298e+08 | G32: =Operating!$F$32+Operating!$G$30 -> 7.9624122e+08 | H32: =Operating!$G$32+Operating!$H$30 -> 7.9624122e+08 | I32: =Operating!$H$32+Operating!$I$30 -> 7.9624122e+08
A34: Illustrative cash excludes financing, dividends and debt maturities. This is a finite cash-flow schedule, not an integrated three-statement forecast. No terminal perpetuity is assumed.

Sheet Valuation
A1: asx-mlx / Valuation
A5: Enterprise Value | B5: =SUM(Operating!C31:I31) -> 3.2698709e+08 | C5: AUD
A6: Cash | B6: =Assumptions!$B$7 -> 374000000 | C6: AUD
A7: Other Assets | B7: =Assumptions!$B$9 -> 0 | C7: AUD
A8: Debt | B8: =Assumptions!$B$8 -> 3285000 | C8: AUD
A9: Equity Value | B9: =B5+B6+B7-B8 -> 6.9770209e+08 | C9: AUD
A10: Diluted Shares | B10: =Assumptions!$B$10 -> 886391538 | C10: shares
A11: Per Share | B11: =B9/B10 -> 0.7871263 | C11: AUD/share
A12: Minimum Illustrative Cash | B12: =MIN(Assumptions!$B$7,Operating!C32:I32) -> 374000000 | C12: AUD
A15: Reference price | B15: =IF(Assumptions!$B$11="","Unavailable",Assumptions!$B$11) -> Unavailable
A16: Model / reference price − 1 | B16: =IF(AND(ISNUMBER(B15),B15>0),B11/B15-1,"Unavailable") -> Unavailable
A19: This is a model output, not a price target or investment recommendation. Corporate costs and residual value are company-attributable; operating cash flows apply ownership once. Residual value is explicit, not a perpetuity.

Sheet Sensitivities
A1: asx-mlx / Sensitivities
A4: Price multiplier × discount rate / AUD per share. All active-case forecast years recomputed, including positive-EBIT tax floor.
C7: =MAX(0,Operating!$B$4+(-0.02)) -> 0.08 | D7: =MAX(0,Operating!$B$4+(0)) -> 0.1 | E7: =MAX(0,Operating!$B$4+(0.02)) -> 0.12
B8: 0.8 | C8: =(SUM(C17:I17)+Assumptions!$B$7+Assumptions!$B$9-Assumptions!$B$8)/Assumptions!$B$10 -> 0.57835952 | D8: =(SUM(C18:I18)+Assumptions!$B$7+Assumptions!$B$9-Assumptions!$B$8)/Assumptions!$B$10 -> 0.57168516 | E8: =(SUM(C19:I19)+Assumptions!$B$7+Assumptions!$B$9-Assumptions!$B$8)/Assumptions!$B$10 -> 0.56545411
B9: 1 | C9: =(SUM(C20:I20)+Assumptions!$B$7+Assumptions!$B$9-Assumptions!$B$8)/Assumptions!$B$10 -> 0.80527652 | D9: =(SUM(C21:I21)+Assumptions!$B$7+Assumptions!$B$9-Assumptions!$B$8)/Assumptions!$B$10 -> 0.7871263 | E9: =(SUM(C22:I22)+Assumptions!$B$7+Assumptions!$B$9-Assumptions!$B$8)/Assumptions!$B$10 -> 0.77032374
B10: 1.2 | C10: =(SUM(C23:I23)+Assumptions!$B$7+Assumptions!$B$9-Assumptions!$B$8)/Assumptions!$B$10 -> 1.0321935 | D10: =(SUM(C24:I24)+Assumptions!$B$7+Assumptions!$B$9-Assumptions!$B$8)/Assumptions!$B$10 -> 1.0025674 | E10: =(SUM(C25:I25)+Assumptions!$B$7+Assumptions!$B$9-Assumptions!$B$8)/Assumptions!$B$10 -> 0.97519337
A15: Auditable discounted-cash-flow helpers
A17: Driver 0.8× / rate column 1 | C17: =(((((Operating!$C$10*Operating!$C$11*Operating!$C$12*$B$8)*(1-Operating!$C$14)-Operating!$C$10*Operating!$C$13-Operating!$C$16)-MAX(0,((Operating!$C$10*Operating!$C$11*Operating!$C$12*$B$8)*(1-Operating!$C$14)-Operating!$C$10*Operating!$C$13-Operating!$C$16))*Operating!$C$15)+Operating!$C$16-Operating!$C$17-Operating!$C$18-Operating!$C$19)*Operating!$B$5-Operating!$C$20+IF(1=Operating!$B$7,Operating!$B$6,0))/(1+C7)^1 -> 40807506 | D17: =(((((Operating!$D$10*Operating!$D$11*Operating!$D$12*$B$8)*(1-Operating!$D$14)-Operating!$D$10*Operating!$D$13-Operating!$D$16)-MAX(0,((Operating!$D$10*Operating!$D$11*Operating!$D$12*$B$8)*(1-Operating!$D$14)-Operating!$D$10*Operating!$D$13-Operating!$D$16))*Operating!$D$15)+Operating!$D$16-Operating!$D$17-Operating!$D$18-Operating!$D$19)*Operating!$B$5-Operating!$D$20+IF(2=Operating!$B$7,Operating!$B$6,0))/(1+C7)^2 -> 37784728 | E17: =(((((Operating!$E$10*Operating!$E$11*Operating!$E$12*$B$8)*(1-Operating!$E$14)-Operating!$E$10*Operating!$E$13-Operating!$E$16)-MAX(0,((Operating!$E$10*Operating!$E$11*Operating!$E$12*$B$8)*(1-Operating!$E$14)-Operating!$E$10*Operating!$E$13-Operating!$E$16))*Operating!$E$15)+Operating!$E$16-Operating!$E$17-Operating!$E$18-Operating!$E$19)*Operating!$B$5-Operating!$E$20+IF(3=Operating!$B$7,Operating!$B$6,0))/(1+C7)^3 -> 34985859 | F17: =(((((Operating!$F$10*Operating!$F$11*Operating!$F$12*$B$8)*(1-Operating!$F$14)-Operating!$F$10*Operating!$F$13-Operating!$F$16)-MAX(0,((Operating!$F$10*Operating!$F$11*Operating!$F$12*$B$8)*(1-Operating!$F$14)-Operating!$F$10*Operating!$F$13-Operating!$F$16))*Operating!$F$15)+Operating!$F$16-Operating!$F$17-Operating!$F$18-Operating!$F$19)*Operating!$B$5-Operating!$F$20+IF(4=Operating!$B$7,Operating!$B$6,0))/(1+C7)^4 -> 32394314 | G17: =(((((Operating!$G$10*Operating!$G$11*Operating!$G$12*$B$8)*(1-Operating!$G$14)-Operating!$G$10*Operating!$G$13-Operating!$G$16)-MAX(0,((Operating!$G$10*Operating!$G$11*Operating!$G$12*$B$8)*(1-Operating!$G$14)-Operating!$G$10*Operating!$G$13-Operating!$G$16))*Operating!$G$15)+Operating!$G$16-Operating!$G$17-Operating!$G$18-Operating!$G$19)*Operating!$B$5-Operating!$G$20+IF(5=Operating!$B$7,Operating!$B$6,0))/(1+C7)^5 -> -4034424.7 | H17: =(((((Operating!$H$10*Operating!$H$11*Operating!$H$12*$B$8)*(1-Operating!$H$14)-Operating!$H$10*Operating!$H$13-Operating!$H$16)-MAX(0,((Operating!$H$10*Operating!$H$11*Operating!$H$12*$B$8)*(1-Operating!$H$14)-Operating!$H$10*Operating!$H$13-Operating!$H$16))*Operating!$H$15)+Operating!$H$16-Operating!$H$17-Operating!$H$18-Operating!$H$19)*Operating!$B$5-Operating!$H$20+IF(6=Operating!$B$7,Operating!$B$6,0))/(1+C7)^6 -> 0 | I17: =(((((Operating!$I$10*Operating!$I$11*Operating!$I$12*$B$8)*(1-Operating!$I$14)-Operating!$I$10*Operating!$I$13-Operating!$I$16)-MAX(0,((Operating!$I$10*Operating!$I$11*Operating!$I$12*$B$8)*(1-Operating!$I$14)-Operating!$I$10*Operating!$I$13-Operating!$I$16))*Operating!$I$15)+Operating!$I$16-Operating!$I$17-Operating!$I$18-Operating!$I$19)*Operating!$B$5-Operating!$I$20+IF(7=Operating!$B$7,Operating!$B$6,0))/(1+C7)^7 -> 0
A18: Driver 0.8× / rate column 2 | C18: =(((((Operating!$C$10*Operating!$C$11*Operating!$C$12*$B$8)*(1-Operating!$C$14)-Operating!$C$10*Operating!$C$13-Operating!$C$16)-MAX(0,((Operating!$C$10*Operating!$C$11*Operating!$C$12*$B$8)*(1-Operating!$C$14)-Operating!$C$10*Operating!$C$13-Operating!$C$16))*Operating!$C$15)+Operating!$C$16-Operating!$C$17-Operating!$C$18-Operating!$C$19)*Operating!$B$5-Operating!$C$20+IF(1=Operating!$B$7,Operating!$B$6,0))/(1+D7)^1 -> 40065551 | D18: =(((((Operating!$D$10*Operating!$D$11*Operating!$D$12*$B$8)*(1-Operating!$D$14)-Operating!$D$10*Operating!$D$13-Operating!$D$16)-MAX(0,((Operating!$D$10*Operating!$D$11*Operating!$D$12*$B$8)*(1-Operating!$D$14)-Operating!$D$10*Operating!$D$13-Operating!$D$16))*Operating!$D$15)+Operating!$D$16-Operating!$D$17-Operating!$D$18-Operating!$D$19)*Operating!$B$5-Operating!$D$20+IF(2=Operating!$B$7,Operating!$B$6,0))/(1+D7)^2 -> 36423229 | E18: =(((((Operating!$E$10*Operating!$E$11*Operating!$E$12*$B$8)*(1-Operating!$E$14)-Operating!$E$10*Operating!$E$13-Operating!$E$16)-MAX(0,((Operating!$E$10*Operating!$E$11*Operating!$E$12*$B$8)*(1-Operating!$E$14)-Operating!$E$10*Operating!$E$13-Operating!$E$16))*Operating!$E$15)+Operating!$E$16-Operating!$E$17-Operating!$E$18-Operating!$E$19)*Operating!$B$5-Operating!$E$20+IF(3=Operating!$B$7,Operating!$B$6,0))/(1+D7)^3 -> 33112026 | F18: =(((((Operating!$F$10*Operating!$F$11*Operating!$F$12*$B$8)*(1-Operating!$F$14)-Operating!$F$10*Operating!$F$13-Operating!$F$16)-MAX(0,((Operating!$F$10*Operating!$F$11*Operating!$F$12*$B$8)*(1-Operating!$F$14)-Operating!$F$10*Operating!$F$13-Operating!$F$16))*Operating!$F$15)+Operating!$F$16-Operating!$F$17-Operating!$F$18-Operating!$F$19)*Operating!$B$5-Operating!$F$20+IF(4=Operating!$B$7,Operating!$B$6,0))/(1+D7)^4 -> 30101842 | G18: =(((((Operating!$G$10*Operating!$G$11*Operating!$G$12*$B$8)*(1-Operating!$G$14)-Operating!$G$10*Operating!$G$13-Operating!$G$16)-MAX(0,((Operating!$G$10*Operating!$G$11*Operating!$G$12*$B$8)*(1-Operating!$G$14)-Operating!$G$10*Operating!$G$13-Operating!$G$16))*Operating!$G$15)+Operating!$G$16-Operating!$G$17-Operating!$G$18-Operating!$G$19)*Operating!$B$5-Operating!$G$20+IF(5=Operating!$B$7,Operating!$B$6,0))/(1+D7)^5 -> -3680755.5 | H18: =(((((Operating!$H$10*Operating!$H$11*Operating!$H$12*$B$8)*(1-Operating!$H$14)-Operating!$H$10*Operating!$H$13-Operating!$H$16)-MAX(0,((Operating!$H$10*Operating!$H$11*Operating!$H$12*$B$8)*(1-Operating!$H$14)-Operating!$H$10*Operating!$H$13-Operating!$H$16))*Operating!$H$15)+Operating!$H$16-Operating!$H$17-Operating!$H$18-Operating!$H$19)*Operating!$B$5-Operating!$H$20+IF(6=Operating!$B$7,Operating!$B$6,0))/(1+D7)^6 -> 0 | I18: =(((((Operating!$I$10*Operating!$I$11*Operating!$I$12*$B$8)*(1-Operating!$I$14)-Operating!$I$10*Operating!$I$13-Operating!$I$16)-MAX(0,((Operating!$I$10*Operating!$I$11*Operating!$I$12*$B$8)*(1-Operating!$I$14)-Operating!$I$10*Operating!$I$13-Operating!$I$16))*Operating!$I$15)+Operating!$I$16-Operating!$I$17-Operating!$I$18-Operating!$I$19)*Operating!$B$5-Operating!$I$20+IF(7=Operating!$B$7,Operating!$B$6,0))/(1+D7)^7 -> 0
A19: Driver 0.8× / rate column 3 | C19: =(((((Operating!$C$10*Operating!$C$11*Operating!$C$12*$B$8)*(1-Operating!$C$14)-Operating!$C$10*Operating!$C$13-Operating!$C$16)-MAX(0,((Operating!$C$10*Operating!$C$11*Operating!$C$12*$B$8)*(1-Operating!$C$14)-Operating!$C$10*Operating!$C$13-Operating!$C$16))*Operating!$C$15)+Operating!$C$16-Operating!$C$17-Operating!$C$18-Operating!$C$19)*Operating!$B$5-Operating!$C$20+IF(1=Operating!$B$7,Operating!$B$6,0))/(1+E7)^1 -> 39350095 | D19: =(((((Operating!$D$10*Operating!$D$11*Operating!$D$12*$B$8)*(1-Operating!$D$14)-Operating!$D$10*Operating!$D$13-Operating!$D$16)-MAX(0,((Operating!$D$10*Operating!$D$11*Operating!$D$12*$B$8)*(1-Operating!$D$14)-Operating!$D$10*Operating!$D$13-Operating!$D$16))*Operating!$D$15)+Operating!$D$16-Operating!$D$17-Operating!$D$18-Operating!$D$19)*Operating!$B$5-Operating!$D$20+IF(2=Operating!$B$7,Operating!$B$6,0))/(1+E7)^2 -> 35134013 | E19: =(((((Operating!$E$10*Operating!$E$11*Operating!$E$12*$B$8)*(1-Operating!$E$14)-Operating!$E$10*Operating!$E$13-Operating!$E$16)-MAX(0,((Operating!$E$10*Operating!$E$11*Operating!$E$12*$B$8)*(1-Operating!$E$14)-Operating!$E$10*Operating!$E$13-Operating!$E$16))*Operating!$E$15)+Operating!$E$16-Operating!$E$17-Operating!$E$18-Operating!$E$19)*Operating!$B$5-Operating!$E$20+IF(3=Operating!$B$7,Operating!$B$6,0))/(1+E7)^3 -> 31369655 | F19: =(((((Operating!$F$10*Operating!$F$11*Operating!$F$12*$B$8)*(1-Operating!$F$14)-Operating!$F$10*Operating!$F$13-Operating!$F$16)-MAX(0,((Operating!$F$10*Operating!$F$11*Operating!$F$12*$B$8)*(1-Operating!$F$14)-Operating!$F$10*Operating!$F$13-Operating!$F$16))*Operating!$F$15)+Operating!$F$16-Operating!$F$17-Operating!$F$18-Operating!$F$19)*Operating!$B$5-Operating!$F$20+IF(4=Operating!$B$7,Operating!$B$6,0))/(1+E7)^4 -> 28008620 | G19: =(((((Operating!$G$10*Operating!$G$11*Operating!$G$12*$B$8)*(1-Operating!$G$14)-Operating!$G$10*Operating!$G$13-Operating!$G$16)-MAX(0,((Operating!$G$10*Operating!$G$11*Operating!$G$12*$B$8)*(1-Operating!$G$14)-Operating!$G$10*Operating!$G$13-Operating!$G$16))*Operating!$G$15)+Operating!$G$16-Operating!$G$17-Operating!$G$18-Operating!$G$19)*Operating!$B$5-Operating!$G$20+IF(5=Operating!$B$7,Operating!$B$6,0))/(1+E7)^5 -> -3363646 | H19: =(((((Operating!$H$10*Operating!$H$11*Operating!$H$12*$B$8)*(1-Operating!$H$14)-Operating!$H$10*Operating!$H$13-Operating!$H$16)-MAX(0,((Operating!$H$10*Operating!$H$11*Operating!$H$12*$B$8)*(1-Operating!$H$14)-Operating!$H$10*Operating!$H$13-Operating!$H$16))*Operating!$H$15)+Operating!$H$16-Operating!$H$17-Operating!$H$18-Operating!$H$19)*Operating!$B$5-Operating!$H$20+IF(6=Operating!$B$7,Operating!$B$6,0))/(1+E7)^6 -> 0 | I19: =(((((Operating!$I$10*Operating!$I$11*Operating!$I$12*$B$8)*(1-Operating!$I$14)-Operating!$I$10*Operating!$I$13-Operating!$I$16)-MAX(0,((Operating!$I$10*Operating!$I$11*Operating!$I$12*$B$8)*(1-Operating!$I$14)-Operating!$I$10*Operating!$I$13-Operating!$I$16))*Operating!$I$15)+Operating!$I$16-Operating!$I$17-Operating!$I$18-Operating!$I$19)*Operating!$B$5-Operating!$I$20+IF(7=Operating!$B$7,Operating!$B$6,0))/(1+E7)^7 -> 0
A20: Driver 1.0× / rate column 1 | C20: =(((((Operating!$C$10*Operating!$C$11*Operating!$C$12*$B$9)*(1-Operating!$C$14)-Operating!$C$10*Operating!$C$13-Operating!$C$16)-MAX(0,((Operating!$C$10*Operating!$C$11*Operating!$C$12*$B$9)*(1-Operating!$C$14)-Operating!$C$10*Operating!$C$13-Operating!$C$16))*Operating!$C$15)+Operating!$C$16-Operating!$C$17-Operating!$C$18-Operating!$C$19)*Operating!$B$5-Operating!$C$20+IF(1=Operating!$B$7,Operating!$B$6,0))/(1+C7)^1 -> 87452079 | D20: =(((((Operating!$D$10*Operating!$D$11*Operating!$D$12*$B$9)*(1-Operating!$D$14)-Operating!$D$10*Operating!$D$13-Operating!$D$16)-MAX(0,((Operating!$D$10*Operating!$D$11*Operating!$D$12*$B$9)*(1-Operating!$D$14)-Operating!$D$10*Operating!$D$13-Operating!$D$16))*Operating!$D$15)+Operating!$D$16-Operating!$D$17-Operating!$D$18-Operating!$D$19)*Operating!$B$5-Operating!$D$20+IF(2=Operating!$B$7,Operating!$B$6,0))/(1+C7)^2 -> 80974147 | E20: =(((((Operating!$E$10*Operating!$E$11*Operating!$E$12*$B$9)*(1-Operating!$E$14)-Operating!$E$10*Operating!$E$13-Operating!$E$16)-MAX(0,((Operating!$E$10*Operating!$E$11*Operating!$E$12*$B$9)*(1-Operating!$E$14)-Operating!$E$10*Operating!$E$13-Operating!$E$16))*Operating!$E$15)+Operating!$E$16-Operating!$E$17-Operating!$E$18-Operating!$E$19)*Operating!$B$5-Operating!$E$20+IF(3=Operating!$B$7,Operating!$B$6,0))/(1+C7)^3 -> 74976062 | F20: =(((((Operating!$F$10*Operating!$F$11*Operating!$F$12*$B$9)*(1-Operating!$F$14)-Operating!$F$10*Operating!$F$13-Operating!$F$16)-MAX(0,((Operating!$F$10*Operating!$F$11*Operating!$F$12*$B$9)*(1-Operating!$F$14)-Operating!$F$10*Operating!$F$13-Operating!$F$16))*Operating!$F$15)+Operating!$F$16-Operating!$F$17-Operating!$F$18-Operating!$F$19)*Operating!$B$5-Operating!$F$20+IF(4=Operating!$B$7,Operating!$B$6,0))/(1+C7)^4 -> 69422280 | G20: =(((((Operating!$G$10*Operating!$G$11*Operating!$G$12*$B$9)*(1-Operating!$G$14)-Operating!$G$10*Operating!$G$13-Operating!$G$16)-MAX(0,((Operating!$G$10*Operating!$G$11*Operating!$G$12*$B$9)*(1-Operating!$G$14)-Operating!$G$10*Operating!$G$13-Operating!$G$16))*Operating!$G$15)+Operating!$G$16-Operating!$G$17-Operating!$G$18-Operating!$G$19)*Operating!$B$5-Operating!$G$20+IF(5=Operating!$B$7,Operating!$B$6,0))/(1+C7)^5 -> 30250729 | H20: =(((((Operating!$H$10*Operating!$H$11*Operating!$H$12*$B$9)*(1-Operating!$H$14)-Operating!$H$10*Operating!$H$13-Operating!$H$16)-MAX(0,((Operating!$H$10*Operating!$H$11*Operating!$H$12*$B$9)*(1-Operating!$H$14)-Operating!$H$10*Operating!$H$13-Operating!$H$16))*Operating!$H$15)+Operating!$H$16-Operating!$H$17-Operating!$H$18-Operating!$H$19)*Operating!$B$5-Operating!$H$20+IF(6=Operating!$B$7,Operating!$B$6,0))/(1+C7)^6 -> 0 | I20: =(((((Operating!$I$10*Operating!$I$11*Operating!$I$12*$B$9)*(1-Operating!$I$14)-Operating!$I$10*Operating!$I$13-Operating!$I$16)-MAX(0,((Operating!$I$10*Operating!$I$11*Operating!$I$12*$B$9)*(1-Operating!$I$14)-Operating!$I$10*Operating!$I$13-Operating!$I$16))*Operating!$I$15)+Operating!$I$16-Operating!$I$17-Operating!$I$18-Operating!$I$19)*Operating!$B$5-Operating!$I$20+IF(7=Operating!$B$7,Operating!$B$6,0))/(1+C7)^7 -> 0
A21: Driver 1.0× / rate column 2 | C21: =(((((Operating!$C$10*Operating!$C$11*Operating!$C$12*$B$9)*(1-Operating!$C$14)-Operating!$C$10*Operating!$C$13-Operating!$C$16)-MAX(0,((Operating!$C$10*Operating!$C$11*Operating!$C$12*$B$9)*(1-Operating!$C$14)-Operating!$C$10*Operating!$C$13-Operating!$C$16))*Operating!$C$15)+Operating!$C$16-Operating!$C$17-Operating!$C$18-Operating!$C$19)*Operating!$B$5-Operating!$C$20+IF(1=Operating!$B$7,Operating!$B$6,0))/(1+D7)^1 -> 85862041 | D21: =(((((Operating!$D$10*Operating!$D$11*Operating!$D$12*$B$9)*(1-Operating!$D$14)-Operating!$D$10*Operating!$D$13-Operating!$D$16)-MAX(0,((Operating!$D$10*Operating!$D$11*Operating!$D$12*$B$9)*(1-Operating!$D$14)-Operating!$D$10*Operating!$D$13-Operating!$D$16))*Operating!$D$15)+Operating!$D$16-Operating!$D$17-Operating!$D$18-Operating!$D$19)*Operating!$B$5-Operating!$D$20+IF(2=Operating!$B$7,Operating!$B$6,0))/(1+D7)^2 -> 78056401 | E21: =(((((Operating!$E$10*Operating!$E$11*Operating!$E$12*$B$9)*(1-Operating!$E$14)-Operating!$E$10*Operating!$E$13-Operating!$E$16)-MAX(0,((Operating!$E$10*Operating!$E$11*Operating!$E$12*$B$9)*(1-Operating!$E$14)-Operating!$E$10*Operating!$E$13-Operating!$E$16))*Operating!$E$15)+Operating!$E$16-Operating!$E$17-Operating!$E$18-Operating!$E$19)*Operating!$B$5-Operating!$E$20+IF(3=Operating!$B$7,Operating!$B$6,0))/(1+D7)^3 -> 70960364 | F21: =(((((Operating!$F$10*Operating!$F$11*Operating!$F$12*$B$9)*(1-Operating!$F$14)-Operating!$F$10*Operating!$F$13-Operating!$F$16)-MAX(0,((Operating!$F$10*Operating!$F$11*Operating!$F$12*$B$9)*(1-Operating!$F$14)-Operating!$F$10*Operating!$F$13-Operating!$F$16))*Operating!$F$15)+Operating!$F$16-Operating!$F$17-Operating!$F$18-Operating!$F$19)*Operating!$B$5-Operating!$F$20+IF(4=Operating!$B$7,Operating!$B$6,0))/(1+D7)^4 -> 64509422 | G21: =(((((Operating!$G$10*Operating!$G$11*Operating!$G$12*$B$9)*(1-Operating!$G$14)-Operating!$G$10*Operating!$G$13-Operating!$G$16)-MAX(0,((Operating!$G$10*Operating!$G$11*Operating!$G$12*$B$9)*(1-Operating!$G$14)-Operating!$G$10*Operating!$G$13-Operating!$G$16))*Operating!$G$15)+Operating!$G$16-Operating!$G$17-Operating!$G$18-Operating!$G$19)*Operating!$B$5-Operating!$G$20+IF(5=Operating!$B$7,Operating!$B$6,0))/(1+D7)^5 -> 27598863 | H21: =(((((Operating!$H$10*Operating!$H$11*Operating!$H$12*$B$9)*(1-Operating!$H$14)-Operating!$H$10*Operating!$H$13-Operating!$H$16)-MAX(0,((Operating!$H$10*Operating!$H$11*Operating!$H$12*$B$9)*(1-Operating!$H$14)-Operating!$H$10*Operating!$H$13-Operating!$H$16))*Operating!$H$15)+Operating!$H$16-Operating!$H$17-Operating!$H$18-Operating!$H$19)*Operating!$B$5-Operating!$H$20+IF(6=Operating!$B$7,Operating!$B$6,0))/(1+D7)^6 -> 0 | I21: =(((((Operating!$I$10*Operating!$I$11*Operating!$I$12*$B$9)*(1-Operating!$I$14)-Operating!$I$10*Operating!$I$13-Operating!$I$16)-MAX(0,((Operating!$I$10*Operating!$I$11*Operating!$I$12*$B$9)*(1-Operating!$I$14)-Operating!$I$10*Operating!$I$13-Operating!$I$16))*Operating!$I$15)+Operating!$I$16-Operating!$I$17-Operating!$I$18-Operating!$I$19)*Operating!$B$5-Operating!$I$20+IF(7=Operating!$B$7,Operating!$B$6,0))/(1+D7)^7 -> 0
A22: Driver 1.0× / rate column 3 | C22: =(((((Operating!$C$10*Operating!$C$11*Operating!$C$12*$B$9)*(1-Operating!$C$14)-Operating!$C$10*Operating!$C$13-Operating!$C$16)-MAX(0,((Operating!$C$10*Operating!$C$11*Operating!$C$12*$B$9)*(1-Operating!$C$14)-Operating!$C$10*Operating!$C$13-Operating!$C$16))*Operating!$C$15)+Operating!$C$16-Operating!$C$17-Operating!$C$18-Operating!$C$19)*Operating!$B$5-Operating!$C$20+IF(1=Operating!$B$7,Operating!$B$6,0))/(1+E7)^1 -> 84328790 | D22: =(((((Operating!$D$10*Operating!$D$11*Operating!$D$12*$B$9)*(1-Operating!$D$14)-Operating!$D$10*Operating!$D$13-Operating!$D$16)-MAX(0,((Operating!$D$10*Operating!$D$11*Operating!$D$12*$B$9)*(1-Operating!$D$14)-Operating!$D$10*Operating!$D$13-Operating!$D$16))*Operating!$D$15)+Operating!$D$16-Operating!$D$17-Operating!$D$18-Operating!$D$19)*Operating!$B$5-Operating!$D$20+IF(2=Operating!$B$7,Operating!$B$6,0))/(1+E7)^2 -> 75293563 | E22: =(((((Operating!$E$10*Operating!$E$11*Operating!$E$12*$B$9)*(1-Operating!$E$14)-Operating!$E$10*Operating!$E$13-Operating!$E$16)-MAX(0,((Operating!$E$10*Operating!$E$11*Operating!$E$12*$B$9)*(1-Operating!$E$14)-Operating!$E$10*Operating!$E$13-Operating!$E$16))*Operating!$E$15)+Operating!$E$16-Operating!$E$17-Operating!$E$18-Operating!$E$19)*Operating!$B$5-Operating!$E$20+IF(3=Operating!$B$7,Operating!$B$6,0))/(1+E7)^3 -> 67226395 | F22: =(((((Operating!$F$10*Operating!$F$11*Operating!$F$12*$B$9)*(1-Operating!$F$14)-Operating!$F$10*Operating!$F$13-Operating!$F$16)-MAX(0,((Operating!$F$10*Operating!$F$11*Operating!$F$12*$B$9)*(1-Operating!$F$14)-Operating!$F$10*Operating!$F$13-Operating!$F$16))*Operating!$F$15)+Operating!$F$16-Operating!$F$17-Operating!$F$18-Operating!$F$19)*Operating!$B$5-Operating!$F$20+IF(4=Operating!$B$7,Operating!$B$6,0))/(1+E7)^4 -> 60023567 | G22: =(((((Operating!$G$10*Operating!$G$11*Operating!$G$12*$B$9)*(1-Operating!$G$14)-Operating!$G$10*Operating!$G$13-Operating!$G$16)-MAX(0,((Operating!$G$10*Operating!$G$11*Operating!$G$12*$B$9)*(1-Operating!$G$14)-Operating!$G$10*Operating!$G$13-Operating!$G$16))*Operating!$G$15)+Operating!$G$16-Operating!$G$17-Operating!$G$18-Operating!$G$19)*Operating!$B$5-Operating!$G$20+IF(5=Operating!$B$7,Operating!$B$6,0))/(1+E7)^5 -> 25221128 | H22: =(((((Operating!$H$10*Operating!$H$11*Operating!$H$12*$B$9)*(1-Operating!$H$14)-Operating!$H$10*Operating!$H$13-Operating!$H$16)-MAX(0,((Operating!$H$10*Operating!$H$11*Operating!$H$12*$B$9)*(1-Operating!$H$14)-Operating!$H$10*Operating!$H$13-Operating!$H$16))*Operating!$H$15)+Operating!$H$16-Operating!$H$17-Operating!$H$18-Operating!$H$19)*Operating!$B$5-Operating!$H$20+IF(6=Operating!$B$7,Operating!$B$6,0))/(1+E7)^6 -> 0 | I22: =(((((Operating!$I$10*Operating!$I$11*Operating!$I$12*$B$9)*(1-Operating!$I$14)-Operating!$I$10*Operating!$I$13-Operating!$I$16)-MAX(0,((Operating!$I$10*Operating!$I$11*Operating!$I$12*$B$9)*(1-Operating!$I$14)-Operating!$I$10*Operating!$I$13-Operating!$I$16))*Operating!$I$15)+Operating!$I$16-Operating!$I$17-Operating!$I$18-Operating!$I$19)*Operating!$B$5-Operating!$I$20+IF(7=Operating!$B$7,Operating!$B$6,0))/(1+E7)^7 -> 0
A23: Driver 1.2× / rate column 1 | C23: =(((((Operating!$C$10*Operating!$C$11*Operating!$C$12*$B$10)*(1-Operating!$C$14)-Operating!$C$10*Operating!$C$13-Operating!$C$16)-MAX(0,((Operating!$C$10*Operating!$C$11*Operating!$C$12*$B$10)*(1-Operating!$C$14)-Operating!$C$10*Operating!$C$13-Operating!$C$16))*Operating!$C$15)+Operating!$C$16-Operating!$C$17-Operating!$C$18-Operating!$C$19)*Operating!$B$5-Operating!$C$20+IF(1=Operating!$B$7,Operating!$B$6,0))/(1+C7)^1 -> 1.3409665e+08 | D23: =(((((Operating!$D$10*Operating!$D$11*Operating!$D$12*$B$10)*(1-Operating!$D$14)-Operating!$D$10*Operating!$D$13-Operating!$D$16)-MAX(0,((Operating!$D$10*Operating!$D$11*Operating!$D$12*$B$10)*(1-Operating!$D$14)-Operating!$D$10*Operating!$D$13-Operating!$D$16))*Operating!$D$15)+Operating!$D$16-Operating!$D$17-Operating!$D$18-Operating!$D$19)*Operating!$B$5-Operating!$D$20+IF(2=Operating!$B$7,Operating!$B$6,0))/(1+C7)^2 -> 1.2416357e+08 | E23: =(((((Operating!$E$10*Operating!$E$11*Operating!$E$12*$B$10)*(1-Operating!$E$14)-Operating!$E$10*Operating!$E$13-Operating!$E$16)-MAX(0,((Operating!$E$10*Operating!$E$11*Operating!$E$12*$B$10)*(1-Operating!$E$14)-Operating!$E$10*Operating!$E$13-Operating!$E$16))*Operating!$E$15)+Operating!$E$16-Operating!$E$17-Operating!$E$18-Operating!$E$19)*Operating!$B$5-Operating!$E$20+IF(3=Operating!$B$7,Operating!$B$6,0))/(1+C7)^3 -> 1.1496626e+08 | F23: =(((((Operating!$F$10*Operating!$F$11*Operating!$F$12*$B$10)*(1-Operating!$F$14)-Operating!$F$10*Operating!$F$13-Operating!$F$16)-MAX(0,((Operating!$F$10*Operating!$F$11*Operating!$F$12*$B$10)*(1-Operating!$F$14)-Operating!$F$10*Operating!$F$13-Operating!$F$16))*Operating!$F$15)+Operating!$F$16-Operating!$F$17-Operating!$F$18-Operating!$F$19)*Operating!$B$5-Operating!$F$20+IF(4=Operating!$B$7,Operating!$B$6,0))/(1+C7)^4 -> 1.0645025e+08 | G23: =(((((Operating!$G$10*Operating!$G$11*Operating!$G$12*$B$10)*(1-Operating!$G$14)-Operating!$G$10*Operating!$G$13-Operating!$G$16)-MAX(0,((Operating!$G$10*Operating!$G$11*Operating!$G$12*$B$10)*(1-Operating!$G$14)-Operating!$G$10*Operating!$G$13-Operating!$G$16))*Operating!$G$15)+Operating!$G$16-Operating!$G$17-Operating!$G$18-Operating!$G$19)*Operating!$B$5-Operating!$G$20+IF(5=Operating!$B$7,Operating!$B$6,0))/(1+C7)^5 -> 64535882 | H23: =(((((Operating!$H$10*Operating!$H$11*Operating!$H$12*$B$10)*(1-Operating!$H$14)-Operating!$H$10*Operating!$H$13-Operating!$H$16)-MAX(0,((Operating!$H$10*Operating!$H$11*Operating!$H$12*$B$10)*(1-Operating!$H$14)-Operating!$H$10*Operating!$H$13-Operating!$H$16))*Operating!$H$15)+Operating!$H$16-Operating!$H$17-Operating!$H$18-Operating!$H$19)*Operating!$B$5-Operating!$H$20+IF(6=Operating!$B$7,Operating!$B$6,0))/(1+C7)^6 -> 0 | I23: =(((((Operating!$I$10*Operating!$I$11*Operating!$I$12*$B$10)*(1-Operating!$I$14)-Operating!$I$10*Operating!$I$13-Operating!$I$16)-MAX(0,((Operating!$I$10*Operating!$I$11*Operating!$I$12*$B$10)*(1-Operating!$I$14)-Operating!$I$10*Operating!$I$13-Operating!$I$16))*Operating!$I$15)+Operating!$I$16-Operating!$I$17-Operating!$I$18-Operating!$I$19)*Operating!$B$5-Operating!$I$20+IF(7=Operating!$B$7,Operating!$B$6,0))/(1+C7)^7 -> 0
A24: Driver 1.2× / rate column 2 | C24: =(((((Operating!$C$10*Operating!$C$11*Operating!$C$12*$B$10)*(1-Operating!$C$14)-Operating!$C$10*Operating!$C$13-Operating!$C$16)-MAX(0,((Operating!$C$10*Operating!$C$11*Operating!$C$12*$B$10)*(1-Operating!$C$14)-Operating!$C$10*Operating!$C$13-Operating!$C$16))*Operating!$C$15)+Operating!$C$16-Operating!$C$17-Operating!$C$18-Operating!$C$19)*Operating!$B$5-Operating!$C$20+IF(1=Operating!$B$7,Operating!$B$6,0))/(1+D7)^1 -> 1.3165853e+08 | D24: =(((((Operating!$D$10*Operating!$D$11*Operating!$D$12*$B$10)*(1-Operating!$D$14)-Operating!$D$10*Operating!$D$13-Operating!$D$16)-MAX(0,((Operating!$D$10*Operating!$D$11*Operating!$D$12*$B$10)*(1-Operating!$D$14)-Operating!$D$10*Operating!$D$13-Operating!$D$16))*Operating!$D$15)+Operating!$D$16-Operating!$D$17-Operating!$D$18-Operating!$D$19)*Operating!$B$5-Operating!$D$20+IF(2=Operating!$B$7,Operating!$B$6,0))/(1+D7)^2 -> 1.1968957e+08 | E24: =(((((Operating!$E$10*Operating!$E$11*Operating!$E$12*$B$10)*(1-Operating!$E$14)-Operating!$E$10*Operating!$E$13-Operating!$E$16)-MAX(0,((Operating!$E$10*Operating!$E$11*Operating!$E$12*$B$10)*(1-Operating!$E$14)-Operating!$E$10*Operating!$E$13-Operating!$E$16))*Operating!$E$15)+Operating!$E$16-Operating!$E$17-Operating!$E$18-Operating!$E$19)*Operating!$B$5-Operating!$E$20+IF(3=Operating!$B$7,Operating!$B$6,0))/(1+D7)^3 -> 1.088087e+08 | F24: =(((((Operating!$F$10*Operating!$F$11*Operating!$F$12*$B$10)*(1-Operating!$F$14)-Operating!$F$10*Operating!$F$13-Operating!$F$16)-MAX(0,((Operating!$F$10*Operating!$F$11*Operating!$F$12*$B$10)*(1-Operating!$F$14)-Operating!$F$10*Operating!$F$13-Operating!$F$16))*Operating!$F$15)+Operating!$F$16-Operating!$F$17-Operating!$F$18-Operating!$F$19)*Operating!$B$5-Operating!$F$20+IF(4=Operating!$B$7,Operating!$B$6,0))/(1+D7)^4 -> 98917002 | G24: =(((((Operating!$G$10*Operating!$G$11*Operating!$G$12*$B$10)*(1-Operating!$G$14)-Operating!$G$10*Operating!$G$13-Operating!$G$16)-MAX(0,((Operating!$G$10*Operating!$G$11*Operating!$G$12*$B$10)*(1-Operating!$G$14)-Operating!$G$10*Operating!$G$13-Operating!$G$16))*Operating!$G$15)+Operating!$G$16-Operating!$G$17-Operating!$G$18-Operating!$G$19)*Operating!$B$5-Operating!$G$20+IF(5=Operating!$B$7,Operating!$B$6,0))/(1+D7)^5 -> 58878482 | H24: =(((((Operating!$H$10*Operating!$H$11*Operating!$H$12*$B$10)*(1-Operating!$H$14)-Operating!$H$10*Operating!$H$13-Operating!$H$16)-MAX(0,((Operating!$H$10*Operating!$H$11*Operating!$H$12*$B$10)*(1-Operating!$H$14)-Operating!$H$10*Operating!$H$13-Operating!$H$16))*Operating!$H$15)+Operating!$H$16-Operating!$H$17-Operating!$H$18-Operating!$H$19)*Operating!$B$5-Operating!$H$20+IF(6=Operating!$B$7,Operating!$B$6,0))/(1+D7)^6 -> 0 | I24: =(((((Operating!$I$10*Operating!$I$11*Operating!$I$12*$B$10)*(1-Operating!$I$14)-Operating!$I$10*Operating!$I$13-Operating!$I$16)-MAX(0,((Operating!$I$10*Operating!$I$11*Operating!$I$12*$B$10)*(1-Operating!$I$14)-Operating!$I$10*Operating!$I$13-Operating!$I$16))*Operating!$I$15)+Operating!$I$16-Operating!$I$17-Operating!$I$18-Operating!$I$19)*Operating!$B$5-Operating!$I$20+IF(7=Operating!$B$7,Operating!$B$6,0))/(1+D7)^7 -> 0
A25: Driver 1.2× / rate column 3 | C25: =(((((Operating!$C$10*Operating!$C$11*Operating!$C$12*$B$10)*(1-Operating!$C$14)-Operating!$C$10*Operating!$C$13-Operating!$C$16)-MAX(0,((Operating!$C$10*Operating!$C$11*Operating!$C$12*$B$10)*(1-Operating!$C$14)-Operating!$C$10*Operating!$C$13-Operating!$C$16))*Operating!$C$15)+Operating!$C$16-Operating!$C$17-Operating!$C$18-Operating!$C$19)*Operating!$B$5-Operating!$C$20+IF(1=Operating!$B$7,Operating!$B$6,0))/(1+E7)^1 -> 1.2930749e+08 | D25: =(((((Operating!$D$10*Operating!$D$11*Operating!$D$12*$B$10)*(1-Operating!$D$14)-Operating!$D$10*Operating!$D$13-Operating!$D$16)-MAX(0,((Operating!$D$10*Operating!$D$11*Operating!$D$12*$B$10)*(1-Operating!$D$14)-Operating!$D$10*Operating!$D$13-Operating!$D$16))*Operating!$D$15)+Operating!$D$16-Operating!$D$17-Operating!$D$18-Operating!$D$19)*Operating!$B$5-Operating!$D$20+IF(2=Operating!$B$7,Operating!$B$6,0))/(1+E7)^2 -> 1.1545311e+08 | E25: =(((((Operating!$E$10*Operating!$E$11*Operating!$E$12*$B$10)*(1-Operating!$E$14)-Operating!$E$10*Operating!$E$13-Operating!$E$16)-MAX(0,((Operating!$E$10*Operating!$E$11*Operating!$E$12*$B$10)*(1-Operating!$E$14)-Operating!$E$10*Operating!$E$13-Operating!$E$16))*Operating!$E$15)+Operating!$E$16-Operating!$E$17-Operating!$E$18-Operating!$E$19)*Operating!$B$5-Operating!$E$20+IF(3=Operating!$B$7,Operating!$B$6,0))/(1+E7)^3 -> 1.0308314e+08 | F25: =(((((Operating!$F$10*Operating!$F$11*Operating!$F$12*$B$10)*(1-Operating!$F$14)-Operating!$F$10*Operating!$F$13-Operating!$F$16)-MAX(0,((Operating!$F$10*Operating!$F$11*Operating!$F$12*$B$10)*(1-Operating!$F$14)-Operating!$F$10*Operating!$F$13-Operating!$F$16))*Operating!$F$15)+Operating!$F$16-Operating!$F$17-Operating!$F$18-Operating!$F$19)*Operating!$B$5-Operating!$F$20+IF(4=Operating!$B$7,Operating!$B$6,0))/(1+E7)^4 -> 92038514 | G25: =(((((Operating!$G$10*Operating!$G$11*Operating!$G$12*$B$10)*(1-Operating!$G$14)-Operating!$G$10*Operating!$G$13-Operating!$G$16)-MAX(0,((Operating!$G$10*Operating!$G$11*Operating!$G$12*$B$10)*(1-Operating!$G$14)-Operating!$G$10*Operating!$G$13-Operating!$G$16))*Operating!$G$15)+Operating!$G$16-Operating!$G$17-Operating!$G$18-Operating!$G$19)*Operating!$B$5-Operating!$G$20+IF(5=Operating!$B$7,Operating!$B$6,0))/(1+E7)^5 -> 53805902 | H25: =(((((Operating!$H$10*Operating!$H$11*Operating!$H$12*$B$10)*(1-Operating!$H$14)-Operating!$H$10*Operating!$H$13-Operating!$H$16)-MAX(0,((Operating!$H$10*Operating!$H$11*Operating!$H$12*$B$10)*(1-Operating!$H$14)-Operating!$H$10*Operating!$H$13-Operating!$H$16))*Operating!$H$15)+Operating!$H$16-Operating!$H$17-Operating!$H$18-Operating!$H$19)*Operating!$B$5-Operating!$H$20+IF(6=Operating!$B$7,Operating!$B$6,0))/(1+E7)^6 -> 0 | I25: =(((((Operating!$I$10*Operating!$I$11*Operating!$I$12*$B$10)*(1-Operating!$I$14)-Operating!$I$10*Operating!$I$13-Operating!$I$16)-MAX(0,((Operating!$I$10*Operating!$I$11*Operating!$I$12*$B$10)*(1-Operating!$I$14)-Operating!$I$10*Operating!$I$13-Operating!$I$16))*Operating!$I$15)+Operating!$I$16-Operating!$I$17-Operating!$I$18-Operating!$I$19)*Operating!$B$5-Operating!$I$20+IF(7=Operating!$B$7,Operating!$B$6,0))/(1+E7)^7 -> 0

Sheet Checks
A1: asx-mlx / Checks
A5: Valid active scenario | B5: =IF(OR(Assumptions!B4="bear",Assumptions!B4="base",Assumptions!B4="bull"),"PASS","FAIL") -> PASS
A6: Positive diluted shares | B6: =IF(Assumptions!$B$10>0,"PASS","FAIL") -> PASS
A7: Equity bridge reconciliation | B7: =IF(ABS(Valuation!B9-(Valuation!B5+Valuation!B6+Valuation!B7-Valuation!B8))<0.01,"PASS","FAIL") -> PASS
A8: Central sensitivity reconciliation | B8: =IF(ABS(Sensitivities!D9-Valuation!B11)<0.000001,"PASS","FAIL") -> PASS
A9: Reference quote pair | B9: =IF(OR(AND(Assumptions!$B$11="",Assumptions!$B$13=""),AND(ISNUMBER(Assumptions!$B$11),Assumptions!$B$11>0,Assumptions!$B$13<>"")),"PASS","FAIL") -> PASS
A10: Ownership range | B10: =IF(AND(Operating!$B$5>=0,Operating!$B$5<=1),"PASS","FAIL") -> PASS
A13: Workbook checks are structural, not evidence approval. Import validates all scenarios, declared units, formula integrity and financial constraints independently. Any formula changes require a new model design review.

Sheet Readme
A1: asx-mlx / Readme
A5: WORKFLOW | Read the Markdown memo first. Excel is the editable detailed model. Change blue assumptions, recalculate, save and import to create a new validated research snapshot. Existing snapshots remain immutable.
A9: MODEL | One active scenario drives all formulas. Select bear/base/bull in Assumptions!B4. Forecast horizons are fixed by the source model; shorter cases have zero inputs after their final period.
A13: UNITS | Calculations use absolute currency amounts, not millions. Input provenance comments identify unit, source, author and rationale. Historical rows retain original reported units; normalize before using them in assumptions.
A17: OWNERSHIP | Whole-operation cash flow is multiplied by ownership once. Corporate costs and residual value are company-attributable. Cash, debt and other assets are added at company level.
A21: METHOD | Annual end-period discounting; explicit residual only. Positive EBIT tax floor; no deferred tax or loss carryforwards. Cash excludes debt repayment, funding and dividends. This is not an integrated income statement, balance sheet and cash-flow forecast.
A25: EDITING | Blue inputs are editable. Green formulas link sheets. Black formulas calculate locally. Keep formulas and metadata intact. Synchronization records changed inputs as analyst overrides. Explain their source and rationale in the research memo; formula edits are rejected.
A29: EVIDENCE | A professional workbook layout does not upgrade uncertain evidence. Missing current quotes, mine-life support, payable sales or capital structure remain research gaps. Model values are not recommendations.
A33: KNOWN LIMITATIONS
A35: ILLUSTRATIVE IMPUTED-REVENUE SENSITIVITY ONLY. This is not an actionable fair-value estimate or an investment recommendation.
A39: Production is used solely as the company-style imputed-revenue proxy (100% produced tin sold/paid); it is NOT reported payable sales. The workbook labels it production_tonnes_proxy. Realized payable sales, inventory, settlement timing and revenue must replace this proxy before valuation.
A43: The baseline price AUD63,760/t is the reported trailing-12-month LME-imputed price, NOT realized tin sales price. Scenario price and volume levels are analyst stress assumptions, not company guidance.
... A83: Historical statement summaries now include FY2025 and FY2024 as reported in the 2025 annual report. This is a selected comparative history, not a full three-year normalization or a linked three-statement forecast. Group consolidated actuals must not be compared directly with unscaled whole-operation model rows.

Sheet _Model
A1: investing-excel-v1
A2: {"schema_version":1,"baseline":{"company_id":"asx-mlx","model_type":"finite_mine","purpose":"illustrative_sensitivity","synthetic":false,"currency":"AUD","valuation_date":"2026-09-20","reference_price":null,"quote_date":null,"cash":374000000.0,"debt":3285000.0,"other_assets":0.0,"diluted_shares":886391538.0,"historical":[{"entity":"Metals X Group","metric":"cash_and_cash_equivalents","value":293606000.0,"unit":"AUD","currency":"AUD","period":"2025-12-31","publication_date":"2026-03-25","source":"https://www.metalsx.com.au/wp-content/uploads/2026/03/MLX-Annual-Report-31-December-2025.pdf#page=25","page":"25","basis":"reported","ownership_basis":"consolidated"},{"entity":"Metals X Group","metric":"current_interest_bearing_liabilities","value":2849000.0,"unit":"AUD","currency":"AUD","period":"2025-12-31","publication_date":"2026-03-25","source":"https://www.metalsx.com.au/wp-content/uploads/2026/03/MLX-Annual-Report-31-December-2025.pdf#page=25","page":"25","basis":"reported","ownership_basis":"consolidated"},{"entity":"Metals X Group","metric":"noncurrent_interest_bearing_liabilities","value":436000.0,"unit":"AUD","currency":"AUD","period":"2025-12-31","publication_date":"2026-03-25","source":"https://www.metalsx.com.au/wp-content/uploads/2026/03/MLX-Annual-Report-31-December-2025.pdf#page=25","page":"25","basis":"reported","ownership_basis":"consolidated"},{"entity":"Metals X Limited","metric":"issued_ordinary_shares","value":886391538.0,"unit":"shares","currency":null,"period":"2025-12-31","publication_date":"2026-03-25","source":"https://www.metalsx.com.au/wp-content/uploads/2026/03/MLX-Annual-Report-31-December-2025.pdf#page=62","page":"62","basis":"reported","ownership_basis":"consolidated"},{"entity":"Metals X Group","metric":"rehabilitation_provision_present_value","value":33035000.0,"unit":"AUD","currency":"AUD","period":"2025-12-31","publication_date":"2026-03-25","source":"https://www.metalsx.com.au/wp-content/uploads/2026/03/MLX-Annual-Report-31-December-2025.pdf#page=60","page":"60","basis":"reported","ownership_basis":"consolidated"},{"entity":"Metals X Group","metric":"net_operating_cash_flow","value":128323000.0,"unit":"AUD","currency":"AUD","period":"FY2025","publication_date":"2026-03-25","source":"https://www.metalsx.com.au/wp-content/uploads/2026/03/MLX-Annual-Report-31-December-2025.pdf#page=26","page":"26","basis":"reported","ownership_basis":"consolidated"},{"entity":"Metals X Group","metric":"cash_paid_property_plant_equipment","value":13747000.0,"unit":"AUD","currency":"AUD","period":"FY2025","publication_date":"2026-03-25","source":"https://www.metalsx.com.au/wp-content/uploads/2026/03/MLX-Annual-Report-31-December-2025.pdf#page=26","page":"26","basis":"reported","ownership_basis":"consolidated"},{"entity":"Metals X Group","metric":"cash_paid_mine_properties_development","value":22211000.0,"unit":"AUD","currency":"AUD","period":"FY2025","publication_date":"2026-03-25","source":"https://www.metalsx.com.au/wp-content/uploads/2026/03/MLX-Annual-Report-31-December-2025.pdf#page=26","page":"26","basis":"reported","ownership_basis":"consolidated"},{"entity":"Renison Tin Operation","metric":"tin_in_concentrate_produced","value":10748.0,"unit":"tonnes_tin","currency":null,"period":"FY2025","publication_date":"2026-03-25","source":"https://www.metalsx.com.au/wp-content/uploads/2026/03/MLX-Annual-Report-31-December-2025.pdf#page=9","page":"9","basis":"reported","ownership_basis":"whole_operation"},{"entity":"Renison Tin Operation","metric":"ownership_interest","value":0.5,"unit":"fraction","currency":null,"period":"2026-Q2","publication_date":"2026-07-27","source":"https://www.metalsx.com.au/wp-content/uploads/2026/07/02_MLX_Quarterly-Report_30-June-2026_Final.pdf#page=2","page":"2","basis":"reported","ownership_basis":"whole_operation"},{"entity":"Renison Tin Operation","metric":"tin_in_concentrate_produced","value":2809.0,"unit":"tonnes_tin","currency":null,"period":"2026-Q2","publication_date":"2026-07-27","source":"https://www.metalsx.com.au/wp-content/uploads/2026/07/02_MLX_Quarterly-Report_30-June-2026_Final.pdf#page=2","page":"2","basis":"reported","ownership_basis":"whole_operation"},{"entity":"Renison Tin Operation","metric":"tin_in_concentrate_produced","value":11287.0,"unit":"tonnes_tin","currency":null,"period":"TTM-ended-2026-06-30","publication_date":"2026-07-27","source":"https://www.metalsx.com.au/wp-content/uploads/2026/07/02_MLX_Quarterly-Report_30-June-2026_Final.pdf#page=2","page":"2","basis":"reported","ownership_basis":"whole_operation"},{"entity":"Renison Tin Operation","metric":"imputed_tin_price","value":73834.0,"unit":"AUD_per_tonne_tin","currency":"AUD","period":"2026-Q2","publication_date":"2026-07-27","source":"https://www.metalsx.com.au/wp-content/uploads/2026/07/02_MLX_Quarterly-Report_30-June-2026_Final.pdf#page=2","page":"2","basis":"reported","ownership_basis":"whole_operation"},{"entity":"Renison Tin Operation","metric":"imputed_tin_price","value":63760.0,"unit":"AUD_per_tonne_tin","currency":"AUD","period":"TTM-ended-2026-06-30","publication_date":"2026-07-27","source":"https://www.metalsx.com.au/wp-content/uploads/2026/07/02_MLX_Quarterly-Report_30-June-2026_Final.pdf#page=2","page":"2","basis":"reported","ownership_basis":"whole_operation"},{"entity":"Renison Tin Operation","metric":"c1_cash_production_cost","value":20251.0,"unit":"AUD_per_tonne_tin","currency":"AUD","period":"2026-Q2","publication_date":"2026-07-27","source":"https://www.metalsx.com.au/wp-content/uploads/2026/07/02_MLX_Quarterly-Report_30-June-2026_Final.pdf#page=2","page":"2","basis":"reported","ownership_basis":"whole_operation"},{"entity":"Renison Tin Operation","metric":"c1_cash_production_cost","value":19349.0,"unit":"AUD_per_tonne_tin","currency":"AUD","period":"TTM-ended-2026-06-30","publication_date":"2026-07-27","source":"https://www.metalsx.com.au/wp-content/uploads/2026/07/02_MLX_Quarterly-Report_30-June-2026_Final.pdf#page=2","page":"2","basis":"reported","ownership_basis":"whole_operation"},{"entity":"Renison Tin Operation","metric":"imputed_sales_and_marketing_cost","value":8758.0,"unit":"AUD_per_tonne_tin","currency":"AUD","period":"2026-Q2","publication_date":"2026-07-27","source":"https://www.metalsx.com.au/wp-content/uploads/2026/07/02_MLX_Quarterly-Report_30-June-2026_Final.pdf#page=2","page":"2","basis":"reported","ownership_basis":"whole_operation"},{"entity":"Renison Tin Operation","metric":"all_in_sustaining_cost","value":34865.0,"unit":"AUD_per_tonne_tin","currency":"AUD","period":"2026-Q2","publication_date":"2026-07-27","source":"https://www.metalsx.com.au/wp-content/uploads/2026/07/02_MLX_Quarterly-Report_30-June-2026_Final.pdf#page=2","page":"2","basis":"reported","ownership_basis":"whole_operation"},{"entity":"Renison Tin Operation","metric":"capital_expenditure","value":23400000.0,"unit":"AUD","currency":"AUD","period":"2026-Q2","publication_date":"2026-07-27","source":"https://www.metalsx.com.au/wp-content/uploads/2026/07/02_MLX_Quarterly-Report_30-June-2026_Final.pdf#page=3","page":"3","basis":"reported","ownership_basis":"whole_operation"},{"entity":"Renison Tin Operation","metric":"sustaining_capital_expenditure","value":16450000.0,"unit":"AUD","currency":"AUD","period":"2026-Q2","publication_date":"2026-07-27","source":"https://www.metalsx.com.au/wp-content/uploads/2026/07/02_MLX_Quarterly-Report_30-June-2026_Final.pdf#page=3","page":"3","basis":"reported","ownership_basis":"whole_operation"},{"entity":"Renison Tin Operation","metric":"project_capital_expenditure","value":6950000.0,"unit":"AUD","currency":"AUD","period":"2026-Q2","publication_date":"2026-07-27","source":"https://www.metalsx.com.au/wp-content/uploads/2026/07/02_MLX_Quarterly-Report_30-June-2026_Final.pdf#page=3","page":"3","basis":"reported","ownership_basis":"whole_operation"},{"entity":"Metals X Group","metric":"cash_and_cash_equivalents","value":374000000.0,"unit":"AUD","currency":"AUD","period":"2026-06-30","publication_date":"2026-07-27","source":"https://www.metalsx.com.au/wp-content/uploads/2026/07/02_MLX_Quarterly-Report_30-June-2026_Final.pdf#page=9","page":"9","basis":"reported","ownership_basis":"consolidated"},{"entity":"Metals X Group","metric":"corporate_costs","value":560000.0,"unit":"AUD","currency":"AUD","period":"2026-Q2","publication_date":"2026-07-27","source":"https://www.metalsx.com.au/wp-content/uploads/2026/07/02_MLX_Quarterly-Report_30-June-2026_Final.pdf#page=8","page":"8","basis":"reported","ownership_basis":"consolidated"},{"entity":"Metals X Group","metric":"revenue","value":284999000.0,"unit":"AUD","currency":"AUD","period":"FY2025","publication_date":"2026-03-25","source":"https://www.metalsx.com.au/wp-content/uploads/2026/03/MLX-Annual-Report-31-December-2025.pdf#page=24","page":"24","basis":"reported","ownership_basis":"consolidated"},{"entity":"Metals X Group","metric":"revenue","value":218820000.0,"unit":"AUD","currency":"AUD","period":"FY2024","publication_date":"2026-03-25","source":"https://www.metalsx.com.au/wp-content/uploads/2026/03/MLX-Annual-Report-31-December-2025.pdf#page=24","page":"24","basis":"reported","ownership_basis":"consolidated"},{"entity":"Metals X Group","metric":"cost_of_sales","value":158275000.0,"unit":"AUD","currency":"AUD","period":"FY2025","publication_date":"2026-03-25","source":"https://www.metalsx.com.au/wp-content/uploads/2026/03/MLX-Annual-Report-31-December-2025.pdf#page=24","page":"24","basis":"reported","ownership_basis":"consolidated"},{"entity":"Metals X Group","metric":"cost_of_sales","value":123558000.0,"unit":"AUD","currency":"AUD","period":"FY2024","publication_date":"2026-03-25","source":"https://www.metalsx.com.au/wp-content/uploads/2026/03/MLX-Annual-Report-31-December-2025.pdf#page=24","page":"24","basis":"reported","ownership_basis":"consolidated"},{"entity":"Metals X Group","metric":"gross_profit","value":126724000.0,"unit":"AUD","currency":"AUD","period":"FY2025","publication_date":"2026-03-25","source":"https://www.metalsx.com.au/wp-content/uploads/2026/03/MLX-Annual-Report-31-December-2025.pdf#page=24","page":"24","basis":"reported","ownership_basis":"consolidated"},{"entity":"Metals X Group","metric":"gross_profit","value":95262000.0,"unit":"AUD","currency":"AUD","period":"FY2024","publication_date":"2026-03-25","source":"https://www.metalsx.com.au/wp-content/uploads/2026/03/MLX-Annual-Report-31-December-2025.pdf#page=24","page":"24","basis":"reported","ownership_basis":"consolidated"},{"entity":"Metals X Group","metric":"general_and_administrative_expenses","value":4212000.0,"unit":"AUD","currency":"AUD","period":"FY2025","publication_date":"2026-03-25","source":"https://www.metalsx.com.au/wp-content/uploads/2026/03/MLX-Annual-Report-31-December-2025.pdf#page=24","page":"24","basis":"reported","ownership_basis":"consolidated"},{"entity":"Metals X Group","metric":"general_and_administrative_expenses","value":2744000.0,"unit":"AUD","currency":"AUD","period":"FY2024","publication_date":"2026-03-25","source":"https://www.metalsx.com.au/wp-content/uploads/2026/03/MLX-Annual-Report-31-December-2025.pdf#page=24","page":"24","basis":"reported","ownership_basis":"consolidated"},{"entity":"Metals X Group","metric":"finance_costs","value":980000.0,"unit":"AUD","currency":"AUD","period":"FY2025","publication_date":"2026-03-25","source":"https://www.metalsx.com.au/wp-content/uploads/2026/03/MLX-Annual-Report-31-December-2025.pdf#page=24","page":"24","basis":"reported","ownership_basis":"consolidated"},{"entity":"Metals X Group","metric":"finance_costs","value":566000.0,"unit":"AUD","currency":"AUD","period":"FY2024","publication_date":"2026-03-25","source":"https://www.metalsx.com.au/wp-content/uploads/2026/03/MLX-Annual-Report-31-December-2025.pdf#page=24","page":"24","basis":"reported","ownership_basis":"consolidated"},{"entity":"Metals X Group","metric":"profit_before_tax","value":138275000.0,"unit":"AUD","currency":"AUD","period":"FY2025","publication_date":"2026-03-25","source":"https://www.metalsx.com.au/wp-content/uploads/2026/03/MLX-Annual-Report-31-December-2025.pdf#page=24","page":"24","basis":"reported","ownership_basis":"consolidated"},{"entity":"Metals X Group","metric":"profit_before_tax","value":120227000.0,"unit":"AUD","currency":"AUD","period":"FY2024","publication_date":"2026-03-25","source":"https://www.metalsx.com.au/wp-content/uploads/2026/03/MLX-Annual-Report-31-December-2025.pdf#page=24","page":"24","basis":"reported","ownership_basis":"consolidated"},{"entity":"Metals X Group","metric":"income_tax_expense","value":33670000.0,"unit":"AUD","currency":"AUD","period":"FY2025","publication_date":"2026-03-25","source":"https://www.metalsx.com.au/wp-content/uploads/2026/03/MLX-Annual-Report-31-December-2025.pdf#page=24","page":"24","basis":"reported","ownership_basis":"consolidated"},{"entity":"Metals X Group","metric":"income_tax_expense","value":17878000.0,"unit":"AUD","currency":"AUD","period":"FY2024","publication_date":"2026-03-25","source":"https://www.metalsx.com.au/wp-content/uploads/2026/03/MLX-Annual-Report-31-December-2025.pdf#page=24","page":"24","basis":"reported","ownership_basis":"consolidated"},{"entity":"Metals X Group","metric":"net_income","value":104605000.0,"unit":"AUD","currency":"AUD","period":"FY2025","publication_date":"2026-03-25","source":"https://www.metalsx.com.au/wp-content/uploads/2026/03/MLX-Annual-Report-31-December-2025.pdf#page=24","page":"24","basis":"reported","ownership_basis":"consolidated"},{"entity":"Metals X Group","metric":"net_income","value":102349000.0,"unit":"AUD","currency":"AUD","period":"FY2024","publication_date":"2026-03-25","source":"https://www.metalsx.com.au/wp-content/uploads/2026/03/MLX-Annual-Report-31-December-2025.pdf#page=24","page":"24","basis":"reported","ownership_basis":"consolidated"},{"entity":"Metals X Group","metric":"cash_and_cash_equivalents","value":220644000.0,"unit":"AUD","currency":"AUD","period":"2024-12-31","publication_date":"2026-03-25","source":"https://www.metalsx.com.au/wp-content/uploads/2026/03/MLX-Annual-Report-31-December-2025.pdf#page=25","page":"25","basis":"reported","ownership_basis":"consolidated"},{"entity":"Metals X Group","metric":"trade_and_other_receivables","value":36473000.0,"unit":"AUD","currency":"AUD","period":"2025-12-31","publication_date":"2026-03-25","source":"https://www.metalsx.com.au/wp-content/uploads/2026/03/MLX-Annual-Report-31-December-2025.pdf#page=25","page":"25","basis":"reported","ownership_basis":"consolidated"},{"entity":"Metals X Group","metric":"trade_and_other_receivables","value":8666000.0,"unit":"AUD","currency":"AUD","period":"2024-12-31","publication_date":"2026-03-25","source":"https://www.metalsx.com.au/wp-content/uploads/2026/03/MLX-Annual-Report-31-December-2025.pdf#page=25","page":"25","basis":"reported","ownership_basis":"consolidated"},{"entity":"Metals X Group","metric":"inventories","value":29488000.0,"unit":"AUD","currency":"AUD","period":"2025-12-31","publication_date":"2026-03-25","source":"https://www.metalsx.com.au/wp-content/uploads/2026/03/MLX-Annual-Report-31-December-2025.pdf#page=25","page":"25","basis":"reported","ownership_basis":"consolidated"},{"entity":"Metals X Group","metric":"inventories","value":37573000.0,"unit":"AUD","currency":"AUD","period":"2024-12-31","publication_date":"2026-03-25","source":"https://www.metalsx.com.au/wp-content/uploads/2026/03/MLX-Annual-Report-31-December-2025.pdf#page=25","page":"25","basis":"reported","ownership_basis":"consolidated"},{"entity":"Metals X Group","metric":"total_current_assets","value":363459000.0,"unit":"AUD","currency":"AUD","period":"2025-12-31","publication_date":"2026-03-25","source":"https://www.metalsx.com.au/wp-content/uploads/2026/03/MLX-Annual-Report-31-December-2025.pdf#page=25","page":"25","basis":"reported","ownership_basis":"consolidated"},{"entity":"Metals X Group","metric":"total_current_assets","value":271243000.0,"unit":"AUD","currency":"AUD","period":"2024-12-31","publication_date":"2026-03-25","source":"https://www.metalsx.com.au/wp-content/uploads/2026/03/MLX-Annual-Report-31-December-2025.pdf#page=25","page":"25","basis":"reported","ownership_basis":"consolidated"},{"entity":"Metals X Group","metric":"total_noncurrent_assets","value":255050000.0,"unit":"AUD","currency":"AUD","period":"2025-12-31","publication_date":"2026-03-25","source":"https://www.metalsx.com.au/wp-content/uploads/2026/03/MLX-Annual-Report-31-December-2025.pdf#page=25","page":"25","basis":"reported","ownership_basis":"consolidated"},{"entity":"Metals X Group","metric":"total_noncurrent_assets","value":233789000.0,"unit":"AUD","currency":"AUD","period":"2024-12-31","publication_date":"2026-03-25","source":"https://www.metalsx.com.au/wp-content/uploads/2026/03/MLX-Annual-Report-31-December-2025.pdf#page=25","page":"25","basis":"reported","ownership_basis":"consolidated"},{"entity":"Metals X Group","metric":"total_assets","value":618509000.0,"unit":"AUD","currency":"AUD","period":"2025-12-31","publication_date":"2026-03-25","source":"https://www.metalsx.com.au/wp-content/uploads/2026/03/MLX-Annual-Report-31-December-2025.pdf#page=25","page":"25","basis":"reported","ownership_basis":"consolidated"},{"entity":"Metals X Group","metric":"total_assets","value":505032000.0,"unit":"AUD","currency":"AUD","period":"2024-12-31","publication_date":"2026-03-25","source":"https://www.metalsx.com.au/wp-content/uploads/2026/03/MLX-Annual-Report-31-December-2025.pdf#page=25","page":"25","basis":"reported","ownership_basis":"consolidated"},{"entity":"Metals X Group","metric":"trade_and_other_payables","value":17091000.0,"unit":"AUD","currency":"AUD","period":"2025-12-31","publication_date":"2026-03-25","source":"https://www.metalsx.com.au/wp-content/uploads/2026/03/MLX-Annual-Report-31-December-2025.pdf#page=25","page":"25","basis":"reported","ownership_basis":"consolidated"},{"entity":"Metals X Group","metric":"trade_and_other_payables","value":20972000.0,"unit":"AUD","currency":"AUD","period":"2024-12-31","publication_date":"2026-03-25","source":"https://www.metalsx.com.au/wp-content/uploads/2026/03/MLX-Annual-Report-31-December-2025.pdf#page=25","page":"25","basis":"reported","ownership_basis":"consolidated"},{"entity":"Metals X Group","metric":"current_interest_bearing_liabilities","value":3645000.0,"unit":"AUD","currency":"AUD","period":"2024-12-31","publication_date":"2026-03-25","source":"https://www.metalsx.com.au/wp-content/uploads/2026/03/MLX-Annual-Report-31-December-2025.pdf#page=25","page":"25","basis":"reported","ownership_basis":"consolidated"},{"entity":"Metals X Group","metric":"noncurrent_interest_bearing_liabilities","value":2508000.0,"unit":"AUD","currency":"AUD","period":"2024-12-31","publication_date":"2026-03-25","source":"https://www.metalsx.com.au/wp-content/uploads/2026/03/MLX-Annual-Report-31-December-2025.pdf#page=25","page":"25","basis":"reported","ownership_basis":"consolidated"},{"entity":"Metals X Group","metric":"total_current_liabilities","value":51679000.0,"unit":"AUD","currency":"AUD","period":"2025-12-31","publication_date":"2026-03-25","source":"https://www.metalsx.com.au/wp-content/uploads/2026/03/MLX-Annual-Report-31-December-2025.pdf#page=25","page":"25","basis":"reported","ownership_basis":"consolidated"},{"entity":"Metals X Group","metric":"total_current_liabilities","value":43857000.0,"unit":"AUD","currency":"AUD","period":"2024-12-31","publication_date":"2026-03-25","source":"https://www.metalsx.com.au/wp-content/uploads/2026/03/MLX-Annual-Report-31-December-2025.pdf#page=25","page":"25","basis":"reported","ownership_basis":"consolidated"},{"entity":"Metals X Group","metric":"total_noncurrent_liabilities","value":34297000.0,"unit":"AUD","currency":"AUD","period":"2025-12-31","publication_date":"2026-03-25","source":"https://www.metalsx.com.au/wp-content/uploads/2026/03/MLX-Annual-Report-31-December-2025.pdf#page=25","page":"25","basis":"reported","ownership_basis":"consolidated"},{"entity":"Metals X Group","metric":"total_noncurrent_liabilities","value":33401000.0,"unit":"AUD","currency":"AUD","period":"2024-12-31","publication_date":"2026-03-25","source":"https://www.metalsx.com.au/wp-content/uploads/2026/03/MLX-Annual-Report-31-December-2025.pdf#page=25","page":"25","basis":"reported","ownership_basis":"consolidated"},{"entity":"Metals X Group","metric":"total_liabilities","value":85976000.0,"unit":"AUD","currency":"AUD","period":"2025-12-31","publication_date":"2026-03-25","source":"https://www.metalsx.com.au/wp-content/uploads/2026/03/MLX-Annual-Report-31-December-2025.pdf#page=25","page":"25","basis":"reported","ownership_basis":"consolidated"},{"entity":"Metals X Group","metric":"total_liabilities","value":77258000.0,"unit":"AUD","currency":"AUD","period":"2024-12-31","publication_date":"2026-03-25","source":"https://www.metalsx.com.au/wp-content/uploads/2026/03/MLX-Annual-Report-31-December-2025.pdf#page=25","page":"25","basis":"reported","ownership_basis":"consolidated"},{"entity":"Metals X Group","metric":"total_equity","value":532533000.0,"unit":"AUD","currency":"AUD","period":"2025-12-31","publication_date":"2026-03-25","source":"https://www.metalsx.com.au/wp-content/uploads/2026/03/MLX-Annual-Report-31-December-2025.pdf#page=25","page":"25","basis":"reported","ownership_basis":"consolidated"},{"entity":"Metals X Group","metric":"total_equity","value":427774000.0,"unit":"AUD","currency":"AUD","period":"2024-12-31","publication_date":"2026-03-25","source":"https://www.metalsx.com.au/wp-content/uploads/2026/03/MLX-Annual-Report-31-December-2025.pdf#page=25","page":"25","basis":"reported","ownership_basis":"consolidated"},{"entity":"Metals X Group","metric":"net_operating_cash_flow","value":143567000.0,"unit":"AUD","currency":"AUD","period":"FY2024","publication_date":"2026-03-25","source":"https://www.metalsx.com.au/wp-content/uploads/2026/03/MLX-Annual-Report-31-December-2025.pdf#page=26","page":"26","basis":"reported","ownership_basis":"consolidated"},{"entity":"Metals X Group","metric":"cash_paid_property_plant_equipment","value":17425000.0,"unit":"AUD","currency":"AUD","period":"FY2024","publication_date":"2026-03-25","source":"https://www.metalsx.com.au/wp-content/uploads/2026/03/MLX-Annual-Report-31-December-2025.pdf#page=26","page":"26","basis":"reported","ownership_basis":"consolidated"},{"entity":"Metals X Group","metric":"cash_paid_mine_properties_development","value":22511000.0,"unit":"AUD","currency":"AUD","period":"FY2024","publication_date":"2026-03-25","source":"https://www.metalsx.com.au/wp-content/uploads/2026/03/MLX-Annual-Report-31-December-2025.pdf#page=26","page":"26","basis":"reported","ownership_basis":"consolidated"},{"entity":"Metals X Group","metric":"net_investing_cash_flow","value":-52493000.0,"unit":"AUD","currency":"AUD","period":"FY2025","publication_date":"2026-03-25","source":"https://www.metalsx.com.au/wp-content/uploads/2026/03/MLX-Annual-Report-31-December-2025.pdf#page=26","page":"26","basis":"reported","ownership_basis":"consolidated"},{"entity":"Metals X Group","metric":"net_investing_cash_flow","value":-55453000.0,"unit":"AUD","currency":"AUD","period":"FY2024","publication_date":"2026-03-25","source":"https://www.metalsx.com.au/wp-content/uploads/2026/03/MLX-Annual-Report-31-December-2025.pdf#page=26","page":"26","basis":"reported","ownership_basis":"consolidated"},{"entity":"Metals X Group","metric":"net_financing_cash_flow","value":-2868000.0,"unit":"AUD","currency":"AUD","period":"FY2025","publication_date":"2026-03-25","source":"https://www.metalsx.com.au/wp-content/uploads/2026/03/MLX-Annual-Report-31-December-2025.pdf#page=26","page":"26","basis":"reported","ownership_basis":"consolidated"},{"entity":"Metals X Group","metric":"net_financing_cash_flow","value":-10512000.0,"unit":"AUD","currency":"AUD","period":"FY2024","publication_date":"2026-03-25","source":"https://www.metalsx.com.au/wp-content/uploads/2026/03/MLX-Annual-Report-31-December-2025.pdf#page=26","page":"26","basis":"reported","ownership_basis":"consolidated"},{"entity":"Metals X Group","metric":"net_change_in_cash","value":72962000.0,"unit":"AUD","currency":"AUD","period":"FY2025","publication_date":"2026-03-25","source":"https://www.metalsx.com.au/wp-content/uploads/2026/03/MLX-Annual-Report-31-December-2025.pdf#page=26","page":"26","basis":"reported","ownership_basis":"consolidated"},{"entity":"Metals X Group","metric":"net_change_in_cash","value":77602000.0,"unit":"AUD","currency":"AUD","period":"FY2024","publication_date":"2026-03-25","source":"https://www.metalsx.com.au/wp-content/uploads/2026/03/MLX-Annual-Report-31-December-2025.pdf#page=26","page":"26","basis":"reported","ownership_basis":"consolidated"},{"entity":"Metals X Group","metric":"opening_cash_and_cash_equivalents","value":220644000.0,"unit":"AUD","currency":"AUD","period":"FY2025","publication_date":"2026-03-25","source":"https://www.metalsx.com.au/wp-content/uploads/2026/03/MLX-Annual-Report-31-December-2025.pdf#page=26","page":"26","basis":"reported","ownership_basis":"consolidated"},{"entity":"Metals X Group","metric":"opening_cash_and_cash_equivalents","value":143042000.0,"unit":"AUD","currency":"AUD","period":"FY2024","publication_date":"2026-03-25","source":"https://www.metalsx.com.au/wp-content/uploads/2026/03/MLX-Annual-Report-31-December-2025.pdf#page=26","page":"26","basis":"reported","ownership_basis":"consolidated"}],"scenarios":{"bear":{"discount_rate":0.12,"ownership":0.5,"ownership_basis":"whole_operation","volume_basis":"imputed_production","residual_value":0.0,"years":[{"year":2027,"payable_tonnes":10158.3,"price":51008.0,"price_currency":"AUD","fx":1.0,"unit_cost":30181.8,"royalty_rate":0.0,"tax_rate":0.3,"depreciation":0.0,"capex":93600000.0,"working_capital_change":0.0,"closure":0.0,"corporate_cost":2240000.0},{"year":2028,"payable_tonnes":10158.3,"price":51008.0,"price_currency":"AUD","fx":1.0,"unit_cost":30181.8,"royalty_rate":0.0,"tax_rate":0.3,"depreciation":0.0,"capex":93600000.0,"working_capital_change":0.0,"closure":0.0,"corporate_cost":2240000.0},{"year":2029,"payable_tonnes":10158.3,"price":51008.0,"price_currency":"AUD","fx":1.0,"unit_cost":30181.8,"royalty_rate":0.0,"tax_rate":0.3,"depreciation":0.0,"capex":93600000.0,"working_capital_change":0.0,"closure":100000000.0,"corporate_cost":2240000.0}],"notes":"Illustrative 3-year assumed finite horizon; not reserve-backed life. Price multiplier 0.8, unit-cost multiplier 1.1, production proxy multiplier 0.9; not guidance."},"base":{"discount_rate":0.1,"ownership":0.5,"ownership_basis":"whole_operation","volume_basis":"imputed_production","residual_value":0.0,"years":[{"year":2027,"payable_tonnes":11287.0,"price":63760.0,"price_currency":"AUD","fx":1.0,"unit_cost":27438.0,"royalty_rate":0.0,"tax_rate":0.3,"depreciation":0.0,"capex":93600000.0,"working_capital_change":0.0,"closure":0.0,"corporate_cost":2240000.0},{"year":2028,"payable_tonnes":11287.0,"price":63760.0,"price_currency":"AUD","fx":1.0,"unit_cost":27438.0,"royalty_rate":0.0,"tax_rate":0.3,"depreciation":0.0,"capex":93600000.0,"working_capital_change":0.0,"closure":0.0,"corporate_cost":2240000.0},{"year":2029,"payable_tonnes":11287.0,"price":63760.0,"price_currency":"AUD","fx":1.0,"unit_cost":27438.0,"royalty_rate":0.0,"tax_rate":0.3,"depreciation":0.0,"capex":93600000.0,"working_capital_change":0.0,"closure":0.0,"corporate_cost":2240000.0},{"year":2030,"payable_tonnes":11287.0,"price":63760.0,"price_currency":"AUD","fx":1.0,"unit_cost":27438.0,"royalty_rate":0.0,"tax_rate":0.3,"depreciation":0.0,"capex":93600000.0,"working_capital_change":0.0,"closure":0.0,"corporate_cost":2240000.0},{"year":2031,"payable_tonnes":11287.0,"price":63760.0,"price_currency":"AUD","fx":1.0,"unit_cost":27438.0,"royalty_rate":0.0,"tax_rate":0.3,"depreciation":0.0,"capex":93600000.0,"working_capital_change":0.0,"closure":100000000.0,"corporate_cost":2240000.0}],"notes":"Illustrative 5-year assumed finite horizon; not reserve-backed life. Price multiplier 1.0, unit-cost multiplier 1.0, production proxy multiplier 1.0; not guidance."},"bull":{"discount_rate":0.08,"ownership":0.5,"ownership_basis":"whole_operation","volume_basis":"imputed_production","residual_value":0.0,"years":[{"year":2027,"payable_tonnes":12415.7,"price":76512.0,"price_currency":"AUD","fx":1.0,"unit_cost":26066.1,"royalty_rate":0.0,"tax_rate":0.3,"depreciation":0.0,"capex":93600000.0,"working_capital_change":0.0,"closure":0.0,"corporate_cost":2240000.0},{"year":2028,"payable_tonnes":12415.7,"price":76512.0,"price_currency":"AUD","fx":1.0,"unit_cost":26066.1,"royalty_rate":0.0,"tax_rate":0.3,"depreciation":0.0,"capex":93600000.0,"working_capital_change":0.0,"closure":0.0,"corporate_cost":2240000.0},{"year":2029,"payable_tonnes":12415.7,"price":76512.0,"price_currency":"AUD","fx":1.0,"unit_cost":26066.1,"royalty_rate":0.0,"tax_rate":0.3,"depreciation":0.0,"capex":93600000.0,"working_capital_change":0.0,"closure":0.0,"corporate_cost":2240000.0},{"year":2030,"payable_tonnes":12415.7,"price":76512.0,"price_currency":"AUD","fx":1.0,"unit_cost":26066.1,"royalty_rate":0.0,"tax_rate":0.3,"depreciation":0.0,"capex":93600000.0,"working_capital_change":0.0,"closure":0.0,"corporate_cost":2240000.0},{"year":2031,"payable_tonnes":12415.7,"price":76512.0,"price_currency":"AUD","fx":1.0,"unit_cost":26066.1,"royalty_rate":0.0,"tax_rate":0.3,"depreciation":0.0,"capex":93600000.0,"working_capital_change":0.0,"closure":0.0,"corporate_cost":2240000.0},{"year":2032,"payable_tonnes":12415.7,"price":76512.0,"price_currency":"AUD","fx":1.0,"unit_cost":26066.1,"royalty_rate":0.0,"tax_rate":0.3,"depreciation":0.0,"capex":93600000.0,"working_capital_change":0.0,"closure":0.0,"corporate_cost":2240000.0},{"year":2033,"payable_tonnes":12415.7,"price":76512.0,"price_currency":"AUD","fx":1.0,"unit_cost":26066.1,"royalty_rate":0.0,"tax_rate":0.3,"depreciation":0.0,"capex":93600000.0,"working_capital_change":0.0,"closure":100000000.0,"corporate_cost":2240000.0}],"notes":"I
A3: llustrative 7-year assumed finite horizon; not reserve-backed life. Price multiplier 1.2, unit-cost multiplier 0.95, production proxy multiplier 1.1; not guidance."}},"provenance":{"/cash":{"unit":"AUD","source":"https://www.metalsx.com.au/wp-content/uploads/2026/07/02_MLX_Quarterly-Report_30-June-2026_Final.pdf#page=9","rationale":"Reported group closing cash June 30 2026; no ownership scaling; stale at valuation date.","author":"Agent-authored public example; reported source or explicit assumption as described"},"/debt":{"unit":"AUD","source":"https://www.metalsx.com.au/wp-content/uploads/2026/03/MLX-Annual-Report-31-December-2025.pdf#page=25","rationale":"Sum current 2,849,000 and noncurrent 436,000 financing liabilities at Dec 31 2025; stale proxy, not a verified current bridge.","author":"Agent-authored public example; reported source or explicit assumption as described"},"/other_assets":{"unit":"AUD","source":"analyst-assumption://limited-sensitivity","rationale":"Exclude other investments/residual assets from this limited model; not a statement of zero economic value.","author":"Agent-authored public example; reported source or explicit assumption as described"},"/diluted_shares":{"unit":"shares","source":"https://www.metalsx.com.au/wp-content/uploads/2026/03/MLX-Annual-Report-31-December-2025.pdf#page=62","rationale":"Issued-share denominator Dec 31 2025, NOT verified current diluted shares; illustrative only.","author":"Agent-authored public example; reported source or explicit assumption as described"},"/scenarios/bear/discount_rate":{"unit":"fraction","source":"analyst-assumption://discount-rate","rationale":"Illustrative discount rate; not a derived company WACC.","author":"Agent-authored public example; reported source or explicit assumption as described"},"/scenarios/bear/ownership":{"unit":"fraction","source":"https://www.metalsx.com.au/wp-content/uploads/2026/07/02_MLX_Quarterly-Report_30-June-2026_Final.pdf#page=2","rationale":"Reported 50% ownership of Renison; apply once to whole-operation FCF.","author":"Agent-authored public example; reported source or explicit assumption as described"},"/scenarios/bear/residual_value":{"unit":"AUD","source":"analyst-assumption://finite-horizon","rationale":"No terminal perpetuity or residual asset value; horizon is an unverified stress assumption.","author":"Agent-authored public example; reported source or explicit assumption as described"},"/scenarios/bear/years/0/payable_tonnes":{"unit":"tonnes","source":"https://www.metalsx.com.au/wp-content/uploads/2026/07/02_MLX_Quarterly-Report_30-June-2026_Final.pdf#page=2","rationale":"TTM produced 11,287t ×0.9; IMPUTED PRODUCTION PROXY only, not payable sales. Gross imputed revenue includes 100% produced and marketing cost deducts payable tin charges.","author":"Agent-authored public example; reported source or explicit assumption as described"},"/scenarios/bear/years/0/price":{"unit":"AUD/tonne","source":"https://www.metalsx.com.au/wp-content/uploads/2026/07/02_MLX_Quarterly-Report_30-June-2026_Final.pdf#page=2","rationale":"TTM LME-imputed AUD 63,760/t ×0.8; not realized price, no claim of forecast guidance.","author":"Agent-authored public example; reported source or explicit assumption as described"},"/scenarios/bear/years/0/fx":{"unit":"AUD/AUD","source":"https://www.metalsx.com.au/wp-content/uploads/2026/07/02_MLX_Quarterly-Report_30-June-2026_Final.pdf#page=2","rationale":"All imputed price/costs reported in AUD; identity conversion.","author":"Agent-authored public example; reported source or explicit assumption as described"},"/scenarios/bear/years/0/unit_cost":{"unit":"AUD/tonne","source":"https://www.metalsx.com.au/wp-content/uploads/2026/07/02_MLX_Quarterly-Report_30-June-2026_Final.pdf#page=2","rationale":"(TTM C 1 19,349 + imputed sales/marketing 8,089) ×1.1; includes royalties/payable deductions. Assumed future run-rate, not guidance.","author":"Agent-authored public example; reported source or explicit assumption as described"},"/scenarios/bear/years/0/royalty_rate":{"unit":"fraction","source":"https://www.metalsx.com.au/wp-content/uploads/2026/07/02_MLX_Quarterly-Report_30-June-2026_Final.pdf#page=3","rationale":"Royalties already inside imputed sales/marketing; zero additional charge avoids double counting.","author":"Agent-authored public example; reported source or explicit assumption as described"},"/scenarios/bear/years/0/tax_rate":{"unit":"fraction","source":"analyst-assumption://simplified-tax","rationale":"Assume 30% tax on positive cash-based EBIT; no depreciation shields/losses. Not a verified fiscal forecast.","author":"Agent-authored public example; reported source or explicit assumption as described"},"/scenarios/bear/years/0/depreciation":{"unit":"AUD","source":"analyst-assumption://no-tax-depreciation","rationale":"Assume no depreciation tax shield; uncertain taxable bases need reconciliation.","author":"Agent-authored public example; reported source or explicit assumption as described"},"/scenarios/bear/years/0/capex":{"unit":"AUD","source":"https://www.metalsx.com.au/wp-content/uploads/2026/07/02_MLX_Quarterly-Report_30-June-2026_Final.pdf#page=3","rationale":"Annualize total whole-operation quarterly 23.4m ×4, includes sustaining and project spend; illustrative, no AISC double deduction.","author":"Agent-authored public example; reported source or explicit assumption as described"},"/scenarios/bear/years/0/working_capital_change":{"unit":"AUD","source":"analyst-assumption://flat-working-capital","rationale":"Assume zero annual change solely for sensitivity; inventory/receivables timing is not established.","author":"Agent-authored public example; reported source or explicit assumption as described"},"/scenarios/bear/years/0/closure":{"unit":"AUD","source":"analyst-assumption://nominal-closure","rationale":"Assume nominal whole-operation 100m at final model year; zero earlier payments assumed. Not the reported discounted accounting provision.","author":"Agent-authored public example; reported source or explicit assumption as described"},"/scenarios/bear/years/0/corporate_cost":{"unit":"AUD","source":"https://www.metalsx.com.au/wp-content/uploads/2026/07/02_MLX_Quarterly-Report_30-June-2026_Final.pdf#page=8","rationale":"Annualized group quarterly 0.56m ×4; deducted after ownership scaling, not scaled again.","author":"Agent-authored public example; reported source or explicit assumption as described"},"/scenarios/bear/years/1/payable_tonnes":{"unit":"tonnes","source":"https://www.metalsx.com.au/wp-content/uploads/2026/07/02_MLX_Quarterly-Report_30-June-2026_Final.pdf#page=2","rationale":"TTM produced 11,287t ×0.9; IMPUTED PRODUCTION PROXY only, not payable sales. Gross imputed revenue includes 100% produced and marketing cost deducts payable tin charges.","author":"Agent-authored public example; reported source or explicit assumption as described"},"/scenarios/bear/years/1/price":{"unit":"AUD/tonne","source":"https://www.metalsx.com.au/wp-content/uploads/2026/07/02_MLX_Quarterly-Report_30-June-2026_Final.pdf#page=2","rationale":"TTM LME-imputed AUD 63,760/t ×0.8; not realized price, no claim of forecast guidance.","author":"Agent-authored public example; reported source or explicit assumption as described"},"/scenarios/bear/years/1/fx":{"unit":"AUD/AUD","source":"https://www.metalsx.com.au/wp-content/uploads/2026/07/02_MLX_Quarterly-Report_30-June-2026_Final.pdf#page=2","rationale":"All imputed price/costs reported in AUD; identity conversion.","author":"Agent-authored public example; reported source or explicit assumption as described"},"/scenarios/bear/years/1/unit_cost":{"unit":"AUD/tonne","source":"https://www.metalsx.com.au/wp-content/uploads/2026/07/02_MLX_Quarterly-Report_30-June-2026_Final.pdf#page=2","rationale":"(TTM C 1 19,349 + imputed sales/marketing 8,089) ×1.1; includes royalties/payable deductions. Assumed future run-rate, not guidance.","author":"Agent-authored public example; reported source or explicit assumption as described"},"/scenarios/bear/years/1/royalty_rate":{"unit":"fraction","source":"https://www.metalsx.com.au/wp-content/uploads/2026/07/02_MLX_Quarterly-Report_30-June-2026_Final.pdf#page=3","rationale":"Royalties already inside imputed sales/marketing; zero additional charge avoids double counting.","author":"Agent-authored public example; reported source or explicit assumption as described"},"/scenarios/bear/years/1/tax_rate":{"unit":"fraction","source":"analyst-assumption://simplified-tax","rationale":"Assume 30% tax on positive cash-based EBIT; no depreciation shields/losses. Not a verified fiscal forecast.","author":"Agent-authored public example; reported source or explicit assumption as described"},"/scenarios/bear/years/1/depreciation":{"unit":"AUD","source":"analyst-assumption://no-tax-depreciation","rationale":"Assume no depreciation tax shield; uncertain taxable bases need reconciliation.","author":"Agent-authored public example; reported source or explicit assumption as described"},"/scenarios/bear/years/1/capex":{"unit":"AUD","source":"https://www.metalsx.com.au/wp-content/uploads/2026/07/02_MLX_Quarterly-Report_30-June-2026_Final.pdf#page=3","rationale":"Annualize total whole-operation quarterly 23.4m ×4, includes sustaining and project spend; illustrative, no AISC double deduction.","author":"Agent-authored public example; reported source or explicit assumption as described"},"/scenarios/bear/years/1/working_capital_change":{"unit":"AUD","source":"analyst-assumption://flat-working-capital","rationale":"Assume zero annual change solely for sensitivity; inventory/receivables timing is not established.","author":"Agent-authored public example; reported source or explicit assumption as described"},"/scenarios/bear/years/1/closure":{"unit":"AUD","source":"analyst-assumption://nominal-closure","rationale":"Assume nominal whole-operation 100m at final model year; zero earlier payments assumed. Not the reported discounted accounting provision.","author":"Agent-authored public example; reported source or explicit assumption as described"},"/scenarios/bear/years/1/corporate_cost":{"unit":"AUD","source":"https://www.metalsx.com.au/wp-content/uploads/2026/07/02_MLX_Quarterly-Report_30-June-2026_Final.pdf#page=8","rationale":"Annualized group quarterly 0.56m ×4; deducted after ownership scaling, not scaled again.","author":"Agent-authored public example; reported source or explicit assumption as described"},"/scenarios/bear/years/2/payable_tonnes":{"unit":"tonnes","source":"https://www.metalsx.com.au/wp-content/uploads/2026/07/02_MLX_Quarterly-Report_30-June-2026_Final.pdf#page=2","rationale":"TTM produced 11,287t ×0.9; IMPUTED PRODUCTION PROXY only, not payable sales. Gross imputed revenue includes 100% produced and marketing cost deducts payable tin charges.","author":"Agent-authored public example; reported source or explicit assumption as described"},"/scenarios/bear/years/2/price":{"unit":"AUD/tonne","source":"https://www.metalsx.com.au/wp-content/uploads/2026/07/02_MLX_Quarterly-Report_30-June-2026_Final.pdf#page=2","rationale":"TTM LME-imputed AUD 63,760/t ×0.8; not realized price, no claim of forecast guidance.","author":"Agent-authored public example; reported source or explicit assumption as described"},"/scenarios/bear/years/2/fx":{"unit":"AUD/AUD","source":"https://www.metalsx.com.au/wp-content/uploads/2026/07/02_MLX_Quarterly-Report_30-June-2026_Final.pdf#page=2","rationale":"All imputed price/costs reported in AUD; identity conversion.","author":"Agent-authored public example; reported source or explicit assumption as described"},"/scenarios/bear/years/2/unit_cost":{"unit":"AUD/tonne","source":"https://www.metalsx.com.au/wp-content/uploads/2026/07/02_MLX_Quarterly-Report_30-June-2026_Final.pdf#page=2","rationale":"(TTM C 1 19,349 + imputed sales/marketing 8,089) ×1.1; includes royalties/payable deductions. Assumed future run-rate, not guidance.","author":"Agent-authored public example; reported source or explicit assumption as described"},"/scenarios/bear/years/2/royalty_rate":{"unit":"fraction","source":"https://www.metalsx.com.au/wp-content/uploads/2026/07/02_MLX_Quarterly-Report_30-June-2026_Final.pdf#page=3","rationale":"Royalties already inside imputed sales/marketing; zero additional charge avoids double counting.","author":"Agent-authored public example; reported source or explicit assumption as described"},"/scenarios/bear/years/2/tax_rate":{"unit":"fraction","source":"analyst-assumption://simplified-tax","rationale":"Assume 30% tax on positive cash-based EBIT; no depreciation shields/losses. Not a verified fiscal forecast.","author":"Agent-authored public example; reported source or explicit assumption as described"},"/scenarios/bear/years/2/depreciation":{"unit":"AUD","source":"analyst-assumption://no-tax-depreciation","rationale":"Assume no depreciation tax shield; uncertain taxable bases need reconciliation.","author":"Agent-authored public example; reported source or explicit assumption as described"},"/scenarios/bear/years/2/capex":{"unit":"AUD","source":"https://www.metalsx.com.au/wp-content/uploads/2026/07/02_MLX_Quarterly-Report_30-June-2026_Final.pdf#page=3","rationale":"Annualize total whole-operation quarterly 23.4m ×4, includes sustaining and project spend; illustrative, no AISC double deduction.","author":"Agent-authored public example; reported source or explicit assumption as described"},"/scenarios/bear/years/2/working_capital_change":{"unit":"AUD","source":"analyst-assumption://flat-working-capital","rationale":"Assume zero annual change solely for sensitivity; inventory/receivables timing is not established.","author":"Agent-authored public example; reported source or explicit assumption as described"},"/scenarios/bear/years/2/closure":{"unit":"AUD","source":"analyst-assumption://nominal-closure","rationale":"Assume nominal whole-operation 100m at final model year; zero earlier payments assumed. Not the reported discounted accounting provision.","author":"Agent-authored public example; reported source or explicit assumption as described"},"/scenarios/bear/years/2/corporate_cost":{"unit":"AUD","source":"https://www.metalsx.com.au/wp-content/uploads/2026/07/02_MLX_Quarterly-Report_30-June-2026_Final.pdf#page=8","rationale":"Annualized group quarterly 0.56m ×4; deducted after ownership scaling, not scaled again.","author":"Agent-authored public example; reported source or explicit assumption as described"},"/scenarios/base/discount_rate":{"unit":"fraction","source":"analyst-assumption://discount-rate","rationale":"Illustrative discount rate; not a derived company WACC.","author":"Agent-authored public example; reported source or explicit assumption as described"},"/scenarios/base/ownership":{"unit":"fraction","source":"https://www.metalsx.com.au/wp-content/uploads/2026/07/02_MLX_Quarterly-Report_30-June-2026_Final.pdf#page=2","rationale":"Reported 50% ownership of Renison; apply once to whole-operation FCF.","author":"Agent-authored public example; reported source or explicit assumption as described"},"/scenarios/base/residual_value":{"unit":"AUD","source":"analyst-assumption://finite-horizon","rationale":"No terminal perpetuity or residual asset value; horizon is an unverified stress assumption.","author":"Agent-authored public example; reported source or explicit assumption as described"},"/scenarios/base/years/0/payable_tonnes":{"unit":"tonnes","source":"https://www.metalsx.com.au/wp-content/uploads/2026/07/02_MLX_Quarterly-Report_30-June-2026_Final.pdf#page=2","rationale":"TTM produced 11,287t ×1.0; IMPUTED PRODUCTION PROXY only, not payable sales. Gross imputed revenue includes 100% produced and marketing cost deducts payable tin charges.","author":"Agent-authored public example; reported source or explicit assumption as described"},"/scenarios/base/years/0/price":{"unit":"AUD/tonne","source":"https://www.metalsx.com.au/wp-content/uploads/2026/07/02_MLX_Quarterly-Report_30-June-2026_Final.pdf#page=2","rationale":"TTM LME-imputed AUD 63,760/t ×1.0; not realized price, no claim of forecast guidance.","author":"Agent-authored public example; reported source or explicit assumption as described"},"/scenarios/base/years/0/fx":{"unit":"AUD/AUD","source":"https://www.metalsx.com.au/wp-content/uploads/2026/07/02_MLX_Quarterly-Report_30-June-2026_Final.pdf#page=2","rationale":"All imputed price/costs reported in AUD; identity conversion.","author":"Agent-authored public example; reported source or explicit assumption as described"},"/scenarios/base/years/0/unit_cost":{"unit":"AUD/tonne","source":"https://www.metalsx.com.au/wp-content/uploads/2026/07/02_MLX_Quarterly-Report_30-June-2026_Final.pdf#page=2","rationale":"(TTM C 1 19,349 + imputed sales/marketing 8,089) ×1.0; includes royalties/payable deductions. Assumed future run-rate, not guidance.","author":"Agent-authored public example; reported source or explicit assumption as described"},"/scenarios/base/years/0/royalty_rate":{"unit":"fraction","source":"https://www.metalsx.com.au/wp-content/uploads/2026/07/02_MLX_Quarterly-Report_30-June-2026_Final.pdf#page=3","rationale":"Royalties already inside imputed sales/marketing; zero additional charge avoids double counting.","author":"Agent-authored public example; reported source or explicit assumption as described"},"/scenarios/base/years/0/tax_rate":{"unit":"fraction","source":"analyst-assumption://simplified-tax","rationale":"Assume 30% tax on positive cash-based EBIT; no depreciation shields/losses. Not a verified fiscal forecast.","author":"Agent-authored public example; reported source or explicit assumption as described"},"/scenarios/base/years/0/depreciation":{"unit":"AUD","source":"analyst-assumption://no-tax-depreciation","rationale":"Assume no depreciation tax shield; uncertain taxable bases need reconciliation.","author":"Agent-authored public example; reported source or explicit assumption as described"},"/scenarios/base/years/0/capex":{"unit":"AUD","source":"https://www.metalsx.com.au/wp-content/uploads/2026/07/02_MLX_Quarterly-Report_30-June-2026_Final.pdf#page=3","rationale":"Annualize total whole-operation quarterly 23.4m ×4, includes sustaining and project spend; illustrative, no AISC double deduction.","author":"Agent-authored public example; reported source or explicit assumption as described"},"/scenarios/base/years/0/working_capital_change":{"unit":"AUD","source":"analyst-assumption://flat-working-capital","rationale":"Assume zero annual change solely for sensitivity; inventory/receivables timing is not established.","author":"Agent-authored public example; reported source or explicit assumption as described"},"/scenarios/base/years/0/closure":{"unit":"AUD","source":"analyst-assumption://nominal-closure","rationale":"Assume nominal whole-operation 100m at final model year; zero earlier payments assumed. Not the reported discounted accounting provision.","author":"Agent-authored public example; reported source or explicit assumption as described"},"/scenarios/base/years/0/corporate_cost":{"unit":"AUD","source":"https://www.metalsx.com.au/wp-content/uploads/2026/07/02_MLX_Quarterly-Report_30-June-2026_Final.pdf#page=8","rationale":"Annualized group quarterly 0.56m ×4; deducted after ownership scaling, not scaled again.","author":"Agent-authored public example; reported source or explicit assumption as described"},"/scenarios/base/years/1/payable_tonnes":{"unit":"tonnes","source":"https://www.metalsx.com.au/wp-content/uploads/2026/07/02_MLX_Quarterly-Report_30-June-2026_Final.pdf#page=2","rationale":"TTM produced 11,287t ×1.0; IMPUTED PRODUCTION PROXY only, not payable sales. Gross imputed revenue includes 100% produced and marketing cost deducts payable tin charges.","author":"Agent-authored public example; reported source or explicit assumption as described"},"/scenarios/base/years/1/price":{"unit":"AUD/tonne","source":"https://www.metalsx.com.au/wp-content/uploads/2026/07/02_MLX_Quarterly-Report_30-June-2026_Final.pdf#page=2","rationale":"TTM LME-imputed AUD 63,760/t ×1.0; not realized price, no claim of forecast guidance.","author":"Agent-authored public example; reported source or explicit assumption as described"},"/scenarios/base/years/1/fx":{"unit":"AUD/AUD","source":"https://www.metalsx.com.au/wp-content/uploads/2026/07/02_MLX_Quarterly-Report_30-June-2026_Final.pdf#page=2","rationale":"All imputed price/costs reported in AUD; identity conversion.","author":"Agent-authored public example; reported source or explicit assumption as described"},"/scenarios/base/years/1/unit_cost":{"unit":"AUD/tonne","source":"https://www.metalsx.com.au/wp-content/uploads/2026/07/02_MLX_Quarterly-Report_30-June-2026_Final.pdf#page=2","rationale":"(TTM C 1 19,349 + imputed sales/marketing 8,089) ×1.0; includes royalties/payable deductions. Assumed future run-rate, not guidance.","author":"Agent-authored public example; reported source or explicit assumption as described"},"/scenarios/base/years/1/royalty_rate":{"unit":"fraction","source":"https://www.metalsx.com.au/wp-content/uploads/2026/07/02_MLX_Quarterly-Report_30-June-2026_Final.pdf#page=3","rationale":"Royalties already inside imputed sales/marketing; zero additional charge avoids double counting.","author":"Agent-authored public example; reported source or explicit assumption as described"},"/scenarios/base/years/1/tax_rate":{"unit":"fraction","source":"analyst-assumption://simplified-tax","rationale":"Assume 30% tax on positive cash-based EBIT; no depreciation shields/losses. Not a verified fiscal forecast.","author":"Agent-authored public example; reported source or explicit assumption as described"},"/scenarios/base/years/1/depreciation":{"unit":"AUD","source":"analyst-assumption://no-tax-depreciation","rationale":"Assume no depreciation tax shield; uncertain taxable bases need reconciliation.","author":"Agent-authored public example; reported source or explicit assumption as described"},"/scenarios/base/years/1/capex":{"unit":"AUD","source":"https://www.metalsx.com.au/wp-content/uploads/2026/07/02_MLX_Quarterly-Report_30-June-2026_Final.pdf#page=3","rationale":"Annualize total whole-operation quarterly 23.4m ×4, includes sustaining and project spend; illustrative, no AISC double deduction.","author":"Agent-authored public example; reported source or explicit assumption as described"},"/scenarios/base/years/1/working_capital_change":{"unit":"AUD","source":"analyst-assumption://flat-working-capital","rationale":"Assume zero annual change solely for sensitivity; inventory/receivables timing is not established.","author":"Agent-authored public example; reported source or explicit assumption as described"},"/scenarios/base/years/1/closure":{"unit":"AUD","source":"analyst-assumption://nominal-closure","rationale":"Assume nominal whole-operation 100m at final model year; zero earlier payments assumed. Not the reported discounted accounting provision.","author":"Agent-authored public example; reported source or explicit assumption as described"},"/scenarios/base/years/1/corporate_cost":{"unit":"AUD","source":"https://www.metalsx.com.au/wp-content/uploads/2026/07/02_MLX_Quarterly-Report_30-June-2026_Final.pdf#page=8","rationale":"Annualized group quarterly 0.56m ×4; deducted after ownership scaling, not scaled again.","author":"Agent-authored public example; reported source or explicit assumption as described"},"/scenarios/base/years/2/payable_tonnes":{"unit":"tonnes","source":"https://www.metalsx.com.au/wp-content/uploads/2026/07/02_MLX_Quarterly-Report_30-June-2026_Final.pdf#page=2","rationale":"TTM produced 11,287t ×1.0; IMPUTED PRODUCTION PROXY only, not payable sales. Gross imputed revenue includes 100% produced and marketing cost deducts payable tin charges.","author":"Agent-authored public example; reported source or explicit assumption as described"},"/scenarios/base/years/2/price":{"unit":"AUD/tonne","source":"https://www.metalsx.com.au/wp-content/uploads/2026/07/02_MLX_Quarterly-Report_30-June-2026_Final.pdf#page=2","rationale":"TTM LME-imputed AUD 63,760/t ×1.0; not realized price, no claim of forecast guidance.","author":"Agent-authored public example; reported source or explicit assumption as described"},"/scenarios/base/years/2/fx":{"unit":"AUD/AUD","source":"https://www.metalsx.com.au/wp-content/uploads/2026/07/02_MLX_Quarterly-Report_30-June-2026_Final.pdf#page=2","rationale":"All imputed price/costs reported in AUD; identity conversion.","author":"Agent-authored public example; reported source or explicit assumption as described"},"/scenarios/base/years/2/unit_cost":{"unit":"AUD/tonne","source":"https://www.metalsx.com.au/wp-content/uploads/2026/07/02_MLX_Quarterly-Report_30-June-2026_Final.pdf#page=2","rationale":"(TTM C 1 19,349 + imputed sales/marketing 8,089) ×1.0; includes royalties/payable deductions. Assumed future run-rate, not guidance.","author":"Agent-authored public example; reported source or explicit assumption as described"},"/scenarios/base/years/2/royalty_rate":{"unit":"fraction","source":"https://www.metalsx.com.au/wp-content/uploads/2026/07/02_MLX_Quarterly-Report_30-June-2026_Final.pdf#page=3","rationale":"Royalties already inside imputed sales/marketing; zero additional charge avoids double counting.","author":"Agent-authored public example; reported source or explicit assumption as described"},"/scenarios/base/years/2/tax_rate":{"unit":"fraction","source":"analyst-assumption://simplified-tax","rationale":"Assume 30% tax on positive cash-based EBIT; no depreciation shields/losses. Not a verified fiscal forecast.","author":"Agent-authored public example; reported source or explicit assumption as described"},"/scenarios/base/years/2/depreciation":{"unit":"AUD","source":"analyst-assumption://no-tax-depreciation","rationale":"Assume no depreciation tax shield; uncertain taxable bases need reconciliation.","author":"Agent-authored public example; reported source or explicit assumption as described"},"/scenarios/base/years/2/capex":{"unit":"AUD","source":"https://www.metalsx.com.au/wp-content/uploads/2026/07/02_MLX_Quarterly-Report_30-June-2026_Final.pdf#page=3","rationale":"Annualize total whole-operation quarterly 23.4m ×4, includes sustaining and project spend; illustrative, no AISC double deduction.","author":"Agent-authored public example; reported source or explicit assumption as described"},"/scenarios/base/years/2/working_capital_change":{"unit":"AUD","source":"analyst-assumption://flat-working-capital","rationale":"Assume zero annual change solely for sensitivity; inventory/receivables timing is not established.","author":"Agent-authored public example; reported source or explicit assumption as described"},"/scenarios/base/years/2/closure":{"unit":"AUD","source":"analyst-assumption://nominal-closure","rationale":"Assume nominal whole-operation 100m at final model year; zero earlier payments assumed. Not the reported discounted accounting provision.","author":"Agent-authored public example; reported source or explicit assumption as described"},"/scenarios/base/years/2/corporate_cost":{"unit":"AUD","source":"https://www.metalsx.com.au/wp-content/uploads/2026/07/02_MLX_Quarterly-Report_30-June-2026_Final.pdf#page=8","rationale":"Annualized group quarterly 0.56m ×4; deducted after ownership scaling, not scaled again.","author":"Agent-authored public example; reported source or explicit assumption as described"},"/scenarios/base/years/3/payable_tonnes":{"unit":"tonnes","source":"https://www.metalsx.com.au/wp-content/uploads/2026/07/02_MLX_Quarterly-Report_30-June-2026_Final.pdf#page=2","rationale":"TTM produced 11,287t ×1.0; IMPUTED PRODUCTION PROXY only, not payable sales. Gross imputed revenue includes 100% produced and marketing cost deducts payable tin charges.","author":"Agent-authored public example; reported source or explicit assumption as described"},"/scenarios/base/years/3/price":{"unit":"AUD/tonne","source":"https://www.metalsx.com.au/wp-content/uploads/2026/07/02_MLX_Quarterly-Report_30-June-2026_Final.pdf#page=2","rationale":"TTM LME-imputed AUD 63,760/t ×1.0; not realized price, no claim of forecast guidance.","author":"Agent-authored public example; reported source or explicit assumption as described"},"/scenarios/base/years/3/fx":{"unit":"AUD/AUD","source":"https://www.metalsx.com.au/wp-content/uploads/2026/07/02_MLX_Quarterly-Report_30-June-2026_Final.pdf#page=2","rationale":"All imputed price/costs reported in AUD; identity conversion.","author":"Agent-authored public example; reported source or explicit assumption as described"},"/scenarios/base/years/3/unit_cost":{"unit":"AUD/tonne","source":"https://www.metalsx.com.au/wp-content/uploads/2026/07/02_MLX_Quarterly-Report_30-June-2026_Final.pdf#page=2","rationale":"(TTM C 1 19,349 + imputed sales/marketing 8,089) ×1.0; includes royalties/payable deductions. Assumed future run-rate, not guidance.","author":"Agent-authored public example; reported source or explicit assumption as described"},"/scenarios/base/years/3/royalty_rate":{"unit":"fraction","source":"https://www.metalsx.com.au/wp-content/uploads/2026/07/02_MLX_Quarterly-Report_30-June-2026_Final.pdf#page=3","rationale":"Royalties already inside imputed sales/marketing; zero additional charge avoids double counting.","author":"Agent-authored public example; reported source or explicit assumption as described"},"/scenarios/base/years/3/tax_rate":{"unit":"fraction","source":"analyst-assumption://simplified-tax","rationale":"Assume 30% tax on positive cash-based EBIT; no depreciation shields/losses. Not a verified fiscal forecast.","author":"Agent-authored public example; reported source or explicit assumption as described"},"/scenarios/base/years/3/depreciation":{"unit":"AUD","source":"analyst-assumption://no-tax-depreciation","rationale":"Assume no depreciation tax shield; uncertain taxable bases need reconciliation.","author":"Agent-authored public example; reported source or explicit assumption as described
A4: "},"/scenarios/base/years/3/capex":{"unit":"AUD","source":"https://www.metalsx.com.au/wp-content/uploads/2026/07/02_MLX_Quarterly-Report_30-June-2026_Final.pdf#page=3","rationale":"Annualize total whole-operation quarterly 23.4m ×4, includes sustaining and project spend; illustrative, no AISC double deduction.","author":"Agent-authored public example; reported source or explicit assumption as described"},"/scenarios/base/years/3/working_capital_change":{"unit":"AUD","source":"analyst-assumption://flat-working-capital","rationale":"Assume zero annual change solely for sensitivity; inventory/receivables timing is not established.","author":"Agent-authored public example; reported source or explicit assumption as described"},"/scenarios/base/years/3/closure":{"unit":"AUD","source":"analyst-assumption://nominal-closure","rationale":"Assume nominal whole-operation 100m at final model year; zero earlier payments assumed. Not the reported discounted accounting provision.","author":"Agent-authored public example; reported source or explicit assumption as described"},"/scenarios/base/years/3/corporate_cost":{"unit":"AUD","source":"https://www.metalsx.com.au/wp-content/uploads/2026/07/02_MLX_Quarterly-Report_30-June-2026_Final.pdf#page=8","rationale":"Annualized group quarterly 0.56m ×4; deducted after ownership scaling, not scaled again.","author":"Agent-authored public example; reported source or explicit assumption as described"},"/scenarios/base/years/4/payable_tonnes":{"unit":"tonnes","source":"https://www.metalsx.com.au/wp-content/uploads/2026/07/02_MLX_Quarterly-Report_30-June-2026_Final.pdf#page=2","rationale":"TTM produced 11,287t ×1.0; IMPUTED PRODUCTION PROXY only, not payable sales. Gross imputed revenue includes 100% produced and marketing cost deducts payable tin charges.","author":"Agent-authored public example; reported source or explicit assumption as described"},"/scenarios/base/years/4/price":{"unit":"AUD/tonne","source":"https://www.metalsx.com.au/wp-content/uploads/2026/07/02_MLX_Quarterly-Report_30-June-2026_Final.pdf#page=2","rationale":"TTM LME-imputed AUD 63,760/t ×1.0; not realized price, no claim of forecast guidance.","author":"Agent-authored public example; reported source or explicit assumption as described"},"/scenarios/base/years/4/fx":{"unit":"AUD/AUD","source":"https://www.metalsx.com.au/wp-content/uploads/2026/07/02_MLX_Quarterly-Report_30-June-2026_Final.pdf#page=2","rationale":"All imputed price/costs reported in AUD; identity conversion.","author":"Agent-authored public example; reported source or explicit assumption as described"},"/scenarios/base/years/4/unit_cost":{"unit":"AUD/tonne","source":"https://www.metalsx.com.au/wp-content/uploads/2026/07/02_MLX_Quarterly-Report_30-June-2026_Final.pdf#page=2","rationale":"(TTM C 1 19,349 + imputed sales/marketing 8,089) ×1.0; includes royalties/payable deductions. Assumed future run-rate, not guidance.","author":"Agent-authored public example; reported source or explicit assumption as described"},"/scenarios/base/years/4/royalty_rate":{"unit":"fraction","source":"https://www.metalsx.com.au/wp-content/uploads/2026/07/02_MLX_Quarterly-Report_30-June-2026_Final.pdf#page=3","rationale":"Royalties already inside imputed sales/marketing; zero additional charge avoids double counting.","author":"Agent-authored public example; reported source or explicit assumption as described"},"/scenarios/base/years/4/tax_rate":{"unit":"fraction","source":"analyst-assumption://simplified-tax","rationale":"Assume 30% tax on positive cash-based EBIT; no depreciation shields/losses. Not a verified fiscal forecast.","author":"Agent-authored public example; reported source or explicit assumption as described"},"/scenarios/base/years/4/depreciation":{"unit":"AUD","source":"analyst-assumption://no-tax-depreciation","rationale":"Assume no depreciation tax shield; uncertain taxable bases need reconciliation.","author":"Agent-authored public example; reported source or explicit assumption as described"},"/scenarios/base/years/4/capex":{"unit":"AUD","source":"https://www.metalsx.com.au/wp-content/uploads/2026/07/02_MLX_Quarterly-Report_30-June-2026_Final.pdf#page=3","rationale":"Annualize total whole-operation quarterly 23.4m ×4, includes sustaining and project spend; illustrative, no AISC double deduction.","author":"Agent-authored public example; reported source or explicit assumption as described"},"/scenarios/base/years/4/working_capital_change":{"unit":"AUD","source":"analyst-assumption://flat-working-capital","rationale":"Assume zero annual change solely for sensitivity; inventory/receivables timing is not established.","author":"Agent-authored public example; reported source or explicit assumption as described"},"/scenarios/base/years/4/closure":{"unit":"AUD","source":"analyst-assumption://nominal-closure","rationale":"Assume nominal whole-operation 100m at final model year; zero earlier payments assumed. Not the reported discounted accounting provision.","author":"Agent-authored public example; reported source or explicit assumption as described"},"/scenarios/base/years/4/corporate_cost":{"unit":"AUD","source":"https://www.metalsx.com.au/wp-content/uploads/2026/07/02_MLX_Quarterly-Report_30-June-2026_Final.pdf#page=8","rationale":"Annualized group quarterly 0.56m ×4; deducted after ownership scaling, not scaled again.","author":"Agent-authored public example; reported source or explicit assumption as described"},"/scenarios/bull/discount_rate":{"unit":"fraction","source":"analyst-assumption://discount-rate","rationale":"Illustrative discount rate; not a derived company WACC.","author":"Agent-authored public example; reported source or explicit assumption as described"},"/scenarios/bull/ownership":{"unit":"fraction","source":"https://www.metalsx.com.au/wp-content/uploads/2026/07/02_MLX_Quarterly-Report_30-June-2026_Final.pdf#page=2","rationale":"Reported 50% ownership of Renison; apply once to whole-operation FCF.","author":"Agent-authored public example; reported source or explicit assumption as described"},"/scenarios/bull/residual_value":{"unit":"AUD","source":"analyst-assumption://finite-horizon","rationale":"No terminal perpetuity or residual asset value; horizon is an unverified stress assumption.","author":"Agent-authored public example; reported source or explicit assumption as described"},"/scenarios/bull/years/0/payable_tonnes":{"unit":"tonnes","source":"https://www.metalsx.com.au/wp-content/uploads/2026/07/02_MLX_Quarterly-Report_30-June-2026_Final.pdf#page=2","rationale":"TTM produced 11,287t ×1.1; IMPUTED PRODUCTION PROXY only, not payable sales. Gross imputed revenue includes 100% produced and marketing cost deducts payable tin charges.","author":"Agent-authored public example; reported source or explicit assumption as described"},"/scenarios/bull/years/0/price":{"unit":"AUD/tonne","source":"https://www.metalsx.com.au/wp-content/uploads/2026/07/02_MLX_Quarterly-Report_30-June-2026_Final.pdf#page=2","rationale":"TTM LME-imputed AUD 63,760/t ×1.2; not realized price, no claim of forecast guidance.","author":"Agent-authored public example; reported source or explicit assumption as described"},"/scenarios/bull/years/0/fx":{"unit":"AUD/AUD","source":"https://www.metalsx.com.au/wp-content/uploads/2026/07/02_MLX_Quarterly-Report_30-June-2026_Final.pdf#page=2","rationale":"All imputed price/costs reported in AUD; identity conversion.","author":"Agent-authored public example; reported source or explicit assumption as described"},"/scenarios/bull/years/0/unit_cost":{"unit":"AUD/tonne","source":"https://www.metalsx.com.au/wp-content/uploads/2026/07/02_MLX_Quarterly-Report_30-June-2026_Final.pdf#page=2","rationale":"(TTM C 1 19,349 + imputed sales/marketing 8,089) ×0.95; includes royalties/payable deductions. Assumed future run-rate, not guidance.","author":"Agent-authored public example; reported source or explicit assumption as described"},"/scenarios/bull/years/0/royalty_rate":{"unit":"fraction","source":"https://www.metalsx.com.au/wp-content/uploads/2026/07/02_MLX_Quarterly-Report_30-June-2026_Final.pdf#page=3","rationale":"Royalties already inside imputed sales/marketing; zero additional charge avoids double counting.","author":"Agent-authored public example; reported source or explicit assumption as described"},"/scenarios/bull/years/0/tax_rate":{"unit":"fraction","source":"analyst-assumption://simplified-tax","rationale":"Assume 30% tax on positive cash-based EBIT; no depreciation shields/losses. Not a verified fiscal forecast.","author":"Agent-authored public example; reported source or explicit assumption as described"},"/scenarios/bull/years/0/depreciation":{"unit":"AUD","source":"analyst-assumption://no-tax-depreciation","rationale":"Assume no depreciation tax shield; uncertain taxable bases need reconciliation.","author":"Agent-authored public example; reported source or explicit assumption as described"},"/scenarios/bull/years/0/capex":{"unit":"AUD","source":"https://www.metalsx.com.au/wp-content/uploads/2026/07/02_MLX_Quarterly-Report_30-June-2026_Final.pdf#page=3","rationale":"Annualize total whole-operation quarterly 23.4m ×4, includes sustaining and project spend; illustrative, no AISC double deduction.","author":"Agent-authored public example; reported source or explicit assumption as described"},"/scenarios/bull/years/0/working_capital_change":{"unit":"AUD","source":"analyst-assumption://flat-working-capital","rationale":"Assume zero annual change solely for sensitivity; inventory/receivables timing is not established.","author":"Agent-authored public example; reported source or explicit assumption as described"},"/scenarios/bull/years/0/closure":{"unit":"AUD","source":"analyst-assumption://nominal-closure","rationale":"Assume nominal whole-operation 100m at final model year; zero earlier payments assumed. Not the reported discounted accounting provision.","author":"Agent-authored public example; reported source or explicit assumption as described"},"/scenarios/bull/years/0/corporate_cost":{"unit":"AUD","source":"https://www.metalsx.com.au/wp-content/uploads/2026/07/02_MLX_Quarterly-Report_30-June-2026_Final.pdf#page=8","rationale":"Annualized group quarterly 0.56m ×4; deducted after ownership scaling, not scaled again.","author":"Agent-authored public example; reported source or explicit assumption as described"},"/scenarios/bull/years/1/payable_tonnes":{"unit":"tonnes","source":"https://www.metalsx.com.au/wp-content/uploads/2026/07/02_MLX_Quarterly-Report_30-June-2026_Final.pdf#page=2","rationale":"TTM produced 11,287t ×1.1; IMPUTED PRODUCTION PROXY only, not payable sales. Gross imputed revenue includes 100% produced and marketing cost deducts payable tin charges.","author":"Agent-authored public example; reported source or explicit assumption as described"},"/scenarios/bull/years/1/price":{"unit":"AUD/tonne","source":"https://www.metalsx.com.au/wp-content/uploads/2026/07/02_MLX_Quarterly-Report_30-June-2026_Final.pdf#page=2","rationale":"TTM LME-imputed AUD 63,760/t ×1.2; not realized price, no claim of forecast guidance.","author":"Agent-authored public example; reported source or explicit assumption as described"},"/scenarios/bull/years/1/fx":{"unit":"AUD/AUD","source":"https://www.metalsx.com.au/wp-content/uploads/2026/07/02_MLX_Quarterly-Report_30-June-2026_Final.pdf#page=2","rationale":"All imputed price/costs reported in AUD; identity conversion.","author":"Agent-authored public example; reported source or explicit assumption as described"},"/scenarios/bull/years/1/unit_cost":{"unit":"AUD/tonne","source":"https://www.metalsx.com.au/wp-content/uploads/2026/07/02_MLX_Quarterly-Report_30-June-2026_Final.pdf#page=2","rationale":"(TTM C 1 19,349 + imputed sales/marketing 8,089) ×0.95; includes royalties/payable deductions. Assumed future run-rate, not guidance.","author":"Agent-authored public example; reported source or explicit assumption as described"},"/scenarios/bull/years/1/royalty_rate":{"unit":"fraction","source":"https://www.metalsx.com.au/wp-content/uploads/2026/07/02_MLX_Quarterly-Report_30-June-2026_Final.pdf#page=3","rationale":"Royalties already inside imputed sales/marketing; zero additional charge avoids double counting.","author":"Agent-authored public example; reported source or explicit assumption as described"},"/scenarios/bull/years/1/tax_rate":{"unit":"fraction","source":"analyst-assumption://simplified-tax","rationale":"Assume 30% tax on positive cash-based EBIT; no depreciation shields/losses. Not a verified fiscal forecast.","author":"Agent-authored public example; reported source or explicit assumption as described"},"/scenarios/bull/years/1/depreciation":{"unit":"AUD","source":"analyst-assumption://no-tax-depreciation","rationale":"Assume no depreciation tax shield; uncertain taxable bases need reconciliation.","author":"Agent-authored public example; reported source or explicit assumption as described"},"/scenarios/bull/years/1/capex":{"unit":"AUD","source":"https://www.metalsx.com.au/wp-content/uploads/2026/07/02_MLX_Quarterly-Report_30-June-2026_Final.pdf#page=3","rationale":"Annualize total whole-operation quarterly 23.4m ×4, includes sustaining and project spend; illustrative, no AISC double deduction.","author":"Agent-authored public example; reported source or explicit assumption as described"},"/scenarios/bull/years/1/working_capital_change":{"unit":"AUD","source":"analyst-assumption://flat-working-capital","rationale":"Assume zero annual change solely for sensitivity; inventory/receivables timing is not established.","author":"Agent-authored public example; reported source or explicit assumption as described"},"/scenarios/bull/years/1/closure":{"unit":"AUD","source":"analyst-assumption://nominal-closure","rationale":"Assume nominal whole-operation 100m at final model year; zero earlier payments assumed. Not the reported discounted accounting provision.","author":"Agent-authored public example; reported source or explicit assumption as described"},"/scenarios/bull/years/1/corporate_cost":{"unit":"AUD","source":"https://www.metalsx.com.au/wp-content/uploads/2026/07/02_MLX_Quarterly-Report_30-June-2026_Final.pdf#page=8","rationale":"Annualized group quarterly 0.56m ×4; deducted after ownership scaling, not scaled again.","author":"Agent-authored public example; reported source or explicit assumption as described"},"/scenarios/bull/years/2/payable_tonnes":{"unit":"tonnes","source":"https://www.metalsx.com.au/wp-content/uploads/2026/07/02_MLX_Quarterly-Report_30-June-2026_Final.pdf#page=2","rationale":"TTM produced 11,287t ×1.1; IMPUTED PRODUCTION PROXY only, not payable sales. Gross imputed revenue includes 100% produced and marketing cost deducts payable tin charges.","author":"Agent-authored public example; reported source or explicit assumption as described"},"/scenarios/bull/years/2/price":{"unit":"AUD/tonne","source":"https://www.metalsx.com.au/wp-content/uploads/2026/07/02_MLX_Quarterly-Report_30-June-2026_Final.pdf#page=2","rationale":"TTM LME-imputed AUD 63,760/t ×1.2; not realized price, no claim of forecast guidance.","author":"Agent-authored public example; reported source or explicit assumption as described"},"/scenarios/bull/years/2/fx":{"unit":"AUD/AUD","source":"https://www.metalsx.com.au/wp-content/uploads/2026/07/02_MLX_Quarterly-Report_30-June-2026_Final.pdf#page=2","rationale":"All imputed price/costs reported in AUD; identity conversion.","author":"Agent-authored public example; reported source or explicit assumption as described"},"/scenarios/bull/years/2/unit_cost":{"unit":"AUD/tonne","source":"https://www.metalsx.com.au/wp-content/uploads/2026/07/02_MLX_Quarterly-Report_30-June-2026_Final.pdf#page=2","rationale":"(TTM C 1 19,349 + imputed sales/marketing 8,089) ×0.95; includes royalties/payable deductions. Assumed future run-rate, not guidance.","author":"Agent-authored public example; reported source or explicit assumption as described"},"/scenarios/bull/years/2/royalty_rate":{"unit":"fraction","source":"https://www.metalsx.com.au/wp-content/uploads/2026/07/02_MLX_Quarterly-Report_30-June-2026_Final.pdf#page=3","rationale":"Royalties already inside imputed sales/marketing; zero additional charge avoids double counting.","author":"Agent-authored public example; reported source or explicit assumption as described"},"/scenarios/bull/years/2/tax_rate":{"unit":"fraction","source":"analyst-assumption://simplified-tax","rationale":"Assume 30% tax on positive cash-based EBIT; no depreciation shields/losses. Not a verified fiscal forecast.","author":"Agent-authored public example; reported source or explicit assumption as described"},"/scenarios/bull/years/2/depreciation":{"unit":"AUD","source":"analyst-assumption://no-tax-depreciation","rationale":"Assume no depreciation tax shield; uncertain taxable bases need reconciliation.","author":"Agent-authored public example; reported source or explicit assumption as described"},"/scenarios/bull/years/2/capex":{"unit":"AUD","source":"https://www.metalsx.com.au/wp-content/uploads/2026/07/02_MLX_Quarterly-Report_30-June-2026_Final.pdf#page=3","rationale":"Annualize total whole-operation quarterly 23.4m ×4, includes sustaining and project spend; illustrative, no AISC double deduction.","author":"Agent-authored public example; reported source or explicit assumption as described"},"/scenarios/bull/years/2/working_capital_change":{"unit":"AUD","source":"analyst-assumption://flat-working-capital","rationale":"Assume zero annual change solely for sensitivity; inventory/receivables timing is not established.","author":"Agent-authored public example; reported source or explicit assumption as described"},"/scenarios/bull/years/2/closure":{"unit":"AUD","source":"analyst-assumption://nominal-closure","rationale":"Assume nominal whole-operation 100m at final model year; zero earlier payments assumed. Not the reported discounted accounting provision.","author":"Agent-authored public example; reported source or explicit assumption as described"},"/scenarios/bull/years/2/corporate_cost":{"unit":"AUD","source":"https://www.metalsx.com.au/wp-content/uploads/2026/07/02_MLX_Quarterly-Report_30-June-2026_Final.pdf#page=8","rationale":"Annualized group quarterly 0.56m ×4; deducted after ownership scaling, not scaled again.","author":"Agent-authored public example; reported source or explicit assumption as described"},"/scenarios/bull/years/3/payable_tonnes":{"unit":"tonnes","source":"https://www.metalsx.com.au/wp-content/uploads/2026/07/02_MLX_Quarterly-Report_30-June-2026_Final.pdf#page=2","rationale":"TTM produced 11,287t ×1.1; IMPUTED PRODUCTION PROXY only, not payable sales. Gross imputed revenue includes 100% produced and marketing cost deducts payable tin charges.","author":"Agent-authored public example; reported source or explicit assumption as described"},"/scenarios/bull/years/3/price":{"unit":"AUD/tonne","source":"https://www.metalsx.com.au/wp-content/uploads/2026/07/02_MLX_Quarterly-Report_30-June-2026_Final.pdf#page=2","rationale":"TTM LME-imputed AUD 63,760/t ×1.2; not realized price, no claim of forecast guidance.","author":"Agent-authored public example; reported source or explicit assumption as described"},"/scenarios/bull/years/3/fx":{"unit":"AUD/AUD","source":"https://www.metalsx.com.au/wp-content/uploads/2026/07/02_MLX_Quarterly-Report_30-June-2026_Final.pdf#page=2","rationale":"All imputed price/costs reported in AUD; identity conversion.","author":"Agent-authored public example; reported source or explicit assumption as described"},"/scenarios/bull/years/3/unit_cost":{"unit":"AUD/tonne","source":"https://www.metalsx.com.au/wp-content/uploads/2026/07/02_MLX_Quarterly-Report_30-June-2026_Final.pdf#page=2","rationale":"(TTM C 1 19,349 + imputed sales/marketing 8,089) ×0.95; includes royalties/payable deductions. Assumed future run-rate, not guidance.","author":"Agent-authored public example; reported source or explicit assumption as described"},"/scenarios/bull/years/3/royalty_rate":{"unit":"fraction","source":"https://www.metalsx.com.au/wp-content/uploads/2026/07/02_MLX_Quarterly-Report_30-June-2026_Final.pdf#page=3","rationale":"Royalties already inside imputed sales/marketing; zero additional charge avoids double counting.","author":"Agent-authored public example; reported source or explicit assumption as described"},"/scenarios/bull/years/3/tax_rate":{"unit":"fraction","source":"analyst-assumption://simplified-tax","rationale":"Assume 30% tax on positive cash-based EBIT; no depreciation shields/losses. Not a verified fiscal forecast.","author":"Agent-authored public example; reported source or explicit assumption as described"},"/scenarios/bull/years/3/depreciation":{"unit":"AUD","source":"analyst-assumption://no-tax-depreciation","rationale":"Assume no depreciation tax shield; uncertain taxable bases need reconciliation.","author":"Agent-authored public example; reported source or explicit assumption as described"},"/scenarios/bull/years/3/capex":{"unit":"AUD","source":"https://www.metalsx.com.au/wp-content/uploads/2026/07/02_MLX_Quarterly-Report_30-June-2026_Final.pdf#page=3","rationale":"Annualize total whole-operation quarterly 23.4m ×4, includes sustaining and project spend; illustrative, no AISC double deduction.","author":"Agent-authored public example; reported source or explicit assumption as described"},"/scenarios/bull/years/3/working_capital_change":{"unit":"AUD","source":"analyst-assumption://flat-working-capital","rationale":"Assume zero annual change solely for sensitivity; inventory/receivables timing is not established.","author":"Agent-authored public example; reported source or explicit assumption as described"},"/scenarios/bull/years/3/closure":{"unit":"AUD","source":"analyst-assumption://nominal-closure","rationale":"Assume nominal whole-operation 100m at final model year; zero earlier payments assumed. Not the reported discounted accounting provision.","author":"Agent-authored public example; reported source or explicit assumption as described"},"/scenarios/bull/years/3/corporate_cost":{"unit":"AUD","source":"https://www.metalsx.com.au/wp-content/uploads/2026/07/02_MLX_Quarterly-Report_30-June-2026_Final.pdf#page=8","rationale":"Annualized group quarterly 0.56m ×4; deducted after ownership scaling, not scaled again.","author":"Agent-authored public example; reported source or explicit assumption as described"},"/scenarios/bull/years/4/payable_tonnes":{"unit":"tonnes","source":"https://www.metalsx.com.au/wp-content/uploads/2026/07/02_MLX_Quarterly-Report_30-June-2026_Final.pdf#page=2","rationale":"TTM produced 11,287t ×1.1; IMPUTED PRODUCTION PROXY only, not payable sales. Gross imputed revenue includes 100% produced and marketing cost deducts payable tin charges.","author":"Agent-authored public example; reported source or explicit assumption as described"},"/scenarios/bull/years/4/price":{"unit":"AUD/tonne","source":"https://www.metalsx.com.au/wp-content/uploads/2026/07/02_MLX_Quarterly-Report_30-June-2026_Final.pdf#page=2","rationale":"TTM LME-imputed AUD 63,760/t ×1.2; not realized price, no claim of forecast guidance.","author":"Agent-authored public example; reported source or explicit assumption as described"},"/scenarios/bull/years/4/fx":{"unit":"AUD/AUD","source":"https://www.metalsx.com.au/wp-content/uploads/2026/07/02_MLX_Quarterly-Report_30-June-2026_Final.pdf#page=2","rationale":"All imputed price/costs reported in AUD; identity conversion.","author":"Agent-authored public example; reported source or explicit assumption as described"},"/scenarios/bull/years/4/unit_cost":{"unit":"AUD/tonne","source":"https://www.metalsx.com.au/wp-content/uploads/2026/07/02_MLX_Quarterly-Report_30-June-2026_Final.pdf#page=2","rationale":"(TTM C 1 19,349 + imputed sales/marketing 8,089) ×0.95; includes royalties/payable deductions. Assumed future run-rate, not guidance.","author":"Agent-authored public example; reported source or explicit assumption as described"},"/scenarios/bull/years/4/royalty_rate":{"unit":"fraction","source":"https://www.metalsx.com.au/wp-content/uploads/2026/07/02_MLX_Quarterly-Report_30-June-2026_Final.pdf#page=3","rationale":"Royalties already inside imputed sales/marketing; zero additional charge avoids double counting.","author":"Agent-authored public example; reported source or explicit assumption as described"},"/scenarios/bull/years/4/tax_rate":{"unit":"fraction","source":"analyst-assumption://simplified-tax","rationale":"Assume 30% tax on positive cash-based EBIT; no depreciation shields/losses. Not a verified fiscal forecast.","author":"Agent-authored public example; reported source or explicit assumption as described"},"/scenarios/bull/years/4/depreciation":{"unit":"AUD","source":"analyst-assumption://no-tax-depreciation","rationale":"Assume no depreciation tax shield; uncertain taxable bases need reconciliation.","author":"Agent-authored public example; reported source or explicit assumption as described"},"/scenarios/bull/years/4/capex":{"unit":"AUD","source":"https://www.metalsx.com.au/wp-content/uploads/2026/07/02_MLX_Quarterly-Report_30-June-2026_Final.pdf#page=3","rationale":"Annualize total whole-operation quarterly 23.4m ×4, includes sustaining and project spend; illustrative, no AISC double deduction.","author":"Agent-authored public example; reported source or explicit assumption as described"},"/scenarios/bull/years/4/working_capital_change":{"unit":"AUD","source":"analyst-assumption://flat-working-capital","rationale":"Assume zero annual change solely for sensitivity; inventory/receivables timing is not established.","author":"Agent-authored public example; reported source or explicit assumption as described"},"/scenarios/bull/years/4/closure":{"unit":"AUD","source":"analyst-assumption://nominal-closure","rationale":"Assume nominal whole-operation 100m at final model year; zero earlier payments assumed. Not the reported discounted accounting provision.","author":"Agent-authored public example; reported source or explicit assumption as described"},"/scenarios/bull/years/4/corporate_cost":{"unit":"AUD","source":"https://www.metalsx.com.au/wp-content/uploads/2026/07/02_MLX_Quarterly-Report_30-June-2026_Final.pdf#page=8","rationale":"Annualized group quarterly 0.56m ×4; deducted after ownership scaling, not scaled again.","author":"Agent-authored public example; reported source or explicit assumption as described"},"/scenarios/bull/years/5/payable_tonnes":{"unit":"tonnes","source":"https://www.metalsx.com.au/wp-content/uploads/2026/07/02_MLX_Quarterly-Report_30-June-2026_Final.pdf#page=2","rationale":"TTM produced 11,287t ×1.1; IMPUTED PRODUCTION PROXY only, not payable sales. Gross imputed revenue includes 100% produced and marketing cost deducts payable tin charges.","author":"Agent-authored public example; reported source or explicit assumption as described"},"/scenarios/bull/years/5/price":{"unit":"AUD/tonne","source":"https://www.metalsx.com.au/wp-content/uploads/2026/07/02_MLX_Quarterly-Report_30-June-2026_Final.pdf#page=2","rationale":"TTM LME-imputed AUD 63,760/t ×1.2; not realized price, no claim of forecast guidance.","author":"Agent-authored public example; reported source or explicit assumption as described"},"/scenarios/bull/years/5/fx":{"unit":"AUD/AUD","source":"https://www.metalsx.com.au/wp-content/uploads/2026/07/02_MLX_Quarterly-Report_30-June-2026_Final.pdf#page=2","rationale":"All imputed price/costs reported in AUD; identity conversion.","author":"Agent-authored public example; reported source or explicit assumption as described"},"/scenarios/bull/years/5/unit_cost":{"unit":"AUD/tonne","source":"https://www.metalsx.com.au/wp-content/uploads/2026/07/02_MLX_Quarterly-Report_30-June-2026_Final.pdf#page=2","rationale":"(TTM C 1 19,349 + imputed sales/marketing 8,089) ×0.95; includes royalties/payable deductions. Assumed future run-rate, not guidance.","author":"Agent-authored public example; reported source or explicit assumption as described"},"/scenarios/bull/years/5/royalty_rate":{"unit":"fraction","source":"https://www.metalsx.com.au/wp-content/uploads/2026/07/02_MLX_Quarterly-Report_30-June-2026_Final.pdf#page=3","rationale":"Royalties already inside imputed sales/marketing; zero additional charge avoids double counting.","author":"Agent-authored public example; reported source or explicit assumption as described"},"/scenarios/bull/years/5/tax_rate":{"unit":"fraction","source":"analyst-assumption://simplified-tax","rationale":"Assume 30% tax on positive cash-based EBIT; no depreciation shields/losses. Not a verified fiscal forecast.","author":"Agent-authored public example; reported source or explicit assumption as described"},"/scenarios/bull/years/5/depreciation":{"unit":"AUD","source":"analyst-assumption://no-tax-depreciation","rationale":"Assume no depreciation tax shield; uncertain taxable bases need reconciliation.","author":"Agent-authored public example; reported source or explicit assumption as described"},"/scenarios/bull/years/5/capex":{"unit":"AUD","source":"https://www.metalsx.com.au/wp-content/uploads/2026/07/02_MLX_Quarterly-Report_30-June-2026_Final.pdf#page=3","rationale":"Annualize total whole-operation quarterly 23.4m ×4, includes sustaining and project spend; illustrative, no AISC double deduction.","author":"Agent-authored public example; reported source or explicit assumption as described"},"/scenarios/bull/years/5/working_capital_change":{"unit":"AUD","source":"analyst-assumption://flat-working-capital","rationale":"Assume zero annual change solely for sensitivity; inventory/receivables timing is not established.","author":"Agent-authored public example; reported source or explicit assumption as described"},"/scenarios/bull/years/5/closure":{"unit":"AUD","source":"analyst-assumption://nominal-closure","rationale":"Assume nominal whole-operation 100m at final model year; zero earlier payments assumed. Not the reported discounted accounting provision.","author
A5: ":"Agent-authored public example; reported source or explicit assumption as described"},"/scenarios/bull/years/5/corporate_cost":{"unit":"AUD","source":"https://www.metalsx.com.au/wp-content/uploads/2026/07/02_MLX_Quarterly-Report_30-June-2026_Final.pdf#page=8","rationale":"Annualized group quarterly 0.56m ×4; deducted after ownership scaling, not scaled again.","author":"Agent-authored public example; reported source or explicit assumption as described"},"/scenarios/bull/years/6/payable_tonnes":{"unit":"tonnes","source":"https://www.metalsx.com.au/wp-content/uploads/2026/07/02_MLX_Quarterly-Report_30-June-2026_Final.pdf#page=2","rationale":"TTM produced 11,287t ×1.1; IMPUTED PRODUCTION PROXY only, not payable sales. Gross imputed revenue includes 100% produced and marketing cost deducts payable tin charges.","author":"Agent-authored public example; reported source or explicit assumption as described"},"/scenarios/bull/years/6/price":{"unit":"AUD/tonne","source":"https://www.metalsx.com.au/wp-content/uploads/2026/07/02_MLX_Quarterly-Report_30-June-2026_Final.pdf#page=2","rationale":"TTM LME-imputed AUD 63,760/t ×1.2; not realized price, no claim of forecast guidance.","author":"Agent-authored public example; reported source or explicit assumption as described"},"/scenarios/bull/years/6/fx":{"unit":"AUD/AUD","source":"https://www.metalsx.com.au/wp-content/uploads/2026/07/02_MLX_Quarterly-Report_30-June-2026_Final.pdf#page=2","rationale":"All imputed price/costs reported in AUD; identity conversion.","author":"Agent-authored public example; reported source or explicit assumption as described"},"/scenarios/bull/years/6/unit_cost":{"unit":"AUD/tonne","source":"https://www.metalsx.com.au/wp-content/uploads/2026/07/02_MLX_Quarterly-Report_30-June-2026_Final.pdf#page=2","rationale":"(TTM C 1 19,349 + imputed sales/marketing 8,089) ×0.95; includes royalties/payable deductions. Assumed future run-rate, not guidance.","author":"Agent-authored public example; reported source or explicit assumption as described"},"/scenarios/bull/years/6/royalty_rate":{"unit":"fraction","source":"https://www.metalsx.com.au/wp-content/uploads/2026/07/02_MLX_Quarterly-Report_30-June-2026_Final.pdf#page=3","rationale":"Royalties already inside imputed sales/marketing; zero additional charge avoids double counting.","author":"Agent-authored public example; reported source or explicit assumption as described"},"/scenarios/bull/years/6/tax_rate":{"unit":"fraction","source":"analyst-assumption://simplified-tax","rationale":"Assume 30% tax on positive cash-based EBIT; no depreciation shields/losses. Not a verified fiscal forecast.","author":"Agent-authored public example; reported source or explicit assumption as described"},"/scenarios/bull/years/6/depreciation":{"unit":"AUD","source":"analyst-assumption://no-tax-depreciation","rationale":"Assume no depreciation tax shield; uncertain taxable bases need reconciliation.","author":"Agent-authored public example; reported source or explicit assumption as described"},"/scenarios/bull/years/6/capex":{"unit":"AUD","source":"https://www.metalsx.com.au/wp-content/uploads/2026/07/02_MLX_Quarterly-Report_30-June-2026_Final.pdf#page=3","rationale":"Annualize total whole-operation quarterly 23.4m ×4, includes sustaining and project spend; illustrative, no AISC double deduction.","author":"Agent-authored public example; reported source or explicit assumption as described"},"/scenarios/bull/years/6/working_capital_change":{"unit":"AUD","source":"analyst-assumption://flat-working-capital","rationale":"Assume zero annual change solely for sensitivity; inventory/receivables timing is not established.","author":"Agent-authored public example; reported source or explicit assumption as described"},"/scenarios/bull/years/6/closure":{"unit":"AUD","source":"analyst-assumption://nominal-closure","rationale":"Assume nominal whole-operation 100m at final model year; zero earlier payments assumed. Not the reported discounted accounting provision.","author":"Agent-authored public example; reported source or explicit assumption as described"},"/scenarios/bull/years/6/corporate_cost":{"unit":"AUD","source":"https://www.metalsx.com.au/wp-content/uploads/2026/07/02_MLX_Quarterly-Report_30-June-2026_Final.pdf#page=8","rationale":"Annualized group quarterly 0.56m ×4; deducted after ownership scaling, not scaled again.","author":"Agent-authored public example; reported source or explicit assumption as described"}},"known_limitations":["ILLUSTRATIVE IMPUTED-REVENUE SENSITIVITY ONLY. This is not an actionable fair-value estimate or an investment recommendation.","Production is used solely as the company-style imputed-revenue proxy (100% produced tin sold/paid); it is NOT reported payable sales. The workbook labels it production_tonnes_proxy. Realized payable sales, inventory, settlement timing and revenue must replace this proxy before valuation.","The baseline price AUD63,760/t is the reported trailing-12-month LME-imputed price, NOT realized tin sales price. Scenario price and volume levels are analyst stress assumptions, not company guidance.","Unit cost combines reported trailing-12-month C1 AUD19,349/t and imputed sales/marketing AUD8,089/t. Marketing includes royalties and payable-tin deductions, so separate royalty_rate=0 prevents duplicate deductions. Price-linked marketing behavior is not separately modelled and could materially affect sensitivity.","Finite horizons 3/5/7 years are illustrative assumptions, not reserve-supported mine life. The quarterly report said an updated life-of-mine plan and Ore Reserve were expected in Q3 2026; those updates have not been verified. No perpetuity or residual value is included.","Cash AUD374m is as at June 30 2026; debt AUD3.285m and issued shares886,391,538 are as at December31 2025. These stale mixed-date balances need updated half-year/ASX checks. Issued shares are a proxy, NOT a verified current fully diluted denominator.","Closure is an explicit assumed AUD100m whole-operation nominal final-year payment. The reported AUD33.035m group rehabilitation provision is a present-value accounting figure, not this cash-payment estimate; actual scope/timing and other closure sites remain unmodelled.","Capex annualizes June-quarter whole-operation AUD23.4m to AUD93.6m each model year, including both sustaining and project spend. This is a scenario assumption, not guidance. No additional AISC deduction is made.","Annual corporate costs annualize group June-quarter AUD0.56m to AUD2.24m, deducted once after 50% attribution. Other investments/residual assets are set to zero only to exclude them from this limited sensitivity, not because they have zero economic value.","Tax rate30% is an analyst simplifying assumption; depreciation is assumed zero and no loss carryforwards, corporate tax shields or closure deductions are modelled. No forecast working-capital changes are assumed; this is not verified operational guidance.","Annual row labels2027 onward denote period-end annualized flows one/two/etc years from the valuation date, not an audited fiscal calendar projection. No remaining2026 stub cash flow is forecast. Forecast years are constant run-rate proxies.","No verified current share quote is supplied. Reverse valuation and price/upside comparisons are unavailable. No actual user portfolio is used.","Historical statement summaries now include FY2025 and FY2024 as reported in the 2025 annual report. This is a selected comparative history, not a full three-year normalization or a linked three-statement forecast. Group consolidated actuals must not be compared directly with unscaled whole-operation model rows."],"notes":"Public worked example. Reported historical figures are transcribed from issuer documents; future inputs are agent-authored illustrative assumptions, not management guidance. See MLX-MODEL-NOTES.md for source-page mapping, sign conventions and reconciliation checks."},"inputs":{"/cash":{"sheet":"Assumptions","cell":"B7"},"/debt":{"sheet":"Assumptions","cell":"B8"},"/other_assets":{"sheet":"Assumptions","cell":"B9"},"/diluted_shares":{"sheet":"Assumptions","cell":"B10"},"/reference_price":{"sheet":"Assumptions","cell":"B11"},"/valuation_date":{"sheet":"Assumptions","cell":"B12"},"/quote_date":{"sheet":"Assumptions","cell":"B13"},"/scenarios/bear/discount_rate":{"sheet":"Assumptions","cell":"B20"},"/scenarios/bear/ownership":{"sheet":"Assumptions","cell":"B21"},"/scenarios/bear/residual_value":{"sheet":"Assumptions","cell":"B22"},"/scenarios/bear/years/0/payable_tonnes":{"sheet":"Assumptions","cell":"C25"},"/scenarios/bear/years/1/payable_tonnes":{"sheet":"Assumptions","cell":"D25"},"/scenarios/bear/years/2/payable_tonnes":{"sheet":"Assumptions","cell":"E25"},"/scenarios/bear/years/0/price":{"sheet":"Assumptions","cell":"C26"},"/scenarios/bear/years/1/price":{"sheet":"Assumptions","cell":"D26"},"/scenarios/bear/years/2/price":{"sheet":"Assumptions","cell":"E26"},"/scenarios/bear/years/0/fx":{"sheet":"Assumptions","cell":"C27"},"/scenarios/bear/years/1/fx":{"sheet":"Assumptions","cell":"D27"},"/scenarios/bear/years/2/fx":{"sheet":"Assumptions","cell":"E27"},"/scenarios/bear/years/0/unit_cost":{"sheet":"Assumptions","cell":"C28"},"/scenarios/bear/years/1/unit_cost":{"sheet":"Assumptions","cell":"D28"},"/scenarios/bear/years/2/unit_cost":{"sheet":"Assumptions","cell":"E28"},"/scenarios/bear/years/0/royalty_rate":{"sheet":"Assumptions","cell":"C29"},"/scenarios/bear/years/1/royalty_rate":{"sheet":"Assumptions","cell":"D29"},"/scenarios/bear/years/2/royalty_rate":{"sheet":"Assumptions","cell":"E29"},"/scenarios/bear/years/0/tax_rate":{"sheet":"Assumptions","cell":"C30"},"/scenarios/bear/years/1/tax_rate":{"sheet":"Assumptions","cell":"D30"},"/scenarios/bear/years/2/tax_rate":{"sheet":"Assumptions","cell":"E30"},"/scenarios/bear/years/0/depreciation":{"sheet":"Assumptions","cell":"C31"},"/scenarios/bear/years/1/depreciation":{"sheet":"Assumptions","cell":"D31"},"/scenarios/bear/years/2/depreciation":{"sheet":"Assumptions","cell":"E31"},"/scenarios/bear/years/0/capex":{"sheet":"Assumptions","cell":"C32"},"/scenarios/bear/years/1/capex":{"sheet":"Assumptions","cell":"D32"},"/scenarios/bear/years/2/capex":{"sheet":"Assumptions","cell":"E32"},"/scenarios/bear/years/0/working_capital_change":{"sheet":"Assumptions","cell":"C33"},"/scenarios/bear/years/1/working_capital_change":{"sheet":"Assumptions","cell":"D33"},"/scenarios/bear/years/2/working_capital_change":{"sheet":"Assumptions","cell":"E33"},"/scenarios/bear/years/0/closure":{"sheet":"Assumptions","cell":"C34"},"/scenarios/bear/years/1/closure":{"sheet":"Assumptions","cell":"D34"},"/scenarios/bear/years/2/closure":{"sheet":"Assumptions","cell":"E34"},"/scenarios/bear/years/0/corporate_cost":{"sheet":"Assumptions","cell":"C35"},"/scenarios/bear/years/1/corporate_cost":{"sheet":"Assumptions","cell":"D35"},"/scenarios/bear/years/2/corporate_cost":{"sheet":"Assumptions","cell":"E35"},"/scenarios/base/discount_rate":{"sheet":"Assumptions","cell":"B39"},"/scenarios/base/ownership":{"sheet":"Assumptions","cell":"B40"},"/scenarios/base/residual_value":{"sheet":"Assumptions","cell":"B41"},"/scenarios/base/years/0/payable_tonnes":{"sheet":"Assumptions","cell":"C44"},"/scenarios/base/years/1/payable_tonnes":{"sheet":"Assumptions","cell":"D44"},"/scenarios/base/years/2/payable_tonnes":{"sheet":"Assumptions","cell":"E44"},"/scenarios/base/years/3/payable_tonnes":{"sheet":"Assumptions","cell":"F44"},"/scenarios/base/years/4/payable_tonnes":{"sheet":"Assumptions","cell":"G44"},"/scenarios/base/years/0/price":{"sheet":"Assumptions","cell":"C45"},"/scenarios/base/years/1/price":{"sheet":"Assumptions","cell":"D45"},"/scenarios/base/years/2/price":{"sheet":"Assumptions","cell":"E45"},"/scenarios/base/years/3/price":{"sheet":"Assumptions","cell":"F45"},"/scenarios/base/years/4/price":{"sheet":"Assumptions","cell":"G45"},"/scenarios/base/years/0/fx":{"sheet":"Assumptions","cell":"C46"},"/scenarios/base/years/1/fx":{"sheet":"Assumptions","cell":"D46"},"/scenarios/base/years/2/fx":{"sheet":"Assumptions","cell":"E46"},"/scenarios/base/years/3/fx":{"sheet":"Assumptions","cell":"F46"},"/scenarios/base/years/4/fx":{"sheet":"Assumptions","cell":"G46"},"/scenarios/base/years/0/unit_cost":{"sheet":"Assumptions","cell":"C47"},"/scenarios/base/years/1/unit_cost":{"sheet":"Assumptions","cell":"D47"},"/scenarios/base/years/2/unit_cost":{"sheet":"Assumptions","cell":"E47"},"/scenarios/base/years/3/unit_cost":{"sheet":"Assumptions","cell":"F47"},"/scenarios/base/years/4/unit_cost":{"sheet":"Assumptions","cell":"G47"},"/scenarios/base/years/0/royalty_rate":{"sheet":"Assumptions","cell":"C48"},"/scenarios/base/years/1/royalty_rate":{"sheet":"Assumptions","cell":"D48"},"/scenarios/base/years/2/royalty_rate":{"sheet":"Assumptions","cell":"E48"},"/scenarios/base/years/3/royalty_rate":{"sheet":"Assumptions","cell":"F48"},"/scenarios/base/years/4/royalty_rate":{"sheet":"Assumptions","cell":"G48"},"/scenarios/base/years/0/tax_rate":{"sheet":"Assumptions","cell":"C49"},"/scenarios/base/years/1/tax_rate":{"sheet":"Assumptions","cell":"D49"},"/scenarios/base/years/2/tax_rate":{"sheet":"Assumptions","cell":"E49"},"/scenarios/base/years/3/tax_rate":{"sheet":"Assumptions","cell":"F49"},"/scenarios/base/years/4/tax_rate":{"sheet":"Assumptions","cell":"G49"},"/scenarios/base/years/0/depreciation":{"sheet":"Assumptions","cell":"C50"},"/scenarios/base/years/1/depreciation":{"sheet":"Assumptions","cell":"D50"},"/scenarios/base/years/2/depreciation":{"sheet":"Assumptions","cell":"E50"},"/scenarios/base/years/3/depreciation":{"sheet":"Assumptions","cell":"F50"},"/scenarios/base/years/4/depreciation":{"sheet":"Assumptions","cell":"G50"},"/scenarios/base/years/0/capex":{"sheet":"Assumptions","cell":"C51"},"/scenarios/base/years/1/capex":{"sheet":"Assumptions","cell":"D51"},"/scenarios/base/years/2/capex":{"sheet":"Assumptions","cell":"E51"},"/scenarios/base/years/3/capex":{"sheet":"Assumptions","cell":"F51"},"/scenarios/base/years/4/capex":{"sheet":"Assumptions","cell":"G51"},"/scenarios/base/years/0/working_capital_change":{"sheet":"Assumptions","cell":"C52"},"/scenarios/base/years/1/working_capital_change":{"sheet":"Assumptions","cell":"D52"},"/scenarios/base/years/2/working_capital_change":{"sheet":"Assumptions","cell":"E52"},"/scenarios/base/years/3/working_capital_change":{"sheet":"Assumptions","cell":"F52"},"/scenarios/base/years/4/working_capital_change":{"sheet":"Assumptions","cell":"G52"},"/scenarios/base/years/0/closure":{"sheet":"Assumptions","cell":"C53"},"/scenarios/base/years/1/closure":{"sheet":"Assumptions","cell":"D53"},"/scenarios/base/years/2/closure":{"sheet":"Assumptions","cell":"E53"},"/scenarios/base/years/3/closure":{"sheet":"Assumptions","cell":"F53"},"/scenarios/base/years/4/closure":{"sheet":"Assumptions","cell":"G53"},"/scenarios/base/years/0/corporate_cost":{"sheet":"Assumptions","cell":"C54"},"/scenarios/base/years/1/corporate_cost":{"sheet":"Assumptions","cell":"D54"},"/scenarios/base/years/2/corporate_cost":{"sheet":"Assumptions","cell":"E54"},"/scenarios/base/years/3/corporate_cost":{"sheet":"Assumptions","cell":"F54"},"/scenarios/base/years/4/corporate_cost":{"sheet":"Assumptions","cell":"G54"},"/scenarios/bull/discount_rate":{"sheet":"Assumptions","cell":"B58"},"/scenarios/bull/ownership":{"sheet":"Assumptions","cell":"B59"},"/scenarios/bull/residual_value":{"sheet":"Assumptions","cell":"B60"},"/scenarios/bull/years/0/payable_tonnes":{"sheet":"Assumptions","cell":"C63"},"/scenarios/bull/years/1/payable_tonnes":{"sheet":"Assumptions","cell":"D63"},"/scenarios/bull/years/2/payable_tonnes":{"sheet":"Assumptions","cell":"E63"},"/scenarios/bull/years/3/payable_tonnes":{"sheet":"Assumptions","cell":"F63"},"/scenarios/bull/years/4/payable_tonnes":{"sheet":"Assumptions","cell":"G63"},"/scenarios/bull/years/5/payable_tonnes":{"sheet":"Assumptions","cell":"H63"},"/scenarios/bull/years/6/payable_tonnes":{"sheet":"Assumptions","cell":"I63"},"/scenarios/bull/years/0/price":{"sheet":"Assumptions","cell":"C64"},"/scenarios/bull/years/1/price":{"sheet":"Assumptions","cell":"D64"},"/scenarios/bull/years/2/price":{"sheet":"Assumptions","cell":"E64"},"/scenarios/bull/years/3/price":{"sheet":"Assumptions","cell":"F64"},"/scenarios/bull/years/4/price":{"sheet":"Assumptions","cell":"G64"},"/scenarios/bull/years/5/price":{"sheet":"Assumptions","cell":"H64"},"/scenarios/bull/years/6/price":{"sheet":"Assumptions","cell":"I64"},"/scenarios/bull/years/0/fx":{"sheet":"Assumptions","cell":"C65"},"/scenarios/bull/years/1/fx":{"sheet":"Assumptions","cell":"D65"},"/scenarios/bull/years/2/fx":{"sheet":"Assumptions","cell":"E65"},"/scenarios/bull/years/3/fx":{"sheet":"Assumptions","cell":"F65"},"/scenarios/bull/years/4/fx":{"sheet":"Assumptions","cell":"G65"},"/scenarios/bull/years/5/fx":{"sheet":"Assumptions","cell":"H65"},"/scenarios/bull/years/6/fx":{"sheet":"Assumptions","cell":"I65"},"/scenarios/bull/years/0/unit_cost":{"sheet":"Assumptions","cell":"C66"},"/scenarios/bull/years/1/unit_cost":{"sheet":"Assumptions","cell":"D66"},"/scenarios/bull/years/2/unit_cost":{"sheet":"Assumptions","cell":"E66"},"/scenarios/bull/years/3/unit_cost":{"sheet":"Assumptions","cell":"F66"},"/scenarios/bull/years/4/unit_cost":{"sheet":"Assumptions","cell":"G66"},"/scenarios/bull/years/5/unit_cost":{"sheet":"Assumptions","cell":"H66"},"/scenarios/bull/years/6/unit_cost":{"sheet":"Assumptions","cell":"I66"},"/scenarios/bull/years/0/royalty_rate":{"sheet":"Assumptions","cell":"C67"},"/scenarios/bull/years/1/royalty_rate":{"sheet":"Assumptions","cell":"D67"},"/scenarios/bull/years/2/royalty_rate":{"sheet":"Assumptions","cell":"E67"},"/scenarios/bull/years/3/royalty_rate":{"sheet":"Assumptions","cell":"F67"},"/scenarios/bull/years/4/royalty_rate":{"sheet":"Assumptions","cell":"G67"},"/scenarios/bull/years/5/royalty_rate":{"sheet":"Assumptions","cell":"H67"},"/scenarios/bull/years/6/royalty_rate":{"sheet":"Assumptions","cell":"I67"},"/scenarios/bull/years/0/tax_rate":{"sheet":"Assumptions","cell":"C68"},"/scenarios/bull/years/1/tax_rate":{"sheet":"Assumptions","cell":"D68"},"/scenarios/bull/years/2/tax_rate":{"sheet":"Assumptions","cell":"E68"},"/scenarios/bull/years/3/tax_rate":{"sheet":"Assumptions","cell":"F68"},"/scenarios/bull/years/4/tax_rate":{"sheet":"Assumptions","cell":"G68"},"/scenarios/bull/years/5/tax_rate":{"sheet":"Assumptions","cell":"H68"},"/scenarios/bull/years/6/tax_rate":{"sheet":"Assumptions","cell":"I68"},"/scenarios/bull/years/0/depreciation":{"sheet":"Assumptions","cell":"C69"},"/scenarios/bull/years/1/depreciation":{"sheet":"Assumptions","cell":"D69"},"/scenarios/bull/years/2/depreciation":{"sheet":"Assumptions","cell":"E69"},"/scenarios/bull/years/3/depreciation":{"sheet":"Assumptions","cell":"F69"},"/scenarios/bull/years/4/depreciation":{"sheet":"Assumptions","cell":"G69"},"/scenarios/bull/years/5/depreciation":{"sheet":"Assumptions","cell":"H69"},"/scenarios/bull/years/6/depreciation":{"sheet":"Assumptions","cell":"I69"},"/scenarios/bull/years/0/capex":{"sheet":"Assumptions","cell":"C70"},"/scenarios/bull/years/1/capex":{"sheet":"Assumptions","cell":"D70"},"/scenarios/bull/years/2/capex":{"sheet":"Assumptions","cell":"E70"},"/scenarios/bull/years/3/capex":{"sheet":"Assumptions","cell":"F70"},"/scenarios/bull/years/4/capex":{"sheet":"Assumptions","cell":"G70"},"/scenarios/bull/years/5/capex":{"sheet":"Assumptions","cell":"H70"},"/scenarios/bull/years/6/capex":{"sheet":"Assumptions","cell":"I70"},"/scenarios/bull/years/0/working_capital_change":{"sheet":"Assumptions","cell":"C71"},"/scenarios/bull/years/1/working_capital_change":{"sheet":"Assumptions","cell":"D71"},"/scenarios/bull/years/2/working_capital_change":{"sheet":"Assumptions","cell":"E71"},"/scenarios/bull/years/3/working_capital_change":{"sheet":"Assumptions","cell":"F71"},"/scenarios/bull/years/4/working_capital_change":{"sheet":"Assumptions","cell":"G71"},"/scenarios/bull/years/5/working_capital_change":{"sheet":"Assumptions","cell":"H71"},"/scenarios/bull/years/6/working_capital_change":{"sheet":"Assumptions","cell":"I71"},"/scenarios/bull/years/0/closure":{"sheet":"Assumptions","cell":"C72"},"/scenarios/bull/years/1/closure":{"sheet":"Assumptions","cell":"D72"},"/scenarios/bull/years/2/closure":{"sheet":"Assumptions","cell":"E72"},"/scenarios/bull/years/3/closure":{"sheet":"Assumptions","cell":"F72"},"/scenarios/bull/years/4/closure":{"sheet":"Assumptions","cell":"G72"},"/scenarios/bull/years/5/closure":{"sheet":"Assumptions","cell":"H72"},"/scenarios/bull/years/6/closure":{"sheet":"Assumptions","cell":"I72"},"/scenarios/bull/years/0/corporate_cost":{"sheet":"Assumptions","cell":"C73"},"/scenarios/bull/years/1/corporate_cost":{"sheet":"Assumptions","cell":"D73"},"/scenarios/bull/years/2/corporate_cost":{"sheet":"Assumptions","cell":"E73"},"/scenarios/bull/years/3/corporate_cost":{"sheet":"Assumptions","cell":"F73"},"/scenarios/bull/years/4/corporate_cost":{"sheet":"Assumptions","cell":"G73"},"/scenarios/bull/years/5/corporate_cost":{"sheet":"Assumptions","cell":"H73"},"/scenarios/bull/years/6/corporate_cost":{"sheet":"Assumptions","cell":"I73"}},"outputs":{"active_case":{"sheet":"Assumptions","cell":"B4"},"years/0/year":{"sheet":"Operating","cell":"C9"},"years/0/revenue":{"sheet":"Operating","cell":"C23"},"years/0/operating_cost":{"sheet":"Operating","cell":"C24"},"years/0/royalties":{"sheet":"Operating","cell":"C25"},"years/0/ebit":{"sheet":"Operating","cell":"C26"},"years/0/tax":{"sheet":"Operating","cell":"C27"},"years/0/nopat":{"sheet":"Operating","cell":"C28"},"years/0/operating_fcf":{"sheet":"Operating","cell":"C29"},"years/0/fcf":{"sheet":"Operating","cell":"C30"},"years/0/present_value":{"sheet":"Operating","cell":"C31"},"years/0/illustrative_cash":{"sheet":"Operating","cell":"C32"},"years/1/year":{"sheet":"Operating","cell":"D9"},"years/1/revenue":{"sheet":"Operating","cell":"D23"},"years/1/operating_cost":{"sheet":"Operating","cell":"D24"},"years/1/royalties":{"sheet":"Operating","cell":"D25"},"years/1/ebit":{"sheet":"Operating","cell":"D26"},"years/1/tax":{"sheet":"Operating","cell":"D27"},"years/1/nopat":{"sheet":"Operating","cell":"D28"},"years/1/operating_fcf":{"sheet":"Operating","cell":"D29"},"years/1/fcf":{"sheet":"Operating","cell":"D30"},"years/1/present_value":{"sheet":"Operating","cell":"D31"},"years/1/illustrative_cash":{"sheet":"Operating","cell":"D32"},"years/2/year":{"sheet":"Operating","cell":"E9"},"years/2/revenue":{"sheet":"Operating","cell":"E23"},"years/2/operating_cost":{"sheet":"Operating","cell":"E24"},"years/2/royalties":{"sheet":"Operating","cell":"E25"},"years/2/ebit":{"sheet":"Operating","cell":"E26"},"years/2/tax":{"sheet":"Operating","cell":"E27"},"years/2/nopat":{"sheet":"Operating","cell":"E28"},"years/2/operating_fcf":{"sheet":"Operating","cell":"E29"},"years/2/fcf":{"sheet":"Operating","cell":"E30"},"years/2/present_value":{"sheet":"Operating","cell":"E31"},"years/2/illustrative_cash":{"sheet":"Operating","cell":"E32"},"years/3/year":{"sheet":"Operating","cell":"F9"},"years/3/revenue":{"sheet":"Operating","cell":"F23"},"years/3/operating_cost":{"sheet":"Operating","cell":"F24"},"years/3/royalties":{"sheet":"Operating","cell":"F25"},"years/3/ebit":{"sheet":"Operating","cell":"F26"},"years/3/tax":{"sheet":"Operating","cell":"F27"},"years/3/nopat":{"sheet":"Operating","cell":"F28"},"years/3/operating_fcf":{"sheet":"Operating","cell":"F29"},"years/3/fcf":{"sheet":"Operating","cell":"F30"},"years/3/present_value":{"sheet":"Operating","cell":"F31"},"years/3/illustrative_cash":{"sheet":"Operating","cell":"F32"},"years/4/year":{"sheet":"Operating","cell":"G9"},"years/4/revenue":{"sheet":"Operating","cell":"G23"},"years/4/operating_cost":{"sheet":"Operating","cell":"G24"},"years/4/royalties":{"sheet":"Operating","cell":"G25"},"years/4/ebit":{"sheet":"Operating","cell":"G26"},"years/4/tax":{"sheet":"Operating","cell":"G27"},"years/4/nopat":{"sheet":"Operating","cell":"G28"},"years/4/operating_fcf":{"sheet":"Operating","cell":"G29"},"years/4/fcf":{"sheet":"Operating","cell":"G30"},"years/4/present_value":{"sheet":"Operating","cell":"G31"},"years/4/illustrative_cash":{"sheet":"Operating","cell":"G32"},"years/5/year":{"sheet":"Operating","cell":"H9"},"years/5/revenue":{"sheet":"Operating","cell":"H23"},"years/5/operating_cost":{"sheet":"Operating","cell":"H24"},"years/5/royalties":{"sheet":"Operating","cell":"H25"},"years/5/ebit":{"sheet":"Operating","cell":"H26"},"years/5/tax":{"sheet":"Operating","cell":"H27"},"years/5/nopat":{"sheet":"Operating","cell":"H28"},"years/5/operating_fcf":{"sheet":"Operating","cell":"H29"},"years/5/fcf":{"sheet":"Operating","cell":"H30"},"years/5/present_value":{"sheet":"Operating","cell":"H31"},"years/5/illustrative_cash":{"sheet":"Operating","cell":"H32"},"years/6/year":{"sheet":"Operating","cell":"I9"},"years/6/revenue":{"sheet":"Operating","cell":"I23"},"years/6/operating_cost":{"sheet":"Operating","cell":"I24"},"years/6/royalties":{"sheet":"Operating","cell":"I25"},"years/6/ebit":{"sheet":"Operating","cell":"I26"},"years/6/tax":{"sheet":"Operating","cell":"I27"},"years/6/nopat":{"sheet":"Operating","cell":"I28"},"years/6/operating_fcf":{"sheet":"Operating","cell":"I29"},"years/6/fcf":{"sheet":"Operating","cell":"I30"},"years/6/present_value":{"sheet":"Operating","cell":"I31"},"years/6/illustrative_cash":{"sheet":"Operating","cell":"I32"},"enterprise_value":{"sheet":"Valuation","cell":"B5"},"cash":{"sheet":"Valuation","cell":"B6"},"other_assets":{"sheet":"Valuation","cell":"B7"},"debt":{"sheet":"Valuation","cell":"B8"},"equity_value":{"sheet":"Valuation","cell":"B9"},"diluted_shares":{"sheet":"Valuation","cell":"B10"},"per_share":{"sheet":"Valuation","cell":"B11"},"minimum_illustrative_cash":{"sheet":"Valuation","cell":"B12"},"discount_rate/0":{"sheet":"Sensitivities","cell":"C7"},"discount_rate/1":{"sheet":"Sensitivities","cell":"D7"},"discount_rate/2":{"sheet":"Sensitivities","cell":"E7"},"driver_multiplier/0":{"sheet":"Sensitivities","cell":"B8"},"sensitivity/0/0":{"sheet":"Sensitivities","cell":"C8"},"sensitivity/0/1":{"sheet":"Sensitivities","cell":"D8"},"sensitivity/0/2":{"sheet":"Sensitivities","cell":"E8"},"driver_multiplier/1":{"sheet":"Sensitivities","cell":"B9"},"sensitivity/1/0":{"sheet":"Sensitivities","cell":"C9"},"sensitivity/1/1":{"sheet":"Sensitivities","cell":"D9"},"sensitivity/1/2":{"sheet":"Sensitivities","cell":"E9"},"driver_multiplier/2":{"sheet":"Sensitivities","cell":"B10"},"sensitivity/2/0":{"sheet":"Sensitivities","cell":"C10"},"sensitivity/2/1":{"sheet":"Sensitivities","cell":"D10"},"sensitivity/2/2":{"sheet":"Sensitivities","cell":"E10"},"checks/0":{"sheet":"Checks","cell":"B5"},"checks/1":{"sheet":"Checks","cell":"B6"},"checks/2":{"sheet":"Checks","cell":"B7"},"checks/3":{"sheet":"Checks","cell":"B8"},"checks/4":{"sheet":"Checks","cell":"B9"},"checks/5":{"sheet":"Checks","cell":"B10"}},"formula_cells":{"Operating!B4":"=IF(Assumptions!$B$4=\"bear\",'Assumptions'!$B$20,IF(Assumptions!$B$4=\"base\",'Assumptions'!$B$39,'Assumptions'!$B$58))","Operating!B5":"=IF(Assumptions!$B$4=\"bear\",'Assumptions'!$B$21,IF(Assumptions!$B$4=\"base\",'Assumptions'!$B$40,'Assumptions'!$B$59))","Operating!B6":"=IF(Assumptions!$B$4=\"bear\",'Assumptions'!$B$22,IF(Assumptions!$B$4=\"base\",'Assumptions'!$B$41,'Assumptions'!$B$60))","Operating!B7":"=IF(Assumptions!$B$4=\"bear\",'Assumptions'!$B$23,IF(Assumptions!$B$4=\"base\",'Assumptions'!$B$42,'Assumptions'!$B$61))","Operating!B8":"=IF(Assumptions!$B$4=\"bear\",\"imputed_production\",IF(Assumptions!$B$4=\"base\",\"imputed_production\",\"imputed_production\"))","Operating!C9":"=YEAR(DATEVALUE('Assumptions'!$B$12))+1","Operating!C10":"=IF(Assumptions!$B$4=\"bear\",'Assumptions'!$C$25,IF(Assumptions!$B$4=\"base\",'Assumptions'!$C$44,'Assumptions'!$C$63))","Operating!C11":"=IF(Assumptions!$B$4=\"bear\",'Assumptions'!$C$26,IF(Assumptions!$B$4=\"base\",'Assumptions'!$C$45,'Assumptions'!$C$64))","Operating!C12":"=IF(Assumptions!$B$4=\"bear\",'Assumptions'!$C$27,IF(Assumptions!$B$4=\"base\",'Assumptions'!$C$46,'Assumptions'!$C$65))","Operating!C13":"=IF(Assumptions!$B$4=\"bear\",'Assumptions'!$C$28,IF(Assumptions!$B$4=\"base\",'Assumptions'!$C$47,'Assumptions'!$C$66))","Operating!C14":"=IF(Assumptions!$B$4=\"bear\",'Assumptions'!$C$29,IF(Assumptions!$B$4=\"base\",'Assumptions'!$C$48,'Assumptions'!$C$67))","Operating!C15":"=IF(Assumptions!$B$4=\"bear\",'Assumptions'!$C$30,IF(Assumptions!$B$4=\"base\",'Assumptions'!$C$49,'Assumptions'!$C$68))","Operating!C16":"=IF(Assumptions!$B$4=\"bear\",'Assumptions'!$C$31,IF(Assumptions!$B$4=\"base\",'Assumptions'!$C$50,'Assumptions'!$C$69))","Operating!C17":"=IF(Assumptions!$B$4=\"bear\",'Assumptions'!$C$32,IF(Assumptions!$B$4=\"base\",'Assumptions'!$C$51,'Assumptions'!$C$70))","Operating!C18":"=IF(Assumptions!$B$4=\"bear\",'Assumptions'!$C$33,IF(Assumptions!$B$4=\"base\",'Assumptions'!$C$52,'Assumptions'!$C$71))","Operating!C19":"=IF(Assumptions!$B$4=\"bear\",'Assumptions'!$C$34,IF(Assumptions!$B$4=\"base\",'Assumptions'!$C$53,'Assumptions'!$C$72))","Operating!C20":"=IF(Assumptions!$B$4=\"bear\",'Assumptions'!$C$35,IF(Assumptions!$B$4=\"base\",'Assumptions'!$C$54,'Assumptions'!$C$73))","Operating!C23":"='Operating'!$C$10*'Operating'!$C$11*'Operating'!$C$12","Operating!C24":"='Operating'!$C$10*'Operating'!$C$13","Operating!C25":"='Operating'!$C$23*'Operating'!$C$14","Operating!C26":"='Operating'!$C$23-'Operating'!$C$24-'Operating'!$C$25-'Operating'!$C$16","Operating!C27":"=MAX(0,'Operating'!$C$26)*'Operating'!$C$15","Operating!C28":"='Operating'!$C$26-'Operating'!$C$27","Operating!C29":"='Operating'!$C$28+'Operating'!$C$16-'Operating'!$C$17-'Operating'!$C$18-'Operating'!$C$19","Operating!C30":"='Operating'!$C$29*'Operating'!$B$5-'Operating'!$C$20+IF(1='Operating'!$B$7,'Operating'!$B$6,0)","Operating!C31":"='Operating'!$C$30/(1+'Operating'!$B$4)^1","Operating!C32":"='Assumptions'!$B$7+'Operating'!$C$30","Operating!D9":"=YEAR(DATEVALUE('Assumptions'!$B$12))+2","Operating!D10":"=IF(Assumpt
